Workbook

Sheet AGENDA 
D3: Assunto | E3: Início | F3: Término | G3: Responsável
D5: Mensagem Presidente | E5: 0.375 | F5: 0.38194444 | G5: Rodrigo Demeterco
D6: Resumo EBITDA | E6: 0.38194444 | F6: 0.38541667 | G6: Thiago
D7: Resultados Demercado | E7: 0.38541667 | F7: 0.39236111 | G7: Thiago
D8: Resultados Matriz | E8: 0.39236111 | F8: 0.39930556 | G8: Thiago
D9: Indicadores Financeiros | E9: 0.39930556 | F9: 0.40625 | G9: Thiago
D10: Resultados Condomínios | E10: 0.40625 | F10: 0.42013889 | G10: Rodrigo Habitzreuter
D11: Marketing & IM | E11: 0.42013889 | F11: 0.43402778 | G11: Rodrigo Proença
D12: Engenharia | E12: 0.43402778 | F12: 0.44791667 | G12: Carlos Eduardo/Juliana
D13: Propriedades
D14: Recursos Humanos | E14: 0.44791667 | F14: 0.46180556 | G14: Patricia
D15: TI | E15: 0.46180556 | F15: 0.47569444 | G15: Juliano
D16: Jurídico | E16: 0.47569444 | F16: 0.48958333 | G16: Betina
D19: Assunto | E19: Início | F19: Término | G19: Responsável
D20: Meta Gerência Operações | E20: 0.375 | F20: 0.38194444 | G20: Sérgio
D21: Resultado Hangar Vip | E21: 0.38194444 | F21: 0.39930556 | G21: Sérgio
D22: Resultado Garoto | E22: 0.39930556 | F22: 0.41666667 | G22: Sérgio
D25: Assunto | E25: Início | F25: Término | G25: Responsável
D26: Mensagem Presidente | E26: 0.375 | F26: 0.38194444 | G26: Rodrigo Demeterco
D27: Resumo EBITDA | E27: 0.38194444 | F27: 0.38541667 | G27: Thiago
D28: Resultados Demercado | E28: 0.38541667 | F28: 0.39236111 | G28: Thiago
D29: Resultados Matriz | E29: 0.39236111 | F29: 0.39930556 | G29: Thiago
D30: Indicadores Financeiros | E30: 0.39930556 | F30: 0.40625 | G30: Thiago | J30: 0.40625
D31: Resultados Condomínios | E31: 0.40625 | F31: 0.42013889 | G31: Rodrigo Habitzreuter | J31: 0.42013889
D32: Marketing & IM | E32: 0.42013889 | F32: 0.43402778 | G32: Rodrigo Proença | J32: =J31-J30 -> 0.013888889
D33: Engenharia / Arquitetura | E33: 0.43402778 | F33: 0.44791667 | G33: Ricardo / Juliana
D34: Propriedades | E34: 0.41666667 | F34: 0.43055556 | G34: Cleverson
D35: Recursos Humanos | E35: 0.44791667 | F35: 0.46180556 | G35: Veridiana
D36: TI | E36: 0.46180556 | F36: 0.47569444 | G36: Juliano
D37: Jurídico | E37: 0.47569444 | F37: 0.48958333 | G37: Natália
D43: Assunto | E43: Início | F43: Término | G43: Responsável
D44: Relatório de Auditoria Independente | E44: 0.375 | F44: 0.39583333 | G44: Auditores
D45: Parecer do Conselho Fiscal sobre as DFs | E45: 0.39583333 | F45: 0.40625 | G45: Conselheiros
D46: Apresentação do andamento dos negócios da empresa acumulado Fev/23 | E46: 0.40625 | F46: 0.44791667 | G46: Thiago
D47: Considerações finais | E47: 0.44791667 | F47: 0.46875 | G47: Todos

Sheet Análise Semanal
A2: RITMO SEMANA ANTERIOR
A29: MATRIZ - SEMANA ANTERIOR
A30: REALIZADO/RITMO 2022 | B30: Janeiro | C30: Fevereiro | D30: Março | E30: Abril | F30: Maio | G30: Junho | H30: Julho | I30: Agosto | J30: Setembro | K30: Outubro | L30: Novembro | M30: Dezembro | N30: TOTAL
A31: 1 - FATURAMENTO BRUTO | B31: 4255580.6 | C31: 4255580.6 | D31: 4299728.2 | E31: 4312550.8 | F31: 4405047.6 | G31: 4406354.1 | H31: 4406354.1 | I31: 4414743.2 | J31: 4414777.6 | K31: 4414815.7 | L31: 4476276.8 | M31: 4491045.6 | N31: 52552855
A32: 2 - DEDUÇÃO DE FATURAMENTO | B32: -155328.68 | C32: -155328.68 | D32: -156940.01 | E32: -157408.05 | F32: -160784.31 | G32: -160831.99 | H32: -160831.99 | I32: -161138.22 | J32: -161139.48 | K32: -161140.88 | L32: -163384.2 | M32: -163923.26 | N32: -1918179.8
A33: 3 - FATURAMENTO LIQUIDO | B33: 4100251.9 | C33: 4100251.9 | D33: 4142788.2 | E33: 4155142.7 | F33: 4244263.3 | G33: 4245522.1 | H33: 4245522.1 | I33: 4253604.9 | J33: 4253638.1 | K33: 4253674.9 | L33: 4312892.6 | M33: 4327122.3 | N33: 50634675
A34: 4 - CUSTO MERCADORIA VENDIDA | B34: 0 | C34: 0 | D34: 0 | E34: 0 | F34: 0 | G34: 0 | H34: 0 | I34: 0 | J34: 0 | K34: 0 | L34: 0 | M34: 0 | N34: 0
A35: 5 - LUCRO BRUTO | B35: 4100251.9 | C35: 4100251.9 | D35: 4142788.2 | E35: 4155142.7 | F35: 4244263.3 | G35: 4245522.1 | H35: 4245522.1 | I35: 4253604.9 | J35: 4253638.1 | K35: 4253674.9 | L35: 4312892.6 | M35: 4327122.3 | N35: 50634675
A36: 6 - DESPESAS OPERACIONAIS | B36: -760263.96 | C36: -798744.39 | D36: -781442.35 | E36: -748713.91 | F36: -782460.61 | G36: -969918.35 | H36: -731087.8 | I36: -717953.57 | J36: -758025.34 | K36: -794650.89 | L36: -744417.96 | M36: -772997.37 | N36: -9360676.5
A37: 7 - EBITDA | B37: 3339988 | C37: 3301507.5 | D37: 3361345.8 | E37: 3406428.8 | F37: 3461802.7 | G37: 3275603.8 | H37: 3514434.3 | I37: 3535651.4 | J37: 3495612.8 | K37: 3459024 | L37: 3568474.7 | M37: 3554125 | N37: 41273999
A38: 8 - DEPRECIAÇÃO | B38: -277405.6 | C38: -277405.6 | D38: -277672.27 | E38: -280103.94 | F38: -280120.61 | G38: -280537.28 | H38: -280932.28 | I38: -280932.28 | J38: -280932.28 | K38: -282960.2 | L38: -283585.2 | M38: -288108.12 | N38: -3370695.7
A39: 9 - RESULTADO OPERACIONAL | B39: 3062582.4 | C39: 3024101.9 | D39: 3083673.6 | E39: 3126324.9 | F39: 3181682.1 | G39: 2995066.5 | H39: 3233502 | I39: 3254719.1 | J39: 3214680.5 | K39: 3176063.8 | L39: 3284889.5 | M39: 3266016.8 | N39: 37903303
A40: 10 - OUTRAS RECEITAS E DESPESAS | B40: 64429.04 | C40: 77216.4 | D40: 136348.91 | E40: 169248.96 | F40: 189012.67 | G40: 213302.15 | H40: 223089.23 | I40: 245606.63 | J40: 263720.52 | K40: 264115.61 | L40: 282622.91 | M40: 303474.83 | N40: 2432187.9
A41: 11 - LUCRO ANTES DO IR/CSLL | B41: 3127011.4 | C41: 3101318.3 | D41: 3220022.5 | E41: 3295573.8 | F41: 3370694.8 | G41: 3208368.6 | H41: 3456591.3 | I41: 3500325.7 | J41: 3478401 | K41: 3440179.4 | L41: 3567512.4 | M41: 3569491.7 | N41: 40335491
A42: 12 - IR/CSLL | B42: -585756.86 | C42: -587460.42 | D42: -609724.54 | E42: -619661.52 | F42: -633800.52 | G42: -639556.94 | H42: -640240.39 | I42: -646164.88 | J42: -649683.21 | K42: -647177.54 | L42: -657512.86 | M42: -663565.2 | N42: -7580304.9
A43: 13 - LUCRO LIQUIDO | B43: 2541254.6 | C43: 2513857.9 | D43: 2610297.9 | E43: 2675912.3 | F43: 2736894.3 | G43: 2568811.7 | H43: 2816350.9 | I43: 2854160.8 | J43: 2828717.8 | K43: 2793001.8 | L43: 2909999.5 | M43: 2905926.5 | N43: 32755186
A44: Data atualização | B44: 44568 | N44: 44568
A46: FATURAMENTO BRUTO | F46: CMV | K46: EBITDA
B47: MÊS | C47: ACUMULADO | D47: ANO | E47: Aa | G47: MÊS | H47: ACUMULADO | I47: ANO | L47: MÊS | M47: ACUMULADO | N47: ANO
A48: Semana Anterior | B48: =$B$31 -> 4255580.6 | C48: =SUM($B$31) -> 4255580.6 | D48: =N31 -> 52552855 | E48: =D49-D48 -> 1923233.7 | F48: Semana Anterior | G48: =E34 -> 0 | H48: =SUM(B34:E34) -> 0 | I48: =N34 -> 0 | K48: Semana Anterior | L48: =$B$37 -> 3339988 | M48: =SUM($B$37) -> 3339988 | N48: =N37 -> 41273999 | O48: =N49-N48 -> 2236940.8
A49: Semana atual | B49: ='Matriz senha_capital OK'!$B$34 -> 4291819.8 | C49: =SUM('Matriz senha_capital OK'!$B$34) -> 4291819.8 | D49: ='Matriz senha_capital OK'!N34 -> 54476089 | E49: =B49-B48 -> 36239.23 | F49: Semana atual | G49: 0 | H49: 0 | I49: 0 | K49: Semana atual | L49: ='Matriz senha_capital OK'!$B$40 -> 3442323.9 | M49: =SUM('Matriz senha_capital OK'!$B$40) -> 3442323.9 | N49: ='Matriz senha_capital OK'!N40 -> 43510940 | O49: =L49-L48 -> 102335.94
A50: Variação % | B50: =B49/B48-1 -> 0.0085156958 | C50: =C49/C48-1 -> 0.0085156958 | D50: =D49/D48-1 -> 0.036596179 | F50: Variação % | G50: =G48/G49 -> #DIV/0! | H50: =H48/H49 -> #DIV/0! | I50: =I48/I49 -> #DIV/0! | K50: Variação % | L50: =L49/L48-1 -> 0.030639613 | M50: =M49/M48-1 -> 0.030639613 | N50: =N49/N48-1 -> 0.054197336
A53: LUCRO BRUTO | E53: Aa | F53: DESPESAS OPERACIONAIS
B54: MÊS | C54: ACUMULADO | D54: ANO | G54: MÊS | H54: ACUMULADO | I54: ANO
A55: Semana Anterior | B55: =$B$35 -> 4100251.9 | C55: =SUM($B$35) -> 4100251.9 | D55: =N35 -> 50634675 | E55: =B56-B55 -> 33889.43 | F55: Semana Anterior | G55: =$B$36 -> -760263.96 | H55: =SUM($B$36) -> -760263.96 | I55: =N36 -> -9360676.5 | J55: =I55-I56 -> -391585.53
A56: Semana atual | B56: ='Matriz senha_capital OK'!$B$38 -> 4134141.4 | C56: =SUM('Matriz senha_capital OK'!$B$38) -> 4134141.4 | D56: ='Matriz senha_capital OK'!N38 -> 52480030 | E56: =D55-D56 -> -1845355.2 | F56: Semana atual | G56: ='Matriz senha_capital OK'!$B$39 -> -691817.45 | H56: =SUM('Matriz senha_capital OK'!$B$39) -> -691817.45 | I56: ='Matriz senha_capital OK'!N39 -> -8969091 | J56: =G55-G56 -> -68446.51
A57: Variação % | B57: =B56/B55-1 -> 0.0082652067 | C57: =C56/C55-1 -> 0.0082652067 | D57: =D56/D55-1 -> 0.036444496 | F57: Variação % | G57: =H56/H55-1 -> -0.090029929 | H57: =H56/H55-1 -> -0.090029929 | I57: =I56/I55-1 -> -0.041833037
E59: Aa | F59: RA | G59: Ra
A60: DEMERCADO - SEMANA ANTERIOR
A61: REALIZADO/RITMO 2022 | B61: Janeiro | C61: Fevereiro | D61: Março | E61: Abril | F61: Maio | G61: Junho | H61: Julho | I61: Agosto | J61: Setembro | K61: Outubro | L61: Novembro | M61: Dezembro | N61: TOTAL
A62: 1 - FATURAMENTO BRUTO | B62: 1284468.9 | C62: 1288895.4 | D62: 1289247.8 | E62: 1290182.6 | F62: 1429936.9 | G62: 1492560.6 | H62: 1555184.2 | I62: 1629836.6 | J62: 1693797.1 | K62: 1800656.9 | L62: 1865473.1 | M62: 1865473.1 | N62: 18485713
A63: 2 - DEDUÇÃO DE FATURAMENTO | B63: -118813.36 | C63: -119222.8 | D63: -119255.4 | E63: -119341.85 | F63: -132269.13 | G63: -138061.81 | H63: -143854.49 | I63: -150759.83 | J63: -156676.18 | K63: -166560.7 | L63: -172556.19 | M63: -172556.19 | N63: -1709927.9
A64: 3 - FATURAMENTO LIQUIDO | B64: 1165655.6 | C64: 1169672.6 | D64: 1169992.4 | E64: 1170840.8 | F64: 1297667.8 | G64: 1354498.7 | H64: 1411329.7 | I64: 1479076.7 | J64: 1537121 | K64: 1634096.2 | L64: 1692916.9 | M64: 1692916.9 | N64: 16775785
A65: 4 - CUSTO MERCADORIA VENDIDA | B65: 0 | C65: 0 | D65: 0 | E65: 0 | F65: 0 | G65: 0 | H65: 0 | I65: 0 | J65: 0 | K65: 0 | L65: 0 | M65: 0 | N65: 0
A66: 5 - LUCRO BRUTO | B66: 1165655.6 | C66: 1169672.6 | D66: 1169992.4 | E66: 1170840.8 | F66: 1297667.8 | G66: 1354498.7 | H66: 1411329.7 | I66: 1479076.7 | J66: 1537121 | K66: 1634096.2 | L66: 1692916.9 | M66: 1692916.9 | N66: 16775785
A67: 6 - DESPESAS OPERACIONAIS | B67: -423448.06 | C67: -393887.09 | D67: -432546.68 | E67: -394130.93 | F67: -424913.02 | G67: -586217.81 | H67: -458032.67 | I67: -425691.05 | J67: -417492.77 | K67: -422019.22 | L67: -424719.4 | M67: -403290.58 | N67: -5206389.3
A68: 7 - EBITDA | B68: 742207.5 | C68: 775785.47 | D68: 737445.75 | E68: 776709.83 | F68: 872754.78 | G68: 768280.93 | H68: 953297.01 | I68: 1053385.7 | J68: 1119628.2 | K68: 1212077 | L68: 1268197.5 | M68: 1289626.3 | N68: 11569396
A69: 8 - DEPRECIAÇÃO | B69: -235399.15 | C69: -235399.15 | D69: -235399.15 | E69: -235399.15 | F69: -242136.29 | G69: -242552.96 | H69: -242976.29 | I69: -243392.96 | J69: -243483.21 | K69: -245017.14 | L69: -245017.14 | M69: -245047.14 | N69: -2891219.7
A70: 9 - RESULTADO OPERACIONAL | B70: 506808.35 | C70: 540386.32 | D70: 502046.6 | E70: 541310.68 | F70: 630618.49 | G70: 525727.97 | H70: 710320.72 | I70: 809992.73 | J70: 876144.98 | K70: 967059.85 | L70: 1023180.4 | M70: 1044579.2 | N70: 8678176.2
A71: 10 - OUTRAS RECEITAS E DESPESAS | B71: -581246.23 | C71: -602354.13 | D71: -677847.94 | E71: -711955.81 | F71: -710061.05 | G71: -714313.53 | H71: -714203.38 | I71: -704936.79 | J71: -693403.29 | K71: -676406.29 | L71: -659886.53 | M71: -672632.98 | N71: -8119248
A72: 11 - LUCRO ANTES DO IR/CSLL | B72: -74437.88 | C72: -61967.81 | D72: -175801.34 | E72: -170645.13 | F72: -79442.56 | G72: -188585.56 | H72: -3882.66 | I72: 105055.94 | J72: 182741.69 | K72: 290653.56 | L72: 363293.83 | M72: 371946.2 | N72: 558928.28
A73: 12 - IR/CSLL | B73: 0 | C73: 0 | D73: 0 | E73: 0 | F73: 0 | G73: 0 | H73: 0 | I73: 0 | J73: 0 | K73: 0 | L73: -31375.19 | M73: -72971.38 | N73: -104346.57
A74: 13 - LUCRO LIQUIDO | B74: -74437.88 | C74: -61967.81 | D74: -175801.34 | E74: -170645.13 | F74: -79442.56 | G74: -188585.56 | H74: -3882.66 | I74: 105055.94 | J74: 182741.69 | K74: 290653.56 | L74: 331918.64 | M74: 298974.82 | N74: 454581.71
A75: Data atualização | B75: 44568 | N75: 44568
A77: FATURAMENTO BRUTO | F77: CMV | K77: EBITDA
B78: MÊS | C78: ACUMULADO | D78: ANO | E78: Aa | G78: MÊS | H78: ACUMULADO | I78: ANO | L78: MÊS | M78: ACUMULADO | N78: ANO
A79: Semana Anterior | B79: =$B$62 -> 1284468.9 | C79: =SUM($B$62) -> 1284468.9 | D79: =N62 -> 18485713 | E79: =D80-D79 -> 1386207.6 | F79: Semana Anterior | G79: =E65 -> 0 | H79: =SUM(B65:E65) -> 0 | I79: =N65 -> 0 | K79: Semana Anterior | L79: =$B$68 -> 742207.5 | M79: =SUM($B$68) -> 742207.5 | N79: =N68 -> 11569396 | O79: =L79-L80 -> -175564.53
A80: Semana atual | B80: ='Demercado_senha capital OK'!$B$34 -> 1286906.9 | C80: =SUM('Demercado_senha capital OK'!$B$34) -> 1286906.9 | D80: ='Demercado_senha capital OK'!N34 -> 19871921 | E80: =B80-B79 -> 2437.98 | F80: Semana atual | G80: 0 | H80: 0 | I80: 0 | K80: Semana atual | L80: ='Demercado_senha capital OK'!$B$40 -> 917772.03 | M80: =SUM('Demercado_senha capital OK'!$B$40) -> 917772.03 | N80: ='Demercado_senha capital OK'!N40 -> 12967376 | O80: =N79-N80 -> -1397979.6
A81: Variação % | B81: =B80/B79-1 -> 0.0018980451 | C81: =C80/C79-1 -> 0.0018980451 | D81: =D80/D79-1 -> 0.074988052 | F81: Variação % | G81: =G79/G80 -> #DIV/0! | H81: =H79/H80 -> #DIV/0! | I81: =I79/I80 -> #DIV/0! | K81: Variação % | L81: =L80/L79-1 -> 0.23654373 | M81: =M80/M79-1 -> 0.23654373 | N81: =N80/N79-1 -> 0.12083428
A84: LUCRO BRUTO | E84: Aa | F84: DESPESAS OPERACIONAIS
B85: MÊS | C85: ACUMULADO | D85: ANO | G85: MÊS | H85: ACUMULADO | I85: ANO
A86: Semana Anterior | B86: =$B$66 -> 1165655.6 | C86: =SUM($B$66) -> 1165655.6 | D86: =N66 -> 16775785 | E86: =B86-B87 -> -1580.56 | F86: Semana Anterior | G86: =$B$67 -> -423448.06 | H86: =SUM($B$67) -> -423448.06 | I86: =N67 -> -5206389.3 | J86: =G86-G87 -> -173983.97
A87: Semana atual | B87: ='Demercado_senha capital OK'!$B$38 -> 1167236.1 | C87: =SUM('Demercado_senha capital OK'!$B$38) -> 1167236.1 | D87: ='Demercado_senha capital OK'!N38 -> 18033126 | E87: =D86-D87 -> -1257340.7 | F87: Semana atual | G87: ='Demercado_senha capital OK'!$B$39 -> -249464.09 | H87: =SUM('Demercado_senha capital OK'!$B$39) -> -249464.09 | I87: ='Demercado_senha capital OK'!N39 -> -5065750.4 | J87: =I87-I86 -> 140638.91
A88: Variação % | B88: =B87/B86-1 -> 0.0013559409 | C88: =C87/C86-1 -> 0.0013559409 | D88: =D87/D86-1 -> 0.074949739 | F88: Variação % | G88: =G87/G86-1 -> -0.41087441 | H88: =H87/H86-1 -> -0.41087441 | I88: =I87/I86-1 -> -0.027012753
A91: GAROTO - SEMANA ANTERIOR
A92: REALIZADO/RITMO 2022 | B92: Janeiro | C92: Fevereiro | D92: Março | E92: Abril | F92: Maio | G92: Junho | H92: Julho | I92: Agosto | J92: Setembro | K92: Outubro | L92: Novembro | M92: Dezembro | N92: TOTAL
A93: 1 - FATURAMENTO BRUTO | B93: 89181 | C93: 93265.05 | D93: 96538.94 | E93: 100577.4 | F93: 102451.9 | G93: 104076.6 | H93: 105911.6 | I93: 116210.1 | J93: 113265.2 | K93: 118349.9 | L93: 119993.6 | M93: 147220.2 | N93: 1307041.5
A94: 2 - DEDUÇÃO DE FATURAMENTO | B94: -12708.29 | C94: -13290.28 | D94: -13756.81 | E94: -14332.28 | F94: -14599.4 | G94: -14830.91 | H94: -15092.41 | I94: -16559.95 | J94: -16140.28 | K94: -16864.87 | L94: -17099.09 | M94: -20978.87 | N94: -186253.44
A95: 3 - FATURAMENTO LIQUIDO | B95: 76472.71 | C95: 79974.77 | D95: 82782.13 | E95: 86245.12 | F95: 87852.5 | G95: 89245.69 | H95: 90819.19 | I95: 99650.15 | J95: 97124.92 | K95: 101485.03 | L95: 102894.51 | M95: 126241.33 | N95: 1120788.1
A96: 4 - CUSTO MERCADORIA VENDIDA | B96: 0 | C96: 0 | D96: 0 | E96: 0 | F96: 0 | G96: 0 | H96: 0 | I96: 0 | J96: 0 | K96: 0 | L96: 0 | M96: 0 | N96: 0
A97: 5 - LUCRO BRUTO | B97: 76472.71 | C97: 79974.77 | D97: 82782.13 | E97: 86245.12 | F97: 87852.5 | G97: 89245.69 | H97: 90819.19 | I97: 99650.15 | J97: 97124.92 | K97: 101485.03 | L97: 102894.51 | M97: 126241.33 | N97: 1120788.1
A98: 6 - DESPESAS OPERACIONAIS | B98: -71519.69 | C98: -72128.91 | D98: -77029.02 | E98: -76964.29 | F98: -78606.29 | G98: -71880.13 | H98: -76126.63 | I98: -75503.8 | J98: -83726.88 | K98: -76153.95 | L98: -75523.3 | M98: -104245.63 | N98: -939408.52
A99: 7 - EBITDA | B99: 4953.02 | C99: 7845.86 | D99: 5753.11 | E99: 9280.83 | F99: 9246.21 | G99: 17365.56 | H99: 14692.56 | I99: 24146.35 | J99: 13398.04 | K99: 25331.08 | L99: 27371.21 | M99: 21995.7 | N99: 181379.53
A100: 8 - DEPRECIAÇÃO | B100: -5464.53 | C100: -5464.53 | D100: -5547.86 | E100: -5652.03 | F100: -5693.53 | G100: -5693.53 | H100: -5693.53 | I100: -5693.53 | J100: -5764.36 | K100: -5764.36 | L100: -5764.36 | M100: -5764.36 | N100: -67960.51
A101: 9 - RESULTADO OPERACIONAL | B101: -511.51 | C101: 2381.33 | D101: 205.25 | E101: 3628.8 | F101: 3552.68 | G101: 11672.03 | H101: 8999.03 | I101: 18452.82 | J101: 7633.68 | K101: 19566.72 | L101: 21606.85 | M101: 16231.34 | N101: 113419.02
A102: 10 - OUTRAS RECEITAS E DESPESAS | B102: -913.58 | C102: -889.1 | D102: -838.8 | E102: -605.73 | F102: -585.14 | G102: -506.13 | H102: -213.73 | I102: 41.39 | J102: 405.88 | K102: 578.8 | L102: 1006.14 | M102: 998.4 | N102: -1521.6
A103: 11 - LUCRO ANTES DO IR/CSLL | B103: -1425.09 | C103: 1492.23 | D103: -633.55 | E103: 3023.07 | F103: 2967.54 | G103: 11165.9 | H103: 8785.3 | I103: 18494.21 | J103: 8039.56 | K103: 20145.52 | L103: 22612.99 | M103: 17229.74 | N103: 111897.42
A104: 12 - IR/CSLL | B104: 0 | C104: 0 | D104: 0 | E104: 0 | F104: 0 | G104: 0 | H104: 0 | I104: 0 | J104: 0 | K104: 0 | L104: 0 | M104: 0 | N104: 0
A105: 13 - LUCRO LIQUIDO | B105: -1425.09 | C105: 1492.23 | D105: -633.55 | E105: 3023.07 | F105: 2967.54 | G105: 11165.9 | H105: 8785.3 | I105: 18494.21 | J105: 8039.56 | K105: 20145.52 | L105: 22612.99 | M105: 17229.74 | N105: 111897.42
A106: Data atualização | B106: 44568 | N106: 44568
A108: FATURAMENTO BRUTO | F108: CMV | K108: EBITDA
B109: MÊS | C109: ACUMULADO | D109: ANO | E109: Aa | G109: MÊS | H109: ACUMULADO | I109: ANO | L109: MÊS | M109: ACUMULADO | N109: ANO
A110: Semana Anterior | B110: =$B$93 -> 89181 | C110: =SUM($B$93) -> 89181 | D110: =N93 -> 1307041.5 | E110: =B111-B110 -> #REF! | F110: Semana Anterior | G110: =E96 -> 0 | H110: =SUM(B96:E96) -> 0 | I110: =N96 -> 0 | K110: Semana Anterior | L110: =$B$99 -> 4953.02 | M110: =SUM($B$99) -> 4953.02 | N110: =N99 -> 181379.53 | O110: =L110-L111 -> #REF!
A111: Semana atual | B111: ='Garoto senha_capital OK'!$B$48 -> #REF! | C111: =SUM('Garoto senha_capital OK'!$B$48) -> #REF! | D111: ='Garoto senha_capital OK'!N48 -> #REF! | E111: =D111-D110 -> #REF! | F111: Semana atual | G111: ='Garoto senha_capital OK'!E51 -> #REF! | H111: =SUM('Garoto senha_capital OK'!B51:E51) -> #REF! | I111: ='Garoto senha_capital OK'!N51 -> #REF! | K111: Semana atual | L111: ='Garoto senha_capital OK'!$B$54 -> #REF! | M111: =SUM('Garoto senha_capital OK'!$B$54) -> #REF! | N111: ='Garoto senha_capital OK'!N54 -> #REF! | O111: =N110-N111 -> #REF!
A112: Variação % | B112: =B111/B110-1 -> #REF! | C112: =C111/C110-1 -> #REF! | D112: =D111/D110-1 -> #REF! | F112: Variação % | G112: =G110/G111 -> #REF! | H112: =H110/H111 -> #REF! | I112: =I110/I111 -> #REF! | K112: Variação % | L112: =L110/L111-1 -> #REF! | M112: =M110/M111-1 -> #REF! | N112: =N110/N111-1 -> #REF!
A115: LUCRO BRUTO | E115: Aa | F115: DESPESAS OPERACIONAIS | L115: 7648
B116: MÊS | C116: ACUMULADO | D116: ANO | G116: MÊS | H116: ACUMULADO | I116: ANO
A117: Semana Anterior | B117: =$B$97 -> 76472.71 | C117: =SUM($B$97) -> 76472.71 | D117: =N97 -> 1120788.1 | E117: =B117-B118 -> #REF! | F117: Semana Anterior | G117: =$B$98 -> -71519.69 | H117: =SUM($B$98) -> -71519.69 | I117: =N98 -> -939408.52 | J117: =G117-G118 -> #REF!
A118: Semana atual | B118: ='Garoto senha_capital OK'!$B$52 -> #REF! | C118: =SUM('Garoto senha_capital OK'!$B$52) -> #REF! | D118: ='Garoto senha_capital OK'!N52 -> #REF! | E118: =D117-D118 -> #REF! | F118: Semana atual | G118: ='Garoto senha_capital OK'!$B$53 -> #REF! | H118: =SUM('Garoto senha_capital OK'!$B$53) -> #REF! | I118: ='Garoto senha_capital OK'!N53 -> #REF! | J118: =I117-I118 -> #REF!
A119: Variação % | B119: =B118/B117-1 -> #REF! | C119: =C118/C117-1 -> #REF! | D119: =D118/D117-1 -> #REF! | F119: Variação % | G119: =G118/G117-1 -> #REF! | H119: =H118/H117-1 -> #REF! | I119: =I118/I117-1 -> #REF!
A122: HANGAR - SEMANA ANTERIOR
A123: REALIZADO/RITMO 2022 | B123: Janeiro | C123: Fevereiro | D123: Março | E123: Abril | F123: Maio | G123: Junho | H123: Julho | I123: Agosto | J123: Setembro | K123: Outubro | L123: Novembro | M123: Dezembro | N123: TOTAL
A124: 1 - FATURAMENTO BRUTO | B124: 156605 | C124: 151190 | D124: 151173 | E124: 164700 | F124: 159780 | G124: 166905 | H124: 181805 | I124: 200350 | J124: 195766 | K124: 196200 | L124: 191260 | M124: 171885 | N124: 2087619
A125: 2 - DEDUÇÃO DE FATURAMENTO | B125: -22316.21 | C125: -21544.58 | D125: -21542.15 | E125: -23469.75 | F125: -22768.65 | G125: -23783.97 | H125: -25907.22 | I125: -28549.88 | J125: -27896.66 | K125: -27958.51 | L125: -27254.56 | M125: -24493.61 | N125: -297485.75
A126: 3 - FATURAMENTO LIQUIDO | B126: 134288.79 | C126: 129645.42 | D126: 129630.85 | E126: 141230.25 | F126: 137011.35 | G126: 143121.03 | H126: 155897.78 | I126: 171800.12 | J126: 167869.34 | K126: 168241.49 | L126: 164005.44 | M126: 147391.39 | N126: 1790133.2
A127: 4 - CUSTO MERCADORIA VENDIDA | B127: 0 | C127: 0 | D127: 0 | E127: 0 | F127: 0 | G127: 0 | H127: 0 | I127: 0 | J127: 0 | K127: 0 | L127: 0 | M127: 0 | N127: 0
A128: 5 - LUCRO BRUTO | B128: 134288.79 | C128: 129645.42 | D128: 129630.85 | E128: 141230.25 | F128: 137011.35 | G128: 143121.03 | H128: 155897.78 | I128: 171800.12 | J128: 167869.34 | K128: 168241.49 | L128: 164005.44 | M128: 147391.39 | N128: 1790133.2
A129: 6 - DESPESAS OPERACIONAIS | B129: -133446.95 | C129: -118320.32 | D129: -126332.76 | E129: -133003.06 | F129: -147943.8 | G129: -122885.29 | H129: -128934.98 | I129: -128840.78 | J129: -129544.25 | K129: -130697.22 | L129: -135091.17 | M129: -130346.28 | N129: -1565386.9
A130: 7 - EBITDA | B130: 841.84 | C130: 11325.1 | D130: 3298.09 | E130: 8227.19 | F130: -10932.45 | G130: 20235.74 | H130: 26962.8 | I130: 42959.34 | J130: 38325.09 | K130: 37544.27 | L130: 28914.27 | M130: 17045.11 | N130: 224746.39
A131: 8 - DEPRECIAÇÃO | B131: -27049.78 | C131: -27049.78 | D131: -27232.95 | E131: -27232.95 | F131: -27232.95 | G131: -27256.27 | H131: -27256.27 | I131: -27256.27 | J131: -27256.27 | K131: -27283.65 | L131: -27283.65 | M131: -27283.65 | N131: -326674.44
A132: 9 - RESULTADO OPERACIONAL | B132: -26207.94 | C132: -15724.68 | D132: -23934.86 | E132: -19005.76 | F132: -38165.4 | G132: -7020.53 | H132: -293.47 | I132: 15703.07 | J132: 11068.82 | K132: 10260.62 | L132: 1630.62 | M132: -10238.54 | N132: -101928.05
A133: 10 - OUTRAS RECEITAS E DESPESAS | B133: -4012.99 | C133: -3806.62 | D133: -3688.4 | E133: -3695.61 | F133: -3499.4 | G133: -3425.23 | H133: -3323.95 | I133: -3227.07 | J133: -2530 | K133: -2530 | L133: -2530 | M133: -2530 | N133: -38799.27
A134: 11 - LUCRO ANTES DO IR/CSLL | B134: -30220.93 | C134: -19531.3 | D134: -27623.26 | E134: -22701.37 | F134: -41664.8 | G134: -10445.76 | H134: -3617.42 | I134: 12476 | J134: 8538.82 | K134: 7730.62 | L134: -899.38 | M134: -12768.54 | N134: -140727.32
A135: 12 - IR/CSLL | B135: 0 | C135: 0 | D135: 0 | E135: 0 | F135: 0 | G135: 0 | H135: 0 | I135: 0 | J135: 0 | K135: 0 | L135: 0 | M135: 0 | N135: 0
A136: 13 - LUCRO LIQUIDO | B136: -30220.93 | C136: -19531.3 | D136: -27623.26 | E136: -22701.37 | F136: -41664.8 | G136: -10445.76 | H136: -3617.42 | I136: 12476 | J136: 8538.82 | K136: 7730.62 | L136: -899.38 | M136: -12768.54 | N136: -140727.32
A137: Data atualização | B137: 44568 | N137: 44568
A139: FATURAMENTO BRUTO | F139: CMV | K139: EBITDA
B140: MÊS | C140: ACUMULADO | D140: ANO | E140: Aa | G140: MÊS | H140: ACUMULADO | I140: ANO | L140: MÊS | M140: ACUMULADO | N140: ANO
A141: Semana Anterior | B141: =$B$124 -> 156605 | C141: =SUM($B$124) -> 156605 | D141: =N124 -> 2087619 | E141: =B142-B141 -> -7550.98 | F141: Semana Anterior | G141: =E127 -> 0 | H141: =SUM(B127:E127) -> 0 | I141: =N127 -> 0 | K141: Semana Anterior | L141: =$B$130 -> 841.84 | M141: =SUM($B$130) -> 841.84 | N141: =N130 -> 224746.39 | O141: =L141-L142 -> -6906.87
A142: Semana atual | B142: ='Hangar senha_capital OK'!$B$49 -> 149054.02 | C142: =SUM('Hangar senha_capital OK'!$B$49) -> 149054.02 | D142: ='Hangar senha_capital OK'!N49 -> 2321854 | E142: =D142-D141 -> 234234.95 | F142: Semana atual | G142: ='Hangar senha_capital OK'!E52 -> 0 | H142: =SUM('Hangar senha_capital OK'!B52:E52) -> 0 | I142: ='Hangar senha_capital OK'!N52 -> 0 | K142: Semana atual | L142: ='Hangar senha_capital OK'!$B$55 -> 7748.71 | M142: =SUM('Hangar senha_capital OK'!$B$55) -> 7748.71 | N142: ='Hangar senha_capital OK'!N55 -> 234328.6 | O142: =N141-N142 -> -9582.21
...

Sheet Quadro EBITDA
B2: RITMO
B3: EBITDA (Em R$/Mil) | C3: NOVEMBRO | H3: ACUMULADO JANEIRO A NOVEMBRO | M3: RITMO
C4: Real 2024 | D4: Orç 2025 | E4: Ritmo 2025 | F4: Ritmo 2025 x Orç 2025 | G4: Ritmo 2025 x Real 2024 | H4: Real 2024 | I4: Orç 2025 | J4: Ritmo 2025 | K4: Ritmo 2025 x Orç 2025 | L4: Ritmo 2025 x Real 2024 | M4: Real 2024 | N4: Orç 2025 | O4: Ritmo 2025 | P4: Ritmo 2025 x Orç 2025 | Q4: Ritmo 2025 x Real 2024
B5: Demercado | C5: 1959.1939 | D5: 2065.6617 | E5: 2081.9086 | F5: =(E5/D5-1) -> 0.007865228 | G5: =(E5/C5-1) -> 0.062635286 | H5: 18826.407 | I5: 21831.849 | J5: 22484.974 | K5: =(J5/I5-1) -> 0.029916128 | L5: =(J5/H5-1) -> 0.19433163 | M5: 20743.793 | N5: 23880.127 | O5: 24573.772 | P5: =(O5/N5-1) -> 0.029046974 | Q5: =(O5/M5-1) -> 0.18463253
B6: Capital Realty | C6: 3745.3214 | D6: 3655.6829 | E6: 4138.1043 | F6: =(E6/D6-1) -> 0.13196479 | G6: =(E6/C6-1) -> 0.10487294 | H6: 38194.993 | I6: 37435.673 | J6: 44513.003 | K6: =(J6/I6-1) -> 0.1890531 | L6: =(J6/H6-1) -> 0.16541463 | M6: 40915.713 | N6: 41221.328 | O6: 48685.917 | P6: =(O6/N6-1) -> 0.18108561 | Q6: =(O6/M6-1) -> 0.18990758
B7: Hangar Vip | C7: 75.2033 | D7: 132.52656 | E7: -77.66243 | F7: =(E7/D7-1) -> -1.5860141 | G7: =(E7/C7-1) -> -2.0326998 | H7: 974.56093 | I7: 886.53431 | J7: 940.12334 | K7: =(J7/I7-1) -> 0.060447779 | L7: =(J7/H7-1) -> -0.035336518 | M7: 993.4194 | N7: 1024.6746 | O7: 1043.8898 | P7: =(O7/N7-1) -> 0.018752499 | Q7: =(O7/M7-1) -> 0.050804756
B8: CR Combustíveis | C8: -3.08736 | D8: -3.81875 | E8: 0 | F8: =(E8/D8-1) -> -1 | G8: =(E8/C8-1) -> -1 | H8: -241.31924 | I8: -42.5445 | J8: 151.89878 | K8: =-(J8/I8-1) -> 4.5703506 | L8: =-(J8/H8-1) -> 1.6294516 | M8: -256.31814 | N8: -46.36325 | O8: 151.89878 | P8: =-(O8/N8-1) -> 4.2762755 | Q8: =(O8/M8-1) -> -1.5926181
B9: TOTAL | C9: =SUM(C5:C8) -> 5776.6313 | D9: =SUM(D5:D8) -> 5850.0523 | E9: =SUM(E5:E8) -> 6142.3504 | F9: =E9/D9-1 -> 0.049965037 | G9: =E9/C9-1 -> 0.06331011 | H9: =SUM(H5:H8) -> 57754.642 | I9: =SUM(I5:I8) -> 60111.512 | J9: =SUM(J5:J8) -> 68089.999 | K9: =J9/I9-1 -> 0.1327281 | L9: =J9/H9-1 -> 0.17895284 | M9: =SUM(M5:M8) -> 62396.608 | N9: =SUM(N5:N8) -> 66079.766 | O9: =SUM(O5:O8) -> 74455.478 | P9: =(O9/N9-1) -> 0.12675154 | Q9: =O9/M9-1 -> 0.19326163
B10: Demercado | C10: =C5 -> 1959.1939 | D10: =D5 -> 2065.6617 | E10: =E5 -> 2081.9086 | F10: =(E10/D10-1) -> 0.007865228 | G10: =(E10/C10-1) -> 0.062635286 | H10: =H5 -> 18826.407 | I10: =I5 -> 21831.849 | J10: =J5 -> 22484.974 | K10: =(J10/I10-1) -> 0.029916128 | L10: =(J10/H10-1) -> 0.19433163 | M10: =M5 -> 20743.793 | N10: =N5 -> 23880.127 | O10: =O5 -> 24573.772 | P10: =(O10/N10-1) -> 0.029046974 | Q10: =(O10/M10-1) -> 0.18463253
B11: Margem EBITDA/ROL | C11: =C10/C21 -> 0.81189345 | D11: =D10/D21 -> 0.82522721 | E11: =E10/E21 -> 0.82995533 | F11: =E11-D11 -> 0.004728125 | G11: =E11-C11 -> 0.018061885 | H11: =H5/H21 -> 0.80238679 | I11: =I5/I21 -> 0.81378746 | J11: =J5/J21 -> 0.82642201 | K11: =J11-I11 -> 0.012634551 | L11: =J11-H11 -> 0.024035215 | M11: =M10/M21 -> 0.80228323 | N11: =N10/N21 -> 0.8141497 | O11: =O10/O21 -> 0.82434546 | P11: =O11-N11 -> 0.010195755 | Q11: =O11-M11 -> 0.022062228
B12: Capital Realty | C12: =C6 -> 3745.3214 | D12: =D6 -> 3655.6829 | E12: =E6 -> 4138.1043 | F12: =E12/D12-1 -> 0.13196479 | G12: =E12/C12-1 -> 0.10487294 | H12: =SUM(H6) -> 38194.993 | I12: =SUM(I6) -> 37435.673 | J12: =SUM(J6) -> 44513.003 | K12: =(J12/I12-1) -> 0.1890531 | L12: =(J12/H12-1) -> 0.16541463 | M12: =M6 -> 40915.713 | N12: =N6 -> 41221.328 | O12: =O6 -> 48685.917 | P12: =O12/N12-1 -> 0.18108561 | Q12: =O12/M12-1 -> 0.18990758
B13: Margem EBITDA/ROL | C13: =C12/C22 -> 0.77680827 | D13: =D12/D22 -> 0.77382006 | E13: =E12/E22 -> 0.78942258 | F13: =E13-D13 -> 0.015602521 | G13: =E13-C13 -> 0.012614318 | H13: =H12/H22 -> 0.78858946 | I13: =I12/I22 -> 0.75542693 | J13: =J12/J22 -> 0.80468617 | K13: =J13-I13 -> 0.04925924 | L13: =J13-H13 -> 0.016096707 | M13: =M12/M22 -> 0.77274357 | N13: =N12/N22 -> 0.75574895 | O13: =O12/O22 -> 0.80376435 | P13: =O13-N13 -> 0.048015402 | Q13: =O13-M13 -> 0.031020779
B14: CR Estacionamentos | C14: =(C7) -> 75.2033 | D14: =+D7 -> 132.52656 | E14: =(+E7) -> -77.66243 | F14: =(E14/D14-1) -> -1.5860141 | G14: =(E14/C14-1) -> -2.0326998 | H14: =+H7 -> 974.56093 | I14: =+I7 -> 886.53431 | J14: =J7 -> 940.12334 | K14: =J14/I14-1 -> 0.060447779 | L14: =(J14/H14-1) -> -0.035336518 | M14: =M7-1 -> 992.4194 | N14: =N7-1 -> 1023.6746 | O14: =+O7 -> 1043.8898 | P14: =(O14/N14-1) -> 0.019747691 | Q14: =O14/M14-1 -> 0.051863587
B15: Margem EBITDA/ROL | C15: =C14/C23 -> 0.24987852 | D15: =D14/D23 -> 0.36668824 | E15: =E14/E23 -> -0.19987957 | F15: =E15-D15 -> -0.56656781 | G15: =E15-C15 -> -0.44975809 | H15: =H14/H23 -> 0.29161784 | I15: =I14/I23 -> 0.23933396 | J15: =J14/J23 -> 0.24692748 | K15: =J15-I15 -> 0.007593519 | L15: =J15-H15 -> -0.044690363 | M15: =M14/M23 -> 0.27696557 | N15: =N14/N23 -> 0.25179008 | O15: =O14/O23 -> 0.24919956 | P15: =O15-N15 -> -0.002590522 | Q15: =O15-M15 -> -0.027766009
B16: CR Comércio de Comb | C16: =C8 -> -3.08736 | D16: =D8 -> -3.81875 | E16: =E8 -> 0 | F16: =(E16/D16-1) -> -1 | G16: =(E16/C16-1) -> -1 | H16: =H8 -> -241.31924 | I16: =I8 -> -42.5445 | J16: =J8 -> 151.89878 | K16: =(J16/I16-1) -> -4.5703506 | L16: =((J16/H16)-1) -> -1.6294516 | M16: =M8 -> -256.31814 | N16: =N8 -> -46.36325 | O16: =O8 -> 151.89878 | P16: =(O16/N16-1) -> -4.2762755 | Q16: =(O16/M16-1) -> -1.5926181
B17: Margem EBITDA/ROL | C17: - | D17: - | E17: - | F17: - | G17: - | H17: - | I17: - | J17: - | K17: - | L17: - | M17: - | N17: - | O17: - | P17: - | Q17: -
B20: Faturamento Líquido Ritmo
B21: Demercado | C21: 2413.117 | D21: 2503.143 | E21: 2508.4586 | H21: 23463.008 | I21: 26827.459 | J21: 27207.617 | M21: 25855.948 | N21: 29331.371 | O21: 29810.041
B22: CR Infra | C22: 4821.4232 | D22: 4724.2028 | E22: 5241.9381 | H22: 48434.572 | I22: 49555.651 | J22: 55317.222 | M22: 52948.63 | N22: 54543.679 | O22: 60572.377
B23: CR Estacionamentos | C23: 300.95944 | D23: 361.41481 | E23: 388.54611 | H23: 3341.9112 | I23: 3704.1727 | J23: 3807.2853 | M23: 3583.1869 | N23: 4065.5875 | O23: 4188.9714
B24: CR Comb | C24: 0 | D24: 0 | E24: 0 | H24: 0 | I24: 0 | J24: 0 | M24: 0 | N24: 0 | O24: 0
C25: =SUM(C21:C24) -> 7535.4997 | D25: =SUM(D21:D24) -> 7588.7605 | E25: =SUM(E21:E24) -> 8138.9428 | H25: =SUM(H21:H24) -> 75239.491 | I25: =SUM(I21:I24) -> 80087.283 | J25: =SUM(J21:J24) -> 86332.125 | M25: =SUM(M21:M24) -> 82387.764 | N25: =SUM(N21:N24) -> 87940.637 | O25: =SUM(O21:O24) -> 94571.39
B27: REAL
B29: EBITDA (Em R$/Mil) | C29: JUNHO | H29: ACUMULADO JANEIRO A JUNHO | M29: RITMO
C30: Real 2025 | D30: Orç 2026 | E30: Real 2026 | F30: Real 2026 x Orç 2026 | G30: Real 2026 x Real 2025 | H30: Real 2025 | I30: Orç 2026 | J30: Real 2026 | K30: Real 2026 x Orç 2026 | L30: Real 2026 x Real 2025 | M30: Real 2025 | N30: Orç 2026 | O30: Ritmo 2026 | P30: Ritmo 2026 x Orç 2026 | Q30: Ritmo 2026 x Real 2025
B31: Demercado | C31: ='Quadro DRE Apresentação'!C31 -> 2002.9395 | D31: ='Quadro DRE Apresentação'!D31 -> 2323.1209 | E31: ='Quadro DRE Apresentação'!E31 -> 2210.532 | F31: =(E31/D31-1) -> -0.048464482 | G31: =(E31/C31-1) -> 0.10364393 | H31: ='Quadro DRE Apresentação'!H31 -> 12146.751 | I31: ='Quadro DRE Apresentação'!I31 -> 13654.673 | J31: ='Quadro DRE Apresentação'!J31 -> 13998.193 | K31: =(J31/I31-1) -> 0.025157672 | L31: =(J31/H31-1) -> 0.1524228 | M31: ='Quadro DRE Apresentação'!M31 -> 24854.461 | N31: ='Quadro DRE Apresentação'!N31 -> 28707.954 | O31: ='Quadro DRE Apresentação'!O31 -> 29099.404 | P31: =(O31/N31-1) -> 0.013635598 | Q31: =(O31/M31-1) -> 0.17079198
B32: Margem EBITDA/ROL | C32: =C31/C40 -> 0.81069495 | D32: =D31/D40 -> 0.77704405 | E32: =E31/E40 -> 0.72949153 | F32: =E32-D32 -> -0.04755252 | G32: =E32-C32 -> -0.081203422 | H32: =H31/H40 -> 0.8286848 | I32: =I31/I40 -> 0.79312299 | J32: =J31/J40 -> 0.80282464 | K32: =J32-I32 -> 0.0097016507 | L32: =J32-H32 -> -0.025860156 | M32: =M31/M40 -> 0.83236771 | N32: =N31/N40 -> 0.80819497 | O32: =O31/O40 -> 0.80565598 | P32: =O32-N32 -> -0.0025389944 | Q32: =O32-M32 -> -0.026711736
B33: Capital Realty | C33: ='Quadro DRE Apresentação'!C11 -> 4085.0554 | D33: ='Quadro DRE Apresentação'!D11 -> 4473.0857 | E33: ='Quadro DRE Apresentação'!E11 -> 4974.9488 | F33: =(E33/D33-1) -> 0.11219618 | G33: =(E33/C33-1) -> 0.21784122 | H33: ='Quadro DRE Apresentação'!H11 -> 28475.667 | I33: ='Quadro DRE Apresentação'!I11 -> 30777.921 | J33: ='Quadro DRE Apresentação'!J11 -> 32398.072 | K33: =(J33/I33-1) -> 0.052640053 | L33: =(J33/H33-1) -> 0.13774585 | M33: ='Quadro DRE Apresentação'!M11 -> 49087.274 | N33: ='Quadro DRE Apresentação'!N11 -> 54393.348 | O33: ='Quadro DRE Apresentação'!O11 -> 55712.148 | P33: =(O33/N33-1) -> 0.024245602 | Q33: =(O33/M33-1) -> 0.13496111
B34: Margem EBITDA/ROL | C34: =C33/C41 -> 0.78074961 | D34: =D33/D41 -> 0.81229279 | E34: =E33/E41 -> 0.84275998 | F34: =E34-D34 -> 0.030467199 | G34: =E34-C34 -> 0.062010371 | H34: =H33/H41 -> 0.82592931 | I34: =I33/I41 -> 0.81734218 | J34: =J33/J41 -> 0.84221634 | K34: =J34-I34 -> 0.024874165 | L34: =J34-H34 -> 0.016287035 | M34: =M33/M41 -> 0.81031423 | N34: =N33/N41 -> 0.82623825 | O34: =O33/O41 -> 0.82953568 | P34: =O34-N34 -> 0.0032974335 | Q34: =O34-M34 -> 0.019221452
B35: CR Estacionamentos | C35: ='Quadro DRE Apresentação'!C95 -> 141.44245 | D35: ='Quadro DRE Apresentação'!D95 -> 193.34632 | E35: ='Quadro DRE Apresentação'!E95 -> 260.07537 | F35: =(E35/D35-1) -> 0.34512708 | G35: =(E35/C35-1) -> 0.83873632 | H35: ='Quadro DRE Apresentação'!H95 -> 673.57758 | I35: ='Quadro DRE Apresentação'!I95 -> 746.14484 | J35: ='Quadro DRE Apresentação'!J95 -> 1187.8467 | K35: =(J35/I35-1) -> 0.59197868 | L35: =(J35/H35-1) -> 0.76348904 | M35: ='Quadro DRE Apresentação'!M95 -> 1048.9857 | N35: ='Quadro DRE Apresentação'!N95 -> 1521.582 | O35: ='Quadro DRE Apresentação'!O95 -> 1950.7689 | P35: =((O35/N35)-1) -> 0.28206624 | Q35: =(O35/M35-1) -> 0.85967156
B36: Margem EBITDA/ROL | C36: =C35/C42 -> 0.35268068 | D36: =D35/D42 -> 0.43328752 | E36: =E35/E42 -> 0.54278915 | F36: =E36-D36 -> 0.10950163 | G36: =E36-C36 -> 0.19010847 | H36: =H35/H42 -> 0.29748301 | I36: =I35/I42 -> 0.2834904 | J36: =J35/J42 -> 0.4026773 | K36: =J36-I36 -> 0.1191869 | L36: =J36-H36 -> 0.10519429 | M36: =M35/M42 -> 0.3520488 | N36: =N35/N42 -> 0.38353667 | O36: =O35/O42 -> 0.37829603 | P36: =O36-N36 -> -0.0052406367 | Q36: =O36-M36 -> 0.02624723
B37: TOTAL | C37: =SUM(C31:C35) -> 6231.0288 | D37: =SUM(D31:D35) -> 6991.1422 | E37: =SUM(E31:E35) -> 7447.1285 | F37: =E37/D37-1 -> 0.065223425 | G37: =E37/C37-1 -> 0.19516836 | H37: =SUM(H31:H35) -> 41297.65 | I37: =SUM(I31:I35) -> 45180.349 | J37: =SUM(J31:J35) -> 47585.757 | K37: =J37/I37-1 -> 0.053240128 | L37: =J37/H37-1 -> 0.15226305 | M37: =SUM(M31:M35) -> 74992.364 | N37: =SUM(N31:N35) -> 84624.518 | O37: =SUM(O31:O35) -> 86763.955 | P37: =O37/N37-1 -> 0.02528153 | Q37: =O37/M37-1 -> 0.15697054
B39: Faturamento Líquido Realizado
B40: Demercado | C40: ='Quadro DRE Apresentação'!C27 -> 2470.6451 | D40: ='Quadro DRE Apresentação'!D27 -> 2989.6901 | E40: ='Quadro DRE Apresentação'!E27 -> 3030.2367 | H40: ='Quadro DRE Apresentação'!H27 -> 14657.866 | I40: ='Quadro DRE Apresentação'!I27 -> 17216.337 | J40: ='Quadro DRE Apresentação'!J27 -> 17436.177 | M40: ='Quadro DRE Apresentação'!M27 -> 29859.953 | N40: ='Quadro DRE Apresentação'!N27 -> 35521.074 | O40: ='Quadro DRE Apresentação'!O27 -> 36118.895
B41: CR Infra | C41: ='Quadro DRE Apresentação'!C7 -> 5232.2221 | D41: ='Quadro DRE Apresentação'!D7 -> 5506.7407 | E41: ='Quadro DRE Apresentação'!E7 -> 5903.1622 | H41: ='Quadro DRE Apresentação'!H7 -> 34477.124 | I41: ='Quadro DRE Apresentação'!I7 -> 37656.102 | J41: ='Quadro DRE Apresentação'!J7 -> 38467.636 | M41: ='Quadro DRE Apresentação'!M7 -> 60578.073 | N41: ='Quadro DRE Apresentação'!N7 -> 65832.522 | O41: ='Quadro DRE Apresentação'!O7 -> 67160.64
B42: CR Estacionamento | C42: ='Quadro DRE Apresentação'!C69+'Quadro DRE Apresentação'!C91 -> 401.04961 | D42: ='Quadro DRE Apresentação'!D69+'Quadro DRE Apresentação'!D91 -> 446.23099 | E42: ='Quadro DRE Apresentação'!E69+'Quadro DRE Apresentação'!E91 -> 479.14622 | H42: =+'Quadro DRE Apresentação'!H91 -> 2264.2556 | I42: ='Quadro DRE Apresentação'!I91 -> 2631.9933 | J42: ='Quadro DRE Apresentação'!J91 -> 2949.8725 | M42: ='Quadro DRE Consolidado'!M45 -> 2979.66 | N42: ='Quadro DRE Consolidado'!N45 -> 3967.24 | O42: ='Quadro DRE Apresentação'!O69+'Quadro DRE Apresentação'!O91 -> 5156.7259
B43: CR Comb | C43: 0 | D43: 0 | E43: 0 | H43: ='Quadro DRE Consolidado'!H6 -> 0 | I43: 0 | J43: 0 | M43: ='Quadro DRE Consolidado'!M6 -> 0 | N43: =N24 -> 0 | O43: =O24 -> 0
C44: =SUM(C40:C43) -> 8103.9168 | D44: =SUM(D40:D43) -> 8942.6617 | E44: =SUM(E40:E43) -> 9412.5451 | H44: =SUM(H40:H43) -> 51399.246 | I44: =SUM(I40:I43) -> 57504.433 | J44: =SUM(J40:J43) -> 58853.686 | M44: =SUM(M40:M43) -> 93417.686 | N44: =SUM(N40:N43) -> 105320.84 | O44: =SUM(O40:O43) -> 108436.26
B46: CMV Postos
B47: Posto Esteio | C47: ='Posto Esteio senha_capital OK'!$D$56 -> #REF! | D47: ='Posto Esteio senha_capital OK'!$D$62 -> #REF! | E47: ='Posto Esteio senha_capital OK'!$D$68 -> #REF! | H47: ='Posto Esteio senha_capital OK'!$Q$56 -> #REF! | I47: ='Posto Esteio senha_capital OK'!$Q$62 -> #REF! | J47: ='Posto Esteio senha_capital OK'!$Q$68 -> #REF! | M47: ='Posto Esteio senha_capital OK'!$P$56 -> #REF! | N47: ='Posto Esteio senha_capital OK'!$P$62 -> #REF! | O47: ='Posto Esteio senha_capital OK'!$P$68 -> #REF!
B48: Posto Curitiba | C48: ='Posto Curitiba_senha capital OK'!$D$60 -> #REF! | D48: ='Posto Curitiba_senha capital OK'!$D$66 -> #REF! | E48: ='Posto Curitiba_senha capital OK'!$D$72 -> #REF! | H48: ='Posto Curitiba_senha capital OK'!$Q$60 -> #REF! | I48: ='Posto Curitiba_senha capital OK'!$Q$66 -> #REF! | J48: ='Posto Curitiba_senha capital OK'!$Q$72 -> #REF! | M48: ='Posto Curitiba_senha capital OK'!$P$60 -> #REF! | N48: ='Posto Curitiba_senha capital OK'!$P$66 -> #REF! | O48: ='Posto Curitiba_senha capital OK'!$P$72 -> #REF!
H49: Alterar o acumulado painel cada Posto
B51: Ebtida pré-premiação
B53: Ebitda Pré-Premiação
B54: Ebitda Pré-Premiação Anual Ritmo 2026 | C54: Orçado 2026 | D54: Ritmo 2026 | E54: Ritmo 2026 x Orç 2026
B55: Presidência / Diretoria | C55: =C56+C57 -> 85746.196 | D55: =D56+D57 -> 87312.634 | E55: =D55/C55-1 -> 0.018268309 | F55: Colocar valores para cálculo exato %
B56: Capital Realty / Demercado | C56: 84196.078 | D56: 85439.867 | E56: =D56/C56-1 -> 0.014772529
B57: CR Estacionamentos | C57: 1550.118 | D57: 1872.767 | E57: =D57/C57-1 -> 0.2081448
F142: =F58+#REF! -> #REF!

Sheet Quadro DRE Apresentação
B3: DRE CAPITAL REALTY (Em R$/Mil) | C3: JULHO | H3: ACUMULADO JANEIRO A JULHO | M3: RITMO
C4: Real 2025 | D4: Orç 2026 | E4: Real 2026 | F4: Real 2026 x Orç 2026 | G4: Real 2026 x Real 2025 | H4: Real 2025 | I4: Orç 2026 | J4: Real 2026 | K4: Real 2026 x Orç 2026 | L4: Real 2026 x Real 2025 | M4: Real 2025 | N4: Orç 2026 | O4: Ritmo 2026 | P4: Ritmo 2026 x Orç 2026 | Q4: Ritmo 2026 x Real 2025
B5: 1 - FATURAMENTO BRUTO | C5: ='Matriz senha_capital OK'!B104/1000 -> 5430.4329 | D5: ='Matriz senha_capital OK'!C104/1000 -> 5715.351 | E5: ='Matriz senha_capital OK'!D104/1000 -> 6126.79 | F5: =IFERROR(E5/D5-1," ") -> 0.071988408 | G5: =IFERROR(E5/C5-1," ") -> 0.12823233 | H5: ='Matriz senha_capital OK'!F104/1000 -> 35942.309 | I5: ='Matriz senha_capital OK'!G104/1000 -> 39082.618 | J5: ='Matriz senha_capital OK'!H104/1000 -> 39924.895 | K5: =IFERROR(J5/I5-1," ") -> 0.021551197 | L5: =IFERROR(J5/H5-1," ") -> 0.11080494 | M5: ='Matriz senha_capital OK'!J104/1000 -> 63033.157 | N5: ='Matriz senha_capital OK'!K104/1000 -> 68326.437 | O5: ='Matriz senha_capital OK'!L104/1000 -> 69704.868 | P5: =IFERROR(O5/N5-1," ") -> 0.020174189 | Q5: =IFERROR(O5/M5-1," ") -> 0.10584447
B6: 2 - DEDUÇÃO DE FATURAMENTO | C6: ='Matriz senha_capital OK'!B105/1000 -> -198.2108 | D6: ='Matriz senha_capital OK'!C105/1000 -> -208.61031 | E6: ='Matriz senha_capital OK'!D105/1000 -> -223.62784 | F6: =IFERROR(E6/D6-1," ") -> 0.071988436 | G6: =IFERROR(E6/C6-1," ") -> 0.12823237 | H6: ='Matriz senha_capital OK'!F105/1000 -> -1465.1856 | I6: ='Matriz senha_capital OK'!G105/1000 -> -1426.5156 | J6: ='Matriz senha_capital OK'!H105/1000 -> -1457.2586 | K6: =IFERROR(J6/I6-1," ") -> 0.021551178 | L6: =IFERROR(J6/H6-1," ") -> -0.0054101884 | M6: ='Matriz senha_capital OK'!J105/1000 -> -2455.084 | N6: ='Matriz senha_capital OK'!K105/1000 -> -2493.915 | O6: ='Matriz senha_capital OK'!L105/1000 -> -2544.2276 | P6: =IFERROR(O6/N6-1," ") -> 0.02017418 | Q6: =IFERROR(O6/M6-1," ") -> 0.036309817
B7: 3 - FATURAMENTO LÍQUIDO | C7: ='Matriz senha_capital OK'!B106/1000 -> 5232.2221 | D7: =D5+D6 -> 5506.7407 | E7: =E5+E6 -> 5903.1622 | F7: =IFERROR(E7/D7-1," ") -> 0.071988407 | G7: =IFERROR(E7/C7-1," ") -> 0.12823233 | H7: ='Matriz senha_capital OK'!F106/1000 -> 34477.124 | I7: =I5+I6 -> 37656.102 | J7: ='Matriz senha_capital OK'!H106/1000 -> 38467.636 | K7: =IFERROR(J7/I7-1," ") -> 0.021551198 | L7: =IFERROR(J7/H7-1," ") -> 0.11574378 | M7: ='Matriz senha_capital OK'!J106/1000 -> 60578.073 | N7: ='Matriz senha_capital OK'!K106/1000 -> 65832.522 | O7: ='Matriz senha_capital OK'!L106/1000 -> 67160.64 | P7: =IFERROR(O7/N7-1," ") -> 0.02017419 | Q7: =IFERROR(O7/M7-1," ") -> 0.10866255
B8: 4 - CUSTO MERCADORIA VENDIDA | C8: ='Matriz senha_capital OK'!B107/1000 -> 0 | D8: ='Matriz senha_capital OK'!C107/1000 -> 0 | E8: ='Matriz senha_capital OK'!D107/1000 -> 0 | F8: 0 | G8: =IFERROR(E8/C8-1," ") | H8: ='Matriz senha_capital OK'!F107/1000 -> -75.10715 | I8: ='Matriz senha_capital OK'!G107/1000 -> 0 | J8: ='Matriz senha_capital OK'!H107/1000 -> 0 | K8: =IFERROR(J8/I8-1," ") | L8: =IFERROR(J8/H8-1," ") -> -1 | M8: -75 | N8: ='Matriz senha_capital OK'!M107/1000 -> 0 | O8: ='Matriz senha_capital OK'!N107/1000 -> 0 | P8: 0 | Q8: =IFERROR(O8/M8-1," ") -> -1
B9: 5 - LUCRO BRUTO | C9: =C7+C8 -> 5232.2221 | D9: =D7+D8 -> 5506.7407 | E9: =E7+E8 -> 5903.1622 | F9: =IFERROR(E9/D9-1," ") -> 0.071988407 | G9: =IFERROR(E9/C9-1," ") -> 0.12823233 | H9: =H7+H8 -> 34402.017 | I9: =I7+I8 -> 37656.102 | J9: ='Matriz senha_capital OK'!H108/1000 -> 38467.636 | K9: =IFERROR(J9/I9-1," ") -> 0.021551198 | L9: =IFERROR(J9/H9-1," ") -> 0.11817969 | M9: =M7+M8 -> 60503.073 | N9: =N7+N8 -> 65832.522 | O9: =O7+O8 -> 67160.64 | P9: =IFERROR(O9/N9-1," ") -> 0.02017419 | Q9: =IFERROR(O9/M9-1," ") -> 0.11003685
B10: 6 - DESPESAS OPERACIONAIS | C10: ='Matriz senha_capital OK'!B109/1000 -> -1147.1667 | D10: ='Matriz senha_capital OK'!C109/1000 -> -1033.655 | E10: ='Matriz senha_capital OK'!D109/1000 -> -928.21331 | F10: =IFERROR(E10/D10-1," ") -> -0.10200855 | G10: =IFERROR(E10/C10-1," ") -> -0.19086451 | H10: ='Matriz senha_capital OK'!F109/1000 -> -5926.3496 | I10: ='Matriz senha_capital OK'!G109/1000 -> -6878.1816 | J10: ='Matriz senha_capital OK'!H109/1000 -> -6069.5643 | K10: =IFERROR(J10/I10-1," ") -> -0.11756265 | L10: =IFERROR(J10/H10-1," ") -> 0.024165749 | M10: ='Matriz senha_capital OK'!J109/1000 -> -11415.798 | N10: ='Matriz senha_capital OK'!K109/1000 -> -11439.174 | O10: ='Matriz senha_capital OK'!L109/1000 -> -11448.493 | P10: =IFERROR(O10/N10-1," ") -> 0.00081459814 | Q10: =IFERROR(O10/M10-1," ") -> 0.0028639583
B11: 7 - EBITDA | C11: =C9+C10 -> 4085.0554 | D11: =D9+D10 -> 4473.0857 | E11: =E9+E10 -> 4974.9488 | F11: =IFERROR(E11/D11-1," ") -> 0.11219618 | G11: =IFERROR(E11/C11-1," ") -> 0.21784122 | H11: =H9+H10 -> 28475.667 | I11: =I9+I10 -> 30777.921 | J11: =J9+J10 -> 32398.072 | K11: =IFERROR(J11/I11-1," ") -> 0.052640053 | L11: =IFERROR(J11/H11-1," ") -> 0.13774585 | M11: =M9+M10 -> 49087.274 | N11: =N9+N10 -> 54393.348 | O11: =O9+O10 -> 55712.148 | P11: =IFERROR(O11/N11-1," ") -> 0.024245602 | Q11: =IFERROR(O11/M11-1," ") -> 0.13496111
B12: 8 - DEPRECIAÇÃO | C12: ='Matriz senha_capital OK'!B111/1000 -> -418.15369 | D12: ='Matriz senha_capital OK'!C111/1000 -> -468.14301 | E12: ='Matriz senha_capital OK'!D111/1000 -> -436.85704 | F12: =IFERROR(E12/D12-1," ") -> -0.066829942 | G12: =IFERROR(E12/C12-1," ") -> 0.044728411 | H12: ='Matriz senha_capital OK'!F111/1000 -> -2118.7395 | I12: ='Matriz senha_capital OK'!G111/1000 -> -3160.5392 | J12: ='Matriz senha_capital OK'!H111/1000 -> -2996.9021 | K12: =IFERROR(J12/I12-1," ") -> -0.051775045 | L12: =IFERROR(J12/H12-1," ") -> 0.41447406 | M12: ='Matriz senha_capital OK'!J111/1000 -> -4218.9355 | N12: ='Matriz senha_capital OK'!K111/1000 -> -5667.3463 | O12: ='Matriz senha_capital OK'!L111/1000 -> -5410.2167 | P12: =IFERROR(O12/N12-1," ") -> -0.045370372 | Q12: =IFERROR(O12/M12-1," ") -> 0.28236533
B13: 9 - RESULTADO OPERACIONAL | C13: =C11+C12 -> 3666.9017 | D13: =D11+D12 -> 4004.9427 | E13: =E11+E12 -> 4538.0918 | F13: =IFERROR(E13/D13-1," ") -> 0.13312278 | G13: =IFERROR(E13/C13-1," ") -> 0.23758207 | H13: =H11+H12 -> 26356.927 | I13: =I11+I12 -> 27617.381 | J13: =J11+J12 -> 29401.17 | K13: =IFERROR(J13/I13-1," ") -> 0.06458934 | L13: =IFERROR(J13/H13-1," ") -> 0.11550066 | M13: =M11+M12 -> 44868.339 | N13: =N11+N12 -> 48726.002 | O13: =O11+O12 -> 50301.931 | P13: =IFERROR(O13/N13-1," ") -> 0.032342672 | Q13: =IFERROR(O13/M13-1," ") -> 0.12110081
B14: 10 - OUTRAS RECEITAS E DESPESAS | C14: =C15+C16 -> 261.44248 | D14: ='Matriz senha_capital OK'!C113/1000 -> 46.67786 | E14: ='Matriz senha_capital OK'!D113/1000 -> 148.46575 | F14: =IFERROR(E14/D14-1," ") -> 2.180646 | G14: =IFERROR(E14/C14-1," ") -> -0.43212844 | H14: =H15+H16 -> 1823.1387 | I14: =I15+I16 -> 325.64952 | J14: =J15+J16 -> 766.17974 | K14: =IFERROR(J14/I14-1," ") -> 1.3527741 | L14: =IFERROR(J14/H14-1," ") -> -0.57974688 | M14: =M16+M15 -> 2687.7722 | N14: =N16+N15 -> 598.75397 | O14: =O16+O15 -> 932.25843 | P14: =IFERROR(O14/N14-1," ") -> 0.55699749 | Q14: =IFERROR(O14/M14-1," ") -> -0.65314827 | S14: 37222.007
B15: 10.1 - RECEITAS FINANCEIRAS | C15: ='Matriz senha_capital OK'!B114/1000 -> 290.21771 | D15: ='Matriz senha_capital OK'!C114/1000 -> 65.4437 | E15: ='Matriz senha_capital OK'!D114/1000 -> 166.96791 | F15: =IFERROR(E15/D15-1," ") -> 1.5513214 | G15: =IFERROR(E15/C15-1," ") -> -0.42468049 | H15: ='Matriz senha_capital OK'!F114/1000 -> 2156.3531 | I15: ='Matriz senha_capital OK'!G114/1000 -> 465.44533 | J15: ='Matriz senha_capital OK'!H114/1000 -> 908.45988 | K15: =IFERROR(J15/I15-1," ") -> 0.95180792 | L15: =IFERROR(J15/H15-1," ") -> -0.57870541 | M15: ='Matriz senha_capital OK'!J114/1000 -> 3135.2433 | N15: ='Matriz senha_capital OK'!K114/1000 -> 825.71263 | O15: ='Matriz senha_capital OK'!L114/1000 -> 1161.7014 | P15: =IFERROR(O15/N15-1," ") -> 0.40690765 | Q15: =IFERROR(O15/M15-1," ") -> -0.62947009 | S15: 382
B16: 10.2 - DESPESAS FINANCEIRAS | C16: ='Matriz senha_capital OK'!B115/1000 -> -28.77523 | D16: ='Matriz senha_capital OK'!C115/1000 -> -18.76584 | E16: ='Matriz senha_capital OK'!D115/1000 -> -18.50216 | F16: =IFERROR(E16/D16-1," ") -> -0.014051063 | G16: =IFERROR(E16/C16-1," ") -> -0.35701087 | H16: ='Matriz senha_capital OK'!F115/1000 -> -333.21435 | I16: ='Matriz senha_capital OK'!G115/1000 -> -139.79581 | J16: ='Matriz senha_capital OK'!H115/1000 -> -142.28014 | K16: =IFERROR(J16/I16-1," ") -> 0.017771133 | L16: =IFERROR(J16/H16-1," ") -> -0.57300716 | M16: ='Matriz senha_capital OK'!J115/1000 -> -447.47111 | N16: ='Matriz senha_capital OK'!K115/1000 -> -226.95866 | O16: ='Matriz senha_capital OK'!L115/1000 -> -229.44299 | P16: =IFERROR(O16/N16-1," ") -> 0.010946178 | Q16: =IFERROR(O16/M16-1," ") -> -0.48724513 | S16: -168
B17: 11 - LUCRO ANTES DO IR/CSLL | C17: =C13+C14 -> 3928.3442 | D17: =D13+D14 -> 4051.6206 | E17: =E13+E14 -> 4686.5576 | F17: =IFERROR(E17/D17-1," ") -> 0.15671186 | G17: =IFERROR(E17/C17-1," ") -> 0.19301093 | H17: =H13+H14 -> 28180.066 | I17: =I13+I14 -> 27943.031 | J17: =J13+J14 -> 30167.35 | K17: =IFERROR(J17/I17-1," ") -> 0.079601911 | L17: =IFERROR(J17/H17-1," ") -> 0.070520893 | M17: =M13+M14 -> 47556.111 | N17: =N13+N14 -> 49324.756 | O17: =O13+O14 -> 51234.189 | P17: =IFERROR(O17/N17-1," ") -> 0.038711465 | Q17: =IFERROR(O17/M17-1," ") -> 0.077341865
B18: 12 - IR/CSLL | C18: ='Matriz senha_capital OK'!B117/1000 -> -687.93352 | D18: ='Matriz senha_capital OK'!C117/1000 -> -705.80683 | E18: ='Matriz senha_capital OK'!D117/1000 -> -774.85172 | F18: =IFERROR(E18/D18-1," ") -> 0.09782406 | G18: =IFERROR(E18/C18-1," ") -> 0.1263468 | H18: ='Matriz senha_capital OK'!F117/1000 -> -4593.4736 | I18: ='Matriz senha_capital OK'!G117/1000 -> -4832.5325 | J18: ='Matriz senha_capital OK'!H117/1000 -> -5025.1317 | K18: =IFERROR(J18/I18-1," ") -> 0.039854701 | L18: =IFERROR(J18/H18-1," ") -> 0.093972028 | M18: ='Matriz senha_capital OK'!J117/1000 -> -7868.4805 | N18: ='Matriz senha_capital OK'!K117/1000 -> -8452.5842 | O18: ='Matriz senha_capital OK'!L117/1000 -> -8672.9185 | P18: =IFERROR(O18/N18-1," ") -> 0.026067095 | Q18: =IFERROR(O18/M18-1," ") -> 0.1022355
B19: 13 - LUCRO LÍQUIDO | C19: =C17+C18 -> 3240.4107 | D19: =D17+D18 -> 3345.8137 | E19: =E17+E18 -> 3911.7058 | F19: =IFERROR(E19/D19-1," ") -> 0.16913437 | G19: =IFERROR(E19/C19-1," ") -> 0.20716361 | H19: =H17+H18 -> 23586.593 | I19: =I17+I18 -> 23110.498 | J19: =J17+J18 -> 25142.218 | K19: =IFERROR(J19/I19-1," ") -> 0.087913271 | L19: =IFERROR(J19/H19-1," ") -> 0.0659538 | M19: =M17+M18 -> 39687.63 | N19: =N17+N18 -> 40872.172 | O19: =O17+O18 -> 42561.271 | P19: =IFERROR(O19/N19-1," ") -> 0.041326388 | Q19: =IFERROR(O19/M19-1," ") -> 0.072406447
B20: Margem EBITDA/ROL | C20: =C11/C7 -> 0.78074961 | D20: =D11/D7 -> 0.81229279 | E20: =E11/E7 -> 0.84275998 | H20: =H11/H7 -> 0.82592931 | I20: =I11/I7 -> 0.81734218 | J20: =J11/J7 -> 0.84221634 | M20: =M11/M7 -> 0.81031423 | N20: =N11/N7 -> 0.82623825 | O20: =O11/O7 -> 0.82953568
B23: DRE DEMERCADO (Em R$/Mil) | C23: =C3 -> JULHO | H23: =H3 -> ACUMULADO JANEIRO A JULHO | M23: =M3 -> RITMO
C24: Real 2025 | D24: Orç 2026 | E24: Real 2026 | F24: Real 2026 x Orç 2026 | G24: Real 2026 x Real 2025 | H24: Real 2025 | I24: Orç 2026 | J24: Real 2026 | K24: Real 2026 x Orç 2026 | L24: Real 2026 x Real 2025 | M24: Real 2025 | N24: Orç 2026 | O24: Ritmo 2026 | P24: Ritmo 2026 x Orç 2026 | Q24: Ritmo 2026 x Real 2025
B25: 1 - FATURAMENTO BRUTO | C25: ='Demercado_senha capital OK'!B110/1000 -> 2564.2398 | D25: ='Demercado_senha capital OK'!C110/1000 -> 3102.9476 | E25: ='Demercado_senha capital OK'!D110/1000 -> 3145.0303 | F25: =IFERROR(E25/D25-1," ") -> 0.013562162 | G25: =IFERROR(E25/C25-1," ") -> 0.22649616 | H25: ='Demercado_senha capital OK'!F110/1000 -> 15234.411 | I25: ='Demercado_senha capital OK'!G110/1000 -> 17868.539 | J25: ='Demercado_senha capital OK'!H110/1000 -> 18096.707 | K25: =IFERROR(J25/I25-1," ") -> 0.012769262 | L25: =IFERROR(J25/H25-1," ") -> 0.1878836 | M25: ='Demercado_senha capital OK'!J110/1000 -> 31012.395 | N25: ='Demercado_senha capital OK'!K110/1000 -> 36865.671 | O25: ='Demercado_senha capital OK'!L110/1000 -> 37487.177 | P25: =IFERROR(O25/N25-1," ") -> 0.01685866 | Q25: =IFERROR(O25/M25-1," ") -> 0.20878047
B26: 2 - DEDUÇÃO DE FATURAMENTO | C26: ='Demercado_senha capital OK'!B111/1000 -> -93.59476 | D26: ='Demercado_senha capital OK'!C111/1000 -> -113.25759 | E26: ='Demercado_senha capital OK'!D111/1000 -> -114.79361 | F26: =IFERROR(E26/D26-1," ") -> 0.013562182 | G26: =IFERROR(E26/C26-1," ") -> 0.22649612 | H26: ='Demercado_senha capital OK'!F111/1000 -> -576.54486 | I26: ='Demercado_senha capital OK'!G111/1000 -> -652.20168 | J26: ='Demercado_senha capital OK'!H111/1000 -> -660.52983 | K26: =IFERROR(J26/I26-1," ") -> 0.012769286 | L26: =IFERROR(J26/H26-1," ") -> 0.14566945 | M26: ='Demercado_senha capital OK'!J111/1000 -> -1152.4413 | N26: ='Demercado_senha capital OK'!K111/1000 -> -1345.597 | O26: ='Demercado_senha capital OK'!L111/1000 -> -1368.282 | P26: =IFERROR(O26/N26-1," ") -> 0.016858673 | Q26: =IFERROR(O26/M26-1," ") -> 0.18728997
B27: 3 - FATURAMENTO LÍQUIDO | C27: =C25+C26 -> 2470.6451 | D27: =D25+D26 -> 2989.6901 | E27: =E25+E26 -> 3030.2367 | F27: =IFERROR(E27/D27-1," ") -> 0.013562162 | G27: =IFERROR(E27/C27-1," ") -> 0.22649616 | H27: =H25+H26 -> 14657.866 | I27: =I25+I26 -> 17216.337 | J27: =J25+J26 -> 17436.177 | K27: =IFERROR(J27/I27-1," ") -> 0.012769261 | L27: =IFERROR(J27/H27-1," ") -> 0.18954403 | M27: ='Demercado_senha capital OK'!J112/1000 -> 29859.953 | N27: ='Demercado_senha capital OK'!K112/1000+1 -> 35521.074 | O27: ='Demercado_senha capital OK'!L112/1000 -> 36118.895 | P27: =IFERROR(O27/N27-1," ") -> 0.016830032 | Q27: =IFERROR(O27/M27-1," ") -> 0.2096099
B28: 4 - CUSTO MERCADORIA VENDIDA | C28: 0 | D28: 0 | E28: 0 | F28: 0 | G28: 0 | H28: 0 | I28: 0 | J28: 0 | K28: 0 | L28: 0 | M28: 0 | N28: 0 | O28: 0 | P28: 0 | Q28: 0
B29: 5 - LUCRO BRUTO | C29: =C27+C28 -> 2470.6451 | D29: =D27+D28 -> 2989.6901 | E29: =E27+E28 -> 3030.2367 | F29: =IFERROR(E29/D29-1," ") -> 0.013562162 | G29: =IFERROR(E29/C29-1," ") -> 0.22649616 | H29: =H27+H28 -> 14657.866 | I29: =I27+I28 -> 17216.337 | J29: =J27+J28 -> 17436.177 | K29: =IFERROR(J29/I29-1," ") -> 0.012769261 | L29: =IFERROR(J29/H29-1," ") -> 0.18954403 | M29: =M27+M28 -> 29859.953 | N29: =N27+N28 -> 35521.074 | O29: =O27+O28 -> 36118.895 | P29: =IFERROR(O29/N29-1," ") -> 0.016830032 | Q29: =IFERROR(O29/M29-1," ") -> 0.2096099
B30: 6 - DESPESAS OPERACIONAIS | C30: ='Demercado_senha capital OK'!B114/1000 -> -467.70558 | D30: ='Demercado_senha capital OK'!C114/1000 -> -666.56918 | E30: ='Demercado_senha capital OK'!D114/1000 -> -819.70469 | F30: =IFERROR(E30/D30-1," ") -> 0.22973686 | G30: =IFERROR(E30/C30-1," ") -> 0.75260832 | H30: ='Demercado_senha capital OK'!F114/1000 -> -2511.1154 | I30: ='Demercado_senha capital OK'!G114/1000 -> -3561.6644 | J30: ='Demercado_senha capital OK'!H114/1000 -> -3437.9845 | K30: =IFERROR(J30/I30-1," ") -> -0.034725304 | L30: =IFERROR(J30/H30-1," ") -> 0.36910658 | M30: ='Demercado_senha capital OK'!J114/1000 -> -5005.4923 | N30: ='Demercado_senha capital OK'!K114/1000 -> -6812.1206 | O30: ='Demercado_senha capital OK'!L114/1000 -> -7019.4914 | P30: =IFERROR(O30/N30-1," ") -> 0.030441432 | Q30: =IFERROR(O30/M30-1," ") -> 0.40235785
B31: 7 - EBITDA | C31: =C29+C30 -> 2002.9395 | D31: =(D29+D30) -> 2323.1209 | E31: =E29+E30 -> 2210.532 | F31: =IFERROR(E31/D31-1," ") -> -0.048464482 | G31: =IFERROR(E31/C31-1," ") -> 0.10364393 | H31: =H29+H30 -> 12146.751 | I31: =I29+I30 -> 13654.673 | J31: =J29+J30 -> 13998.193 | K31: =IFERROR(J31/I31-1," ") -> 0.025157672 | L31: =IFERROR(J31/H31-1," ") -> 0.1524228 | M31: =M29+M30 -> 24854.461 | N31: =N29+N30-1 -> 28707.954 | O31: =O29+O30 -> 29099.404 | P31: =IFERROR(O31/N31-1," ") -> 0.013635598 | Q31: =IFERROR(O31/M31-1," ") -> 0.17079198
B32: 8 - DEPRECIAÇÃO | C32: ='Demercado_senha capital OK'!B116/1000 -> -217.843 | D32: ='Demercado_senha capital OK'!C116/1000 -> -212.08769 | E32: ='Demercado_senha capital OK'!D116/1000 -> -203.12457 | F32: =IFERROR(E32/D32-1," ") -> -0.042261387 | G32: =IFERROR(E32/C32-1," ") -> -0.067564393 | H32: ='Demercado_senha capital OK'!F116/1000 -> -1306.9351 | I32: ='Demercado_senha capital OK'!G116/1000 -> -1267.0218 | J32: ='Demercado_senha capital OK'!H116/1000 -> -1215.231 | K32: =IFERROR(J32/I32-1," ") -> -0.040875974 | L32: =IFERROR(J32/H32-1," ") -> -0.070167264 | M32: ='Demercado_senha capital OK'!J116/1000 -> -2617.5621 | N32: ='Demercado_senha capital OK'!K116/1000 -> -2628.5893 | O32: ='Demercado_senha capital OK'!L116/1000 -> -2566.0396 | P32: =IFERROR(O32/N32-1," ") -> -0.023795908 | Q32: =IFERROR(O32/M32-1," ") -> -0.019683373
B33: 9 - RESULTADO OPERACIONAL | C33: =C31+C32 -> 1785.0965 | D33: =D31+D32 -> 2111.0332 | E33: =E31+E32 -> 2007.4074 | F33: =IFERROR(E33/D33-1," ") -> -0.049087684 | G33: =IFERROR(E33/C33-1," ") -> 0.12453722 | H33: =H31+H32 -> 10839.816 | I33: =I31+I32 -> 12387.651 | J33: =J31+J32 -> 12782.962 | K33: =IFERROR(J33/I33-1," ") -> 0.031911661 | L33: =IFERROR(J33/H33-1," ") -> 0.17926004 | M33: =M31+M32 -> 22236.899 | N33: =N31+N32 -> 26079.364 | O33: =O31+O32 -> 26533.364 | P33: =IFERROR(O33/N33-1," ") -> 0.017408391 | Q33: =IFERROR(O33/M33-1," ") -> 0.19321332
B34: 10 - OUTRAS RECEITAS E DESPESAS | C34: =C36+C35 -> -546.65769 | D34: =D36+D35 -> -717.49463 | E34: =E36+E35 -> -709.34235 | F34: =IFERROR(E34/D34-1," ") -> -0.011362148 | G34: =IFERROR(E34/C34-1," ") -> 0.29759878 | H34: =H36+H35 -> -3350.106 | I34: =I36+I35 -> -4660.7192 | J34: =J36+J35 -> -4402.2158 | K34: =IFERROR(J34/I34-1," ") -> -0.055464275 | L34: =IFERROR(J34/H34-1," ") -> 0.31405268 | M34: =M36+M35 -> -5944.9179 | N34: =N36+N35 -> -8763.7286 | O34: =O36+O35 -> -8253.7532 | P34: =IFERROR(O34/N34-1," ") -> -0.058191595 | Q34: =IFERROR(O34/M34-1," ") -> 0.38837128
B35: 10.1 - RECEITAS FINANCEIRAS | C35: ='Demercado_senha capital OK'!B119/1000 -> 123.79369 | D35: ='Demercado_senha capital OK'!C119/1000 -> 94.3265 | E35: ='Demercado_senha capital OK'!D119/1000 -> 105.35181 | F35: =IFERROR(E35/D35-1," ") -> 0.11688454 | G35: =IFERROR(E35/C35-1," ") -> -0.1489727 | H35: ='Demercado_senha capital OK'!F119/1000 -> 800.84841 | I35: ='Demercado_senha capital OK'!G119/1000 -> 525.6098 | J35: ='Demercado_senha capital OK'!H119/1000 -> 644.16808 | K35: =IFERROR(J35/I35-1," ") -> 0.2255633 | L35: =IFERROR(J35/H35-1," ") -> -0.19564293 | M35: ='Demercado_senha capital OK'!J119/1000 -> 2150.2974 | N35: ='Demercado_senha capital OK'!K119/1000 -> 791.26861 | O35: ='Demercado_senha capital OK'!L119/1000 -> 1330.3212 | P35: =IFERROR(O35/N35-1," ") -> 0.68125102 | Q35: =IFERROR(O35/M35-1," ") -> -0.38133154
B36: 10.2 - DESPESAS FINANCEIRAS | C36: ='Demercado_senha capital OK'!B120/1000 -> -670.45138 | D36: ='Demercado_senha capital OK'!C120/1000 -> -811.82113 | E36: ='Demercado_senha capital OK'!D120/1000 -> -814.69416 | F36: =IFERROR(E36/D36-1," ") -> 0.0035389939 | G36: =IFERROR(E36/C36-1," ") -> 0.21514279 | H36: ='Demercado_senha capital OK'!F120/1000 -> -4150.9544 | I36: ='Demercado_senha capital OK'!G120/1000 -> -5186.329 | J36: ='Demercado_senha capital OK'!H120/1000 -> -5046.3838 | K36: =IFERROR(J36/I36-1," ") -> -0.026983466 | L36: =IFERROR(J36/H36-1," ") -> 0.21571652 | M36: ='Demercado_senha capital OK'!J120/1000 -> -8095.2153 | N36: ='Demercado_senha capital OK'!K120/1000 -> -9554.9972 | O36: ='Demercado_senha capital OK'!L120/1000 -> -9584.0744 | P36: =IFERROR(O36/N36-1," ") -> 0.0030431417 | Q36: =IFERROR(O36/M36-1," ") -> 0.18391841
B37: 11 - LUCRO ANTES DO IR/CSLL | C37: =C33+C34 -> 1238.4388 | D37: =D33+D34 -> 1393.5385 | E37: =E33+E34 -> 1298.0651 | F37: =IFERROR(E37/D37-1," ") -> -0.068511524 | G37: =IFERROR(E37/C37-1," ") -> 0.048146335 | H37: =H33+H34 -> 7489.7099 | I37: =I33+I34 -> 7726.9321 | J37: =J33+J34 -> 8380.746 | K37: =IFERROR(J37/I37-1," ") -> 0.084614946 | L37: =IFERROR(J37/H37-1," ") -> 0.11896804 | M37: =M33+M34 -> 16291.981 | N37: =N33+N34 -> 17315.636 | O37: =O33+O34 -> 18279.611 | P37: =IFERROR(O37/N37-1," ") -> 0.05567079 | Q37: =IFERROR(O37/M37-1," ") -> 0.1220005
B38: 12 - IR/CSLL | C38: ='Demercado_senha capital OK'!B122/1000 -> -322.49868 | D38: ='Demercado_senha capital OK'!C122/1000 -> -403.18356 | E38: ='Demercado_senha capital OK'!D122/1000 -> -412.32707 | F38: =IFERROR(E38/D38-1," ") -> 0.022678281 | G38: =IFERROR(E38/C38-1," ") -> 0.27853878 | H38: ='Demercado_senha capital OK'!F122/1000 -> -1964.5671 | I38: ='Demercado_senha capital OK'!G122/1000 -> -2315.7846 | J38: ='Demercado_senha capital OK'!H122/1000 -> -2340.9835 | K38: =IFERROR(J38/I38-1," ") -> 0.01088137 | L38: =IFERROR(J38/H38-1," ") -> 0.19160272 | M38: ='Demercado_senha capital OK'!J122/1000 -> -4148.4654 | N38: ='Demercado_senha capital OK'!K122/1000 -> -4678.1656 | O38: ='Demercado_senha capital OK'!L122/1000 -> -4893.3758 | P38: =IFERROR(O38/N38-1," ") -> 0.046003102 | Q38: =IFERROR(O38/M38-1," ") -> 0.17956288
B39: 13 - LUCRO LÍQUIDO | C39: =C37+C38 -> 915.94013 | D39: =D37+D38 -> 990.35499 | E39: =E37+E38 -> 885.73803 | F39: =IFERROR(E39/D39-1," ") -> -0.10563582 | G39: =IFERROR(E39/C39-1," ") -> -0.03297388 | H39: =H37+H38 -> 5525.1427 | I39: =I37+I38 -> 5411.1474 | J39: =J37+J38 -> 6039.7625 | K39: =IFERROR(J39/I39-1," ") -> 0.11617038 | L39: =IFERROR(J39/H39-1," ") -> 0.093141434 | M39: =M37+M38 -> 12143.516 | N39: =N37+N38 -> 12637.47 | O39: =O37+O38 -> 13386.235 | P39: =IFERROR(O39/N39-1," ") -> 0.059249596 | Q39: =IFERROR(O39/M39-1," ") -> 0.10233605
B40: Margem EBITDA/ROL | C40: =C31/C27 -> 0.81069495 | D40: =D31/D27 -> 0.77704405 | E40: =E31/E27 -> 0.72949153 | H40: =H31/H27 -> 0.8286848 | I40: =I31/I27 -> 0.79312299 | J40: =J31/J27 -> 0.80282464 | M40: =M31/M27 -> 0.83236771 | N40: =N31/N27 -> 0.80819497 | O40: =O31/O27 -> 0.80565598
B41: * Sem Equivalência Patrimonial
B43: DRE DEMERCADO (Em R$/Mil) | C43: =C3 -> JULHO | H43: =H3 -> ACUMULADO JANEIRO A JULHO | M43: =M23 -> RITMO
C44: Real 2025 | D44: Orç 2026 | E44: Real 2026 | F44: Real 2026 x Orç 2026 | G44: Real 2026 x Real 2025 | H44: Real 2025 | I44: Orç 2026 | J44: Real 2026 | K44: Real 2026 x Orç 2026 | L44: Real 2026 x Real 2025 | M44: Real 2025 | N44: Orç 2026 | O44: Ritmo 2026 | P44: Ritmo 2026 x Orç 2026 | Q44: Ritmo 2026 x Real 2025
B45: 1 - FATURAMENTO BRUTO | C45: =C25 -> 2564.2398 | D45: =D25 -> 3102.9476 | E45: =E25 -> 3145.0303 | F45: =IFERROR(E45/D45-1," ") -> 0.013562162 | G45: =IFERROR(E45/C45-1," ") -> 0.22649616 | H45: =H25 -> 15234.411 | I45: =I25 -> 17868.539 | J45: =J25 -> 18096.707 | K45: =IFERROR(J45/I45-1," ") -> 0.012769262 | L45: =IFERROR(J45/H45-1," ") -> 0.1878836 | M45: =M25 -> 31012.395 | N45: =N25 -> 36865.671 | O45: =O25 -> 37487.177 | P45: =IFERROR(O45/N45-1," ") -> 0.01685866 | Q45: =IFERROR(O45/M45-1," ") -> 0.20878047
B46: 2 - DEDUÇÃO DE FATURAMENTO | C46: =C26 -> -93.59476 | D46: =D26 -> -113.25759 | E46: =E26 -> -114.79361 | F46: =IFERROR(E46/D46-1," ") -> 0.013562182 | G46: =IFERROR(E46/C46-1," ") -> 0.22649612 | H46: =H26 -> -576.54486 | I46: =I26 -> -652.20168 | J46: =J26 -> -660.52983 | K46: =IFERROR(J46/I46-1," ") -> 0.012769286 | L46: =IFERROR(J46/H46-1," ") -> 0.14566945 | M46: =M26 -> -1152.4413 | N46: =N26 -> -1345.597 | O46: =O26 -> -1368.282 | P46: =IFERROR(O46/N46-1," ") -> 0.016858673 | Q46: =IFERROR(O46/M46-1," ") -> 0.18728997
B47: 3 - FATURAMENTO LÍQUIDO | C47: =C45+C46 -> 2470.6451 | D47: =D45+D46 -> 2989.6901 | E47: =E45+E46 -> 3030.2367 | F47: =IFERROR(E47/D47-1," ") -> 0.013562162 | G47: =IFERROR(E47/C47-1," ") -> 0.22649616 | H47: =H27 -> 14657.866 | I47: =I27 -> 17216.337 | J47: =J27 -> 17436.177 | K47: =IFERROR(J47/I47-1," ") -> 0.012769261 | L47: =IFERROR(J47/H47-1," ") -> 0.18954403 | M47: =M45+M46 -> 29859.953 | N47: =N45+N46 -> 35520.074 | O47: =O45+O46 -> 36118.895 | P47: =IFERROR(O47/N47-1," ") -> 0.016858659 | Q47: =IFERROR(O47/M47-1," ") -> 0.2096099
B48: 4 - CUSTO MERCADORIA VENDIDA | C48: 0 | D48: 0 | E48: 0 | F48: 0 | G48: 0 | H48: 0 | I48: 0 | J48: 0 | K48: 0 | L48: 0 | M48: 0 | N48: 0 | O48: 0 | P48: 0 | Q48: 0
B49: 5 - LUCRO BRUTO | C49: =C47+C48 -> 2470.6451 | D49: =D47+D48 -> 2989.6901 | E49: =E47+E48 -> 3030.2367 | F49: =IFERROR(E49/D49-1," ") -> 0.013562162 | G49: =IFERROR(E49/C49-1," ") -> 0.22649616 | H49: =H29 -> 14657.866 | I49: =I29 -> 17216.337 | J49: =J29 -> 17436.177 | K49: =IFERROR(J49/I49-1," ") -> 0.012769261 | L49: =IFERROR(J49/H49-1," ") -> 0.18954403 | M49: =M47+M48 -> 29859.953 | N49: =N47+N48 -> 35520.074 | O49: =O47+O48 -> 36118.895 | P49: =IFERROR(O49/N49-1," ") -> 0.016858659 | Q49: =IFERROR(O49/M49-1," ") -> 0.2096099
B50: 6 - DESPESAS OPERACIONAIS | C50: =C30 -> -467.70558 | D50: =D30 -> -666.56918 | E50: =E30 -> -819.70469 | F50: =IFERROR(E50/D50-1," ") -> 0.22973686 | G50: =IFERROR(E50/C50-1," ") -> 0.75260832 | H50: =H30 -> -2511.1154 | I50: =I30 -> -3561.6644 | J50: =J30 -> -3437.9845 | K50: =IFERROR(J50/I50-1," ") -> -0.034725304 | L50: =IFERROR(J50/H50-1," ") -> 0.36910658 | M50: =M30 -> -5005.4923 | N50: =N30 -> -6812.1206 | O50: =O30 -> -7019.4914 | P50: =IFERROR(O50/N50-1," ") -> 0.030441432 | Q50: =IFERROR(O50/M50-1," ") -> 0.40235785
B51: 7 - EBITDA | C51: =C49+C50 -> 2002.9395 | D51: =(D49+D50) -> 2323.1209 | E51: =E49+E50 -> 2210.532 | F51: =IFERROR(E51/D51-1," ") -> -0.048464482 | G51: =IFERROR(E51/C51-1," ") -> 0.10364393 | H51: =H31 -> 12146.751 | I51: =I31 -> 13654.673 | J51: =J31 -> 13998.193 | K51: =IFERROR(J51/I51-1," ") -> 0.025157672 | L51: =IFERROR(J51/H51-1," ") -> 0.1524228 | M51: =M49+M50 -> 24854.461 | N51: =N49+N50 -> 28707.954 | O51: =O49+O50 -> 29099.404 | P51: =IFERROR(O51/N51-1," ") -> 0.013635598 | Q51: =IFERROR(O51/M51-1," ") -> 0.17079198
B52: 8 - DEPRECIAÇÃO | C52: =C32 -> -217.843 | D52: =D32 -> -212.08769 | E52: =E32 -> -203.12457 | F52: =IFERROR(E52/D52-1," ") -> -0.042261387 | G52: =IFERROR(E52/C52-1," ") -> -0.067564393 | H52: =H32 -> -1306.9351 | I52: =I32 -> -1267.0218 | J52: =J32 -> -1215.231 | K52: =IFERROR(J52/I52-1," ") -> -0.040875974 | L52: =IFERROR(J52/H52-1," ") -> -0.070167264 | M52: =M32 -> -2617.5621 | N52: =N32 -> -2628.5893 | O52: =O32 -> -2566.0396 | P52: =IFERROR(O52/N52-1," ") -> -0.023795908 | Q52: =IFERROR(O52/M52-1," ") -> -0.019683373
B53: 9 - RESULTADO OPERACIONAL | C53: =C51+C52 -> 1785.0965 | D53: =D51+D52 -> 2111.0332 | E53: =E51+E52 -> 2007.4074 | F53: =IFERROR(E53/D53-1," ") -> -0.049087684 | G53: =IFERROR(E53/C53-1," ") -> 0.12453722 | H53: =H33 -> 10839.816 | I53: =I33 -> 12387.651 | J53: =J33 -> 12782.962 | K53: =IFERROR(J53/I53-1," ") -> 0.031911661 | L53: =IFERROR(J53/H53-1," ") -> 0.17926004 | M53: =M51+M52 -> 22236.899 | N53: =N51+N52 -> 26079.364 | O53: =O51+O52 -> 26533.364 | P53: =IFERROR(O53/N53-1," ") -> 0.017408391 | Q53: =IFERROR(O53/M53-1," ") -> 0.19321332
B54: 10 - OUTRAS RECEITAS E DESPESAS | C54: =SUM(C55:C57) -> 634.59618 | D54: =SUM(D55:D57) -> 381.56965 | E54: =SUM(E55:E57) -> 623.57589 | F54: =IFERROR(E54/D54-1," ") -> 0.63423868 | G54: =IFERROR(E54/C54-1," ") -> -0.017365838 | H54: =H57+H56+H55 -> 4117.7336 | I54: =I57+I56+I55 -> 2568.8858 | J54: =J57+J56+J55 -> 3441.4315 | K54: =IFERROR(J54/I54-1," ") -> 0.33965923 | L54: =IFERROR(J54/H54-1," ") -> -0.16424133 | M54: =SUM(M55:M57) -> 8107.0821 | N54: =SUM(N55:N57) -> 5274.2714 | O54: =SUM(O55:O57) -> 7258.4247 | P54: =IFERROR(O54/N54-1," ") -> 0.37619475 | Q54: =IFERROR(O54/M54-1," ") -> -0.104681
B55: 10.1 - RECEITAS FINANCEIRAS | C55: =C35 -> 123.79369 | D55: =D35 -> 94.3265 | E55: =E35 -> 105.35181 | F55: =IFERROR(E55/D55-1," ") -> 0.11688454 | G55: =IFERROR(E55/C55-1," ") -> -0.1489727 | H55: =H35 -> 800.84841 | I55: =I35 -> 525.6098 | J55: =J35 -> 644.16808 | K55: =IFERROR(J55/I55-1," ") -> 0.2255633 | L55: =IFERROR(J55/H55-1," ") -> -0.19564293 | M55: =M35 -> 2150.2974 | N55: =N35 -> 791.26861 | O55: =O35 -> 1330.3212 | P55: =IFERROR(O55/N55-1," ") -> 0.68125102 | Q55: =IFERROR(O55/M55-1," ") -> -0.38133154
B56: 10.2 - DESPESAS FINANCEIRAS | C56: =C36 -> -670.45138 | D56: =D36 -> -811.82113 | E56: =E36 -> -814.69416 | F56: =IFERROR(E56/D56-1," ") -> 0.0035389939 | G56: =IFERROR(E56/C56-1," ") -> 0.21514279 | H56: =H36 -> -4150.9544 | I56: =I36 -> -5186.329 | J56: =J36 -> -5046.3838 | K56: =IFERROR(J56/I56-1," ") -> -0.026983466 | L56: =IFERROR(J56/H56-1," ") -> 0.21571652 | M56: =M36 -> -8095.2153 | N56: =N36 -> -9554.9972 | O56: =O36 -> -9584.0744 | P56: =IFERROR(O56/N56-1," ") -> 0.0030431417 | Q56: =IFERROR(O56/M56-1," ") -> 0.18391841
B57: 10.3 - EQUIVALÊNCIA PATRIMONIAL | C57: =(C208*42.5%)+('DCL_D-ESPAÇO '!C18*0.85%) -> 1181.2539 | D57: =(D208*0.425)+('DCL_D-ESPAÇO '!D18*0.85%) -> 1099.0643 | E57: =(E208*0.425)+('DCL_D-ESPAÇO '!E18*0.85%) -> 1332.9182 | F57: =IFERROR(E57/D57-1," ") -> 0.2127755 | G57: =IFERROR(E57/C57-1," ") -> 0.12839269 | H57: =(H208*0.425)+('DCL_D-ESPAÇO '!H18*0.85%) -> 7467.8396 | I57: =(I208*0.425)+('DCL_D-ESPAÇO '!I18*0.85%) -> 7229.6049 | J57: =(J208*0.425)+('DCL_D-ESPAÇO '!J18*0.85%) -> 7843.6473 | K57: =IFERROR(J57/I57-1," ") -> 0.084934428 | L57: =IFERROR(J57/H57-1," ") -> 0.050323489 | M57: 14052 | N57: 14038 | O57: =(O208*0.425)+('DCL_D-ESPAÇO '!O18*0.85%) -> 15512.178 | P57: =IFERROR(O57/N57-1," ") -> 0.10501339 | Q57: =IFERROR(O57/M57-1," ") -> 0.10391246
B58: 11 - LUCRO ANTES DO IR/CSLL | C58: =C53+C54 -> 2419.6927 | D58: =D53+D54 -> 2492.6028 | E58: =E53+E54 -> 2630.9833 | F58: =IFERROR(E58/D58-1," ") -> 0.055516468 | G58: =IFERROR(E58/C58-1," ") -> 0.087321277 | H58: =H54+H53 -> 14957.549 | I58: =I54+I53 -> 14956.537 | J58: =J54+J53 -> 16224.393 | K58: =IFERROR(J58/I58-1," ") -> 0.084769375 | L58: =IFERROR(J58/H58-1," ") -> 0.08469595 | M58: =M53+M54 -> 30343.981 | N58: =N53+N54 -> 31353.636 | O58: =O53+O54 -> 33791.789 | P58: =IFERROR(O58/N58-1," ") -> 0.077763008 | Q58: =IFERROR(O58/M58-1," ") -> 0.1136241
B59: 12 - IR/CSLL | C59: =C38 -> -322.49868 | D59: =D38 -> -403.18356 | E59: =E38 -> -412.32707 | F59: =IFERROR(E59/D59-1," ") -> 0.022678281 | G59: =IFERROR(E59/C59-1," ") -> 0.27853878 | H59: =H38 -> -1964.5671 | I59: =I38 -> -2315.7846 | J59: =J38 -> -2340.9835 | K59: =IFERROR(J59/I59-1," ") -> 0.01088137 | L59: =IFERROR(J59/H59-1," ") -> 0.19160272 | M59: =M38 -> -4148.4654 | N59: =N38 -> -4678.1656 | O59: =O38 -> -4893.3758 | P59: =IFERROR(O59/N59-1," ") -> 0.046003102 | Q59: =IFERROR(O59/M59-1," ") -> 0.17956288
B60: 13 - LUCRO LÍQUIDO | C60: =C58+C59 -> 2097.194 | D60: =D58+D59 -> 2089.4193 | E60: =E58+E59 -> 2218.6563 | F60: =IFERROR(E60/D60-1," ") -> 0.061853069 | G60: =IFERROR(E60/C60-1," ") -> 0.057916561 | H60: =H58+H59 -> 12992.982 | I60: =I58+I59 -> 12640.752 | J60: =J58+J59 -> 13883.41 | K60: =IFERROR(J60/I60-1," ") -> 0.098305651 | L60: =IFERROR(J60/H60-1," ") -> 0.068531415 | M60: =M58+M59 -> 26195.516 | N60: =N58+N59 -> 26675.47 | O60: =O58+O59 -> 28898.413 | P60: =IFERROR(O60/N60-1," ") -> 0.083332848 | Q60: =IFERROR(O60/M60-1," ") -> 0.10318168
B61: Margem EBITDA/ROL | C61: =C51/C47 -> 0.81069495 | D61: =D51/D47 -> 0.77704405 | E61: =E51/E47 -> 0.72949153 | H61: =H51/H47 -> 0.8286848 | I61: =I51/I47 -> 0.79312299 | J61: =J51/J47 -> 0.80282464 | M61: =M51/M47 -> 0.83236771 | N61: =N51/N47 -> 0.80821772 | O61: =O51/O47 -> 0.80565598
B62: * Com Equivalência Patrimonial da DCL Administração e Participações e DCL Shopping Center. - Linha lucro líquido
B65: DRE GAROTO (Em R$/Mil) | C65: =C3 -> JULHO | H65: ACUMULADO JANEIRO A NOVEMBRO | M65: RITMO
C66: Real 2023 | D66: Orç 2024 | E66: Real 2024 | F66: Real 2024 x Orç 2024 | G66: Real 2024 x Real 2023 | H66: Real 2022 | I66: Orç 2023 | J66: Real 2023 | K66: ∆ Real 2023 x Real 2022 | L66: ∆ Real 2023 x Orç 2023 | M66: Real 2023 | N66: Orç 2024 | O66: Ritmo 2024 | P66: Ritmo 2024 x Orç 2024 | Q66: Ritmo 2024 x Real 2023
B67: 1 - FATURAMENTO BRUTO | F67: =IFERROR(E67/C67-1," ") | G67: =IFERROR(E67/D67-1," ") | H67: ='Garoto senha_capital OK'!F139/1000 -> #REF! | I67: ='Garoto senha_capital OK'!G139/1000 -> #REF! | J67: ='Garoto senha_capital OK'!H139/1000 -> #REF! | K67: =IFERROR(J67/H67-1," ") | L67: =IFERROR(J67/I67-1," ") | P67: =IFERROR(O67/M67-1," ") | Q67: =IFERROR(O67/N67-1," ") | S67: 37
B68: 2 - DEDUÇÃO DE FATURAMENTO | F68: =IFERROR(E68/C68-1," ") | G68: =IFERROR(E68/D68-1," ") | H68: ='Garoto senha_capital OK'!F140/1000 -> #REF! | I68: ='Garoto senha_capital OK'!G140/1000 -> #REF! | J68: ='Garoto senha_capital OK'!H140/1000 -> #REF! | K68: =IFERROR(J68/H68-1," ") | L68: =IFERROR(J68/I68-1," ") | P68: =IFERROR(O68/M68-1," ") | Q68: =IFERROR(O68/N68-1," ") | S68: -270
B69: 3 - FATURAMENTO LÍQUIDO | F69: =IFERROR(E69/C69-1," ") | G69: =IFERROR(E69/D69-1," ") | H69: =H67+H68 -> #REF! | I69: =I67+I68 -> #REF! | J69: =J67+J68 -> #REF! | K69: =IFERROR(J69/H69-1," ") | L69: =IFERROR(J69/I69-1," ") | P69: =IFERROR(O69/M69-1," ") | Q69: =IFERROR(O69/N69-1," ") | S69: =S67+S68 -> -233
B70: 4 - CUSTO MERCADORIA VENDIDA | F70: 0 | G70: 0 | H70: 0 | I70: 0 | J70: 0 | K70: 0 | L70: 0 | P70: 0 | Q70: 0
B71: 5 - LUCRO BRUTO | F71: =IFERROR(E71/C71-1," ") | G71: =IFERROR(E71/D71-1," ") | H71: =H69 -> #REF! | I71: =I69 -> #REF! | J71: =J69 -> #REF! | K71: =IFERROR(J71/H71-1," ") | L71: =IFERROR(J71/I71-1," ") | P71: =IFERROR(O71/M71-1," ") | Q71: =IFERROR(O71/N71-1," ")
B72: 6 - DESPESAS OPERACIONAIS | F72: =IFERROR(E72/C72-1," ") | G72: =IFERROR(E72/D72-1," ") | H72: ='Garoto senha_capital OK'!F143/1000 -> #REF! | I72: ='Garoto senha_capital OK'!G143/1000 -> #REF! | J72: ='Garoto senha_capital OK'!H143/1000 -> #REF! | K72: =IFERROR(J72/H72-1," ") | L72: =IFERROR(J72/I72-1," ") | P72: =IFERROR(O72/M72-1," ") | Q72: =IFERROR(O72/N72-1," ")
B73: 7 - EBITDA | C73: =C71+C72 -> 0 | D73: =D71+D72 -> 0 | E73: =E71+E72 -> 0 | F73: =- IFERROR(E73/C73-1," ") -> #VALUE! | G73: =-IFERROR(E73/D73-1," ") -> #VALUE! | H73: =H71+H72 -> #REF! | I73: =I71+I72 -> #REF! | J73: =J71+J72 -> #REF! | K73: =- IFERROR(J73/H73-1," ") -> #VALUE! | L73: =-IFERROR(J73/I73-1," ") -> #VALUE! | M73: =M71+M72 -> 0 | N73: =N71+N72 -> 0 | O73: =O71+O72 -> 0 | P73: =-IFERROR(O73/M73-1," ") -> #VALUE! | Q73: =-IFERROR(O73/N73-1," ") -> #VALUE!
B74: 8 - DEPRECIAÇÃO | F74: =IFERROR(E74/C74-1," ") | G74: =IFERROR(E74/D74-1," ") | H74: ='Garoto senha_capital OK'!F145/1000 -> #REF! | I74: ='Garoto senha_capital OK'!G145/1000 -> #REF! | J74: ='Garoto senha_capital OK'!H145/1000 -> #REF! | K74: =IFERROR(J74/H74-1," ") | L74: =IFERROR(J74/I74-1," ") | P74: =IFERROR(O74/M74-1," ") | Q74: =IFERROR(O74/N74-1," ")
B75: 9 - RESULTADO OPERACIONAL | F75: =-IFERROR(E75/C75-1," ") -> #VALUE! | G75: =-IFERROR(E75/D75-1," ") -> #VALUE! | H75: =H73+H74 -> #REF! | I75: =I73+I74 -> #REF! | J75: =J73+J74 -> #REF! | K75: =(IFERROR(J75/H75-1," ")) | L75: =-IFERROR(J75/I75-1," ") -> #VALUE! | P75: =-IFERROR(O75/M75-1," ") -> #VALUE! | Q75: =-IFERROR(O75/N75-1," ") -> #VALUE!
B76: 10 - OUTRAS RECEITAS E DESPESAS | F76: =-IFERROR(E76/C76-1," ") -> #VALUE! | G76: =IFERROR(E76/D76-1," ") | H76: ='Garoto senha_capital OK'!F147/1000 -> #REF! | I76: ='Garoto senha_capital OK'!G147/1000 -> #REF! | J76: ='Garoto senha_capital OK'!H147/1000 -> #REF! | K76: =-IFERROR(J76/H76-1," ") -> #VALUE! | L76: =IFERROR(J76/I76-1," ") | P76: =-IFERROR(O76/M76-1," ") -> #VALUE! | Q76: =IFERROR(O76/N76-1," ")
B77: 11 - LUCRO ANTES DO IR/CSLL | F77: =IFERROR(E77/C77-1," ") | G77: =IFERROR(E77/D77-1," ") | H77: =H75+H76 -> #REF! | I77: =I75+I76 -> #REF! | J77: =J75+J76 -> #REF! | K77: =- IFERROR(J77/H77-1," ") -> #VALUE! | L77: =IFERROR(J77/I77-1," ") | P77: =IFERROR(O77/M77-1," ") | Q77: =IFERROR(O77/N77-1," ")
B78: 12 - IR/CSLL | F78: 0 | G78: =IFERROR(E78/D78-1," ") | H78: 0 | I78: ='Garoto senha_capital OK'!G149/1000 -> #REF! | J78: ='Garoto senha_capital OK'!H149/1000 -> #REF! | K78: 0 | L78: =IFERROR(J78/I78-1," ") | P78: 0 | Q78: =IFERROR(O78/N78-1," ")
B79: 13 - LUCRO LÍQUIDO | F79: =IFERROR(E79/C79-1," ") | G79: =IFERROR(E79/D79-1," ") | H79: =H77+H78 -> #REF! | I79: =I77+I78 -> #REF! | J79: =J77+J78 -> #REF! | K79: =(IFERROR(J79/H79-1," ")) | L79: =IFERROR(J79/I79-1," ") | P79: =-IFERROR(O79/M79-1," ") -> #VALUE! | Q79: =- IFERROR(O79/N79-1," ") -> #VALUE!
B80: Margem EBITDA/ROL | C80: =C73/C69 -> #DIV/0! | D80: =D73/D69 -> #DIV/0! | H80: =H73/H69 -> #REF! | I80: =I73/I69 -> #REF! | J80: =J73/J69 -> #REF! | M80: =M73/M69 -> #DIV/0! | N80: =N73/N69 -> #DIV/0! | O80: =O73/O69 -> #DIV/0!
B82: Margem Despesas Operacionais/ROL | C82: =C72/C69 -> #DIV/0! | D82: =D72/D69 -> #DIV/0! | E82: =E72/E69 -> #DIV/0! | H82: =H72/H69 -> #REF! | I82: =I72/I69 -> #REF! | J82: =J72/J69 -> #REF! | M82: =M72/M69 -> #DIV/0! | N82: =N72/N69 -> #DIV/0! | O82: =O72/O69 -> #DIV/0!
B84: Margem Lucro Líquido/ROL | C84: =C79/C69 -> #DIV/0! | D84: =D79/D69 -> #DIV/0! | E84: =E79/E69 -> #DIV/0! | H84: =H79/H69 -> #REF! | I84: =I79/I69 -> #REF! | J84: =J79/J69 -> #REF! | M84: =M79/M69 -> #DIV/0! | N84: =N79/N69 -> #DIV/0! | O84: =O79/O69 -> #DIV/0!
C85: =C60-C39 -> 1181.2539 | D85: =D60-D39 -> 1099.0643 | E85: =E60-E39 -> 1332.9182
B87: DRE HANGAR VIP (Em R$/Mil) | C87: =C3 -> JULHO | H87: =H3 -> ACUMULADO JANEIRO A JULHO | M87: =M3 -> RITMO
C88: Real 2025 | D88: Orç 2026 | E88: Real 2026 | F88: Real 2026 x Orç 2026 | G88: Real 2026 x Real 2025 | H88: Real 2025 | I88: Orç 2026 | J88: Real 2026 | K88: Real 2026 x Orç 2026 | L88: Real 2026 x Real 2025 | M88: Real 2025 | N88: Orç 2026 | O88: Ritmo 2026 | P88: Ritmo 2026 x Orç 2026 | Q88: Ritmo 2026 x Real 2025
B89: 1 - FATURAMENTO BRUTO | C89: ='Hangar senha_capital OK'!B131/1000 -> 471.43324 | D89: ='Hangar senha_capital OK'!C131/1000 -> 520.386 | E89: ='Hangar senha_capital OK'!D131/1000 -> 559.40313 | F89: =IFERROR(E89/D89-1," ") -> 0.074977286 | G89: =IFERROR(E89/C89-1," ") -> 0.18660095 | H89: ='Hangar senha_capital OK'!F131/1000 -> 2650.309 | I89: ='Hangar senha_capital OK'!G131/1000 -> 3069.38 | J89: ='Hangar senha_capital OK'!H131/1000 -> 3447.7093 | K89: =IFERROR(J89/I89-1," ") -> 0.12325918 | L89: =IFERROR(J89/H89-1," ") -> 0.30087067 | M89: ='Hangar senha_capital OK'!J131/1000 -> 4863.8396 | N89: ='Hangar senha_capital OK'!K131/1000 -> 5484.732 | O89: ='Hangar senha_capital OK'!L131/1000 -> 6021.2993 | P89: =IFERROR(O89/N89-1," ") -> 0.097829258 | Q89: =IFERROR(O89/M89-1," ") -> 0.23797242
B90: 2 - DEDUÇÃO DE FATURAMENTO | C90: ='Hangar senha_capital OK'!B132/1000 -> -70.38363 | D90: ='Hangar senha_capital OK'!C132/1000 -> -74.15501 | E90: ='Hangar senha_capital OK'!D132/1000 -> -80.25691 | F90: =IFERROR(E90/D90-1," ") -> 0.082285742 | G90: =IFERROR(E90/C90-1," ") -> 0.14027807 | H90: ='Hangar senha_capital OK'!F132/1000 -> -386.05337 | I90: ='Hangar senha_capital OK'!G132/1000 -> -437.38669 | J90: ='Hangar senha_capital OK'!H132/1000 -> -497.8368 | K90: =IFERROR(J90/I90-1," ") -> 0.13820747 | L90: =IFERROR(J90/H90-1," ") -> 0.28955434 | M90: ='Hangar senha_capital OK'!J132/1000 -> -706.70387 | N90: ='Hangar senha_capital OK'!K132/1000 -> -781.57436 | O90: ='Hangar senha_capital OK'!L132/1000 -> -864.57339 | P90: =IFERROR(O90/N90-1," ") -> 0.10619467 | Q90: =IFERROR(O90/M90-1," ") -> 0.2233885
B91: 3 - FATURAMENTO LÍQUIDO | C91: =C89+C90 -> 401.04961 | D91: =D89+D90 -> 446.23099 | E91: =E89+E90 -> 479.14622 | F91: =IFERROR(E91/D91-1," ") -> 0.073762761 | G91: =IFERROR(E91/C91-1," ") -> 0.19473055 | H91: =H89+H90 -> 2264.2556 | I91: =I89+I90 -> 2631.9933 | J91: =J89+J90 -> 2949.8725 | K91: =IFERROR(J91/I91-1," ") -> 0.12077506 | L91: =IFERROR(J91/H91-1," ") -> 0.30280009 | M91: =M89+M90 -> 4157.1357 | N91: =N89+N90 -> 4703.1576 | O91: =O89+O90 -> 5156.7259 | P91: =IFERROR(O91/N91-1," ") -> 0.096439087 | Q91: =IFERROR(O91/M91-1," ") -> 0.24045165
B92: 4 - CUSTO MERCADORIA VENDIDA | C92: 0 | D92: 0 | E92: 0 | F92: 0 | G92: 0 | H92: 0 | I92: 0 | J92: 0 | K92: 0 | L92: 0 | M92: 0 | N92: 0 | O92: 0 | P92: 0 | Q92: 0
B93: 5 - LUCRO BRUTO | C93: =C91+C92 -> 401.04961 | D93: =D91+D92 -> 446.23099 | E93: =E91+E92 -> 479.14622 | F93: =IFERROR(E93/D93-1," ") -> 0.073762761 | G93: =IFERROR(E93/C93-1," ") -> 0.19473055 | H93: =H91 -> 2264.2556 | I93: =I91 -> 2631.9933 | J93: =J91 -> 2949.8725 | K93: =IFERROR(J93/I93-1," ") -> 0.12077506 | L93: =IFERROR(J93/H93-1," ") -> 0.30280009 | M93: =M91+M92 -> 4157.1357 | N93: =N91+N92 -> 4703.1576 | O93: =O91+O92 -> 5156.7259 | P93: =IFERROR(O93/N93-1," ") -> 0.096439087 | Q93: =IFERROR(O93/M93-1," ") -> 0.24045165
B94: 6 - DESPESAS OPERACIONAIS | C94: ='Hangar senha_capital OK'!B135/1000 -> -259.60716 | D94: ='Hangar senha_capital OK'!C135/1000 -> -252.88467 | E94: ='Hangar senha_capital OK'!D135/1000 -> -219.07085 | F94: =IFERROR(E94/D94-1," ") -> -0.13371242 | G94: =IFERROR(E94/C94-1," ") -> -0.15614481 | H94: ='Hangar senha_capital OK'!F135/1000 -> -1590.6781 | I94: ='Hangar senha_capital OK'!G135/1000 -> -1885.8485 | J94: ='Hangar senha_capital OK'!H135/1000 -> -1762.0258 | K94: =IFERROR(J94/I94-1," ") -> -0.065658876 | L94: =IFERROR(J94/H94-1," ") -> 0.10771992 | M94: ='Hangar senha_capital OK'!J135/1000 -> -3108.15 | N94: ='Hangar senha_capital OK'!K135/1000 -> -3181.5756 | O94: ='Hangar senha_capital OK'!L135/1000 -> -3205.9569 | P94: =IFERROR(O94/N94-1," ") -> 0.0076632816 | Q94: =IFERROR(O94/M94-1," ") -> 0.031467896
B95: 7 - EBITDA | C95: =C93+C94 -> 141.44245 | D95: =D93+D94 -> 193.34632 | E95: =E93+E94 -> 260.07537 | F95: =IFERROR(E95/D95-1," ") -> 0.34512708 | G95: =IFERROR(E95/C95-1," ") -> 0.83873632 | H95: =H93+H94 -> 673.57758 | I95: =I93+I94 -> 746.14484 | J95: =J93+J94 -> 1187.8467 | K95: =(IFERROR(J95/I95-1," ")) -> 0.59197868 | L95: =IFERROR(J95/H95-1," ") -> 0.76348904 | M95: =M93+M94 -> 1048.9857 | N95: =N93+N94 -> 1521.582 | O95: =O93+O94 -> 1950.7689 | P95: =(IFERROR(O95/N95-1," ")) -> 0.28206624 | Q95: =IFERROR(O95/M95-1," ") -> 0.85967156
B96: 8 - DEPRECIAÇÃO | C96: ='Hangar senha_capital OK'!B137/1000 -> -42.8642 | D96: ='Hangar senha_capital OK'!C137/1000 -> -46.25173 | E96: ='Hangar senha_capital OK'!D137/1000 -> -43.08163 | F96: =IFERROR(E96/D96-1," ") -> -0.068540139 | G96: =IFERROR(E96/C96-1," ") -> 0.0050725314 | H96: ='Hangar senha_capital OK'!F137/1000 -> -300.71395 | I96: ='Hangar senha_capital OK'!G137/1000 -> -322.83281 | J96: ='Hangar senha_capital OK'!H137/1000 -> -299.88051 | K96: =IFERROR(J96/I96-1," ") -> -0.071096553 | L96: =IFERROR(J96/H96-1," ") -> -0.0027715375 | M96: ='Hangar senha_capital OK'!J137/1000 -> -511.63264 | N96: ='Hangar senha_capital OK'!K137/1000 -> -547.66656 | O96: ='Hangar senha_capital OK'!L137/1000 -> -524.71426 | P96: =IFERROR(O96/N96-1," ") -> -0.04190926 | Q96: =IFERROR(O96/M96-1," ") -> 0.025568384
B97: 9 - RESULTADO OPERACIONAL | C97: =C95+C96 -> 98.57825 | D97: =D95+D96 -> 147.09459 | E97: =E95+E96 -> 216.99374 | F97: =IFERROR(E97/D97-1," ") -> 0.47519865 | G97: =IFERROR(E97/C97-1," ") -> 1.2012334 | H97: =H95+H96 -> 372.86363 | I97: =I95+I96 -> 423.31203 | J97: =J95+J96 -> 887.96617 | K97: =IFERROR(J97/I97-1," ") -> 1.0976634 | L97: =IFERROR(J97/H97-1," ") -> 1.381477 | M97: =M95+M96 -> 537.35309 | N97: =N95+N96 -> 973.91545 | O97: =O95+O96 -> 1426.0547 | P97: =IFERROR(O97/N97-1," ") -> 0.46424894 | Q97: =IFERROR(O97/M97-1," ") -> 1.6538503
B98: 10 - OUTRAS RECEITAS E DESPESAS | C98: ='Hangar senha_capital OK'!B139/1000 -> -11.99234 | D98: ='Hangar senha_capital OK'!C139/1000 -> -9.18305 | E98: ='Hangar senha_capital OK'!D139/1000 -> -0.80054 | F98: =IFERROR(E98/D98-1," ") -> -0.91282417 | G98: =IFERROR(E98/C98-1," ") -> -0.93324572 | H98: ='Hangar senha_capital OK'!F139/1000 -> -86.2422 | I98: ='Hangar senha_capital OK'!G139/1000 -> -65.03489 | J98: ='Hangar senha_capital OK'!H139/1000 -> -34.44861 | K98: =IFERROR(J98/I98-1," ") -> -0.47030571 | L98: =IFERROR(J98/H98-1," ") -> -0.6005597 | M98: ='Hangar senha_capital OK'!J139/1000 -> -127.92137 | N98: ='Hangar senha_capital OK'!K139/1000 -> -111.16926 | O98: ='Hangar senha_capital OK'!L139/1000 -> -80.58298 | P98: =IFERROR(O98/N98-1," ") -> -0.27513253 | Q98: =IFERROR(O98/M98-1," ") -> -0.3700585
B99: 10.1 - RECEITAS FINANCEIRAS | C99: ='Hangar senha_capital OK'!B140/1000 -> 3.78841 | D99: ='Hangar senha_capital OK'!C140/1000 -> 5.21558 | E99: ='Hangar senha_capital OK'!D140/1000 -> 10.03661 | F99: =IFERROR(E99/D99-1," ") -> 0.92435165 | G99: =IFERROR(E99/C99-1," ") -> 1.6492935 | H99: ='Hangar senha_capital OK'!F140/1000 -> 12.39338 | I99: ='Hangar senha_capital OK'!G140/1000 -> 38.03807 | J99: ='Hangar senha_capital OK'!H140/1000 -> 52.77669 | K99: =IFERROR(J99/I99-1," ") -> 0.38747024 | L99: =IFERROR(J99/H99-1," ") -> 3.2584581 | M99: ='Hangar senha_capital OK'!J140/1000 -> 45.18364 | N99: ='Hangar senha_capital OK'!K140/1000 -> 62.83368 | O99: ='Hangar senha_capital OK'!L140/1000 -> 77.5723 | P99: =IFERROR(O99/N99-1," ") -> 0.2345656 | Q99: =IFERROR(O99/M99-1," ") -> 0.71682273
B100: 10.2 - DESPESAS FINANCEIRAS | C100: ='Hangar senha_capital OK'!B141/1000 -> -15.78075 | D100: ='Hangar senha_capital OK'!C141/1000 -> -14.39863 | E100: ='Hangar senha_capital OK'!D141/1000 -> -10.83715 | F100: =IFERROR(E100/D100-1," ") -> -0.24734853 | G100: =IFERROR(E100/C100-1," ") -> -0.31326775 | H100: ='Hangar senha_capital OK'!F141/1000 -> -98.63558 | I100: ='Hangar senha_capital OK'!G141/1000 -> -103.07296 | J100: ='Hangar senha_capital OK'!H141/1000 -> -87.2253 | K100: =IFERROR(J100/I100-1," ") -> -0.15375187 | L100: =IFERROR(J100/H100-1," ") -> -0.11568118 | M100: ='Hangar senha_capital OK'!J141/1000 -> -173.10501 | N100: ='Hangar senha_capital OK'!K141/1000 -> -174.00294 | O100: ='Hangar senha_capital OK'!L141/1000 -> -158.15528 | P100: =IFERROR(O100/N100-1," ") -> -0.091076967 | Q100: =IFERROR(O100/M100-1," ") -> -0.086362203
B101: 11 - LUCRO ANTES DO IR/CSLL | C101: =C97+C98 -> 86.58591 | D101: =D97+D98 -> 137.91154 | E101: =E97+E98 -> 216.1932 | F101: =IFERROR(E101/D101-1," ") -> 0.56762226 | G101: =(IFERROR(E101/C101-1," ")) -> 1.4968635 | H101: =H97+H98 -> 286.62143 | I101: =I97+I98 -> 358.27714 | J101: =J97+J98 -> 853.51756 | K101: =IFERROR(J101/I101-1," ") -> 1.3822831 | L101: =IFERROR(J101/H101-1," ") -> 1.9778567 | M101: =M97+M98 -> 409.43172 | N101: =N97+N98 -> 862.74619 | O101: =O97+O98 -> 1345.4717 | P101: =IFERROR(O101/N101-1," ") -> 0.55952203 | Q101: =IFERROR(O101/M101-1," ") -> 2.2861931
B102: 12 - IR/CSLL | C102: ='Hangar senha_capital OK'!B143/1000 -> -15.04749 | D102: ='Hangar senha_capital OK'!C143/1000 -> -32.3209 | E102: ='Hangar senha_capital OK'!D143/1000 -> -46.46344 | F102: =IFERROR(E102/D102-1," ") -> 0.4375664 | G102: =-IFERROR(E102/C102-1," ") -> -2.0877867 | H102: ='Hangar senha_capital OK'!F143/1000 -> -53.16372 | I102: ='Hangar senha_capital OK'!G143/1000 -> -81.85308 | J102: ='Hangar senha_capital OK'!H143/1000 -> -190.16749 | K102: =IFERROR(J102/I102-1," ") -> 1.3232784 | L102: =IFERROR(J102/H102-1," ") -> 2.5770162 | M102: ='Hangar senha_capital OK'!J143/1000 -> -101.236 | N102: ='Hangar senha_capital OK'!K143/1000 -> -199.24983 | O102: ='Hangar senha_capital OK'!L143/1000 -> -307.56424 | P102: =IFERROR(O102/N102-1," ") -> 0.54361105 | Q102: =IFERROR(O102/M102-1," ") -> 2.0380916
B103: 13 - LUCRO LÍQUIDO | C103: =C101+C102 -> 71.53842 | D103: =D101+D102 -> 105.59064 | E103: =E101+E102 -> 169.72976 | F103: =IFERROR(E103/D103-1," ") -> 0.60743187 | G103: =(IFERROR(E103/C103-1," ")) -> 1.3725679 | H103: =H101+H102 -> 233.45771 | I103: =I101+I102 -> 276.42406 | J103: =J101+J102 -> 663.35007 | K103: =IFERROR(J103/I103-1," ") -> 1.3997552 | L103: =IFERROR(J103/H103-1," ") -> 1.8414143 | M103: =M101+M102 -> 308.19572 | N103: =N101+N102 -> 663.49636 | O103: =O101+O102 -> 1037.9074 | P103: =IFERROR(O103/N103-1," ") -> 0.56430014 | Q103: =IFERROR(O103/M103-1," ") -> 2.3676894
B104: Margem EBITDA/ROL | C104: =C95/C91 -> 0.35268068 | D104: =D95/D91 -> 0.43328752 | E104: =E95/E91 -> 0.54278915 | H104: =H95/H91 -> 0.29748301 | I104: =I95/I91 -> 0.2834904 | J104: =J95/J91 -> 0.4026773 | M104: =M95/M91 -> 0.25233377 | N104: =N95/N91 -> 0.3235235 | O104: =O95/O91 -> 0.37829603
B107: DRE POSTO ESTEIO (Em R$/Mil) | C107: =C3 -> JULHO | H107: ACUMULADO JANEIRO A NOVEMBRO | M107: RITMO
C108: Real 2023 | D108: Orç 2024 | E108: Real 2024 | F108: Real 2024 x Orç 2024 | G108: Real 2024 x Real 2023 | H108: Real 2022 | I108: Orç 2023 | J108: Real 2023 | K108: ∆ Real 2023 x Real 2022 | L108: ∆ Real 2023 x Orç 2023 | M108: Real 2023 | N108: Orç 2024 | O108: Ritmo 2024 | P108: Ritmo 2024 x Orç 2024 | Q108: Ritmo 2024 x Real 2023
B109: 1 - FATURAMENTO BRUTO | C109: 0 | D109: 0 | E109: 0 | F109: =IFERROR(E109/C109-1," ") | G109: =IFERROR(E109/D109-1," ") | H109: 2479.6293 | I109: 0 | J109: 0 | K109: =IFERROR(J109/H109-1," ") -> -1 | L109: =IFERROR(J109/I109-1," ") | M109: 2479.63 | N109: 0 | O109: 0 | P109: =IFERROR(O109/M109-1," ") -> -1 | Q109: =IFERROR(O109/N109-1," ") | S109: -141
B110: 2 - DEDUÇÃO DE FATURAMENTO | C110: 0 | D110: 0 | E110: 0 | F110: =IFERROR(E110/C110-1," ") | G110: =IFERROR(E110/D110-1," ") | H110: -37.985 | I110: 0 | J110: 0 | K110: =IFERROR(J110/H110-1," ") -> -1 | L110: =IFERROR(J110/I110-1," ") | M110: -37.99 | N110: 0 | O110: 0 | P110: =IFERROR(O110/M110-1," ") -> -1 | Q110: =IFERROR(O110/N110-1," ") | S110: 379
B111: 3 - FATURAMENTO LÍQUIDO | C111: =C109+C110 -> 0 | D111: =D109+D110 -> 0 | E111: =E109+E110 -> 0 | F111: =IFERROR(E111/C111-1," ") | G111: =IFERROR(E111/D111-1," ") | H111: =H109+H110 -> 2441.6443 | I111: =I109+I110 -> 0 | J111: =J109+J110 -> 0 | K111: =IFERROR(J111/H111-1," ") -> -1 | L111: =IFERROR(J111/I111-1," ") | M111: =M109+M110 -> 2441.64 | N111: =N109+N110 -> 0 | O111: =O109+O110 -> 0 | P111: =IFERROR(O111/M111-1," ") -> -1 | Q111: =IFERROR(O111/N111-1," ") | S111: =S109+S110 -> 238
B112: 4 - CUSTO MERCADORIA VENDIDA | C112: 0 | D112: 0 | E112: 0 | F112: =IFERROR(E112/C112-1," ") | G112: =IFERROR(E112/D112-1," ") | H112: -2356.0097 | I112: 0 | J112: 0 | K112: =IFERROR(J112/H112-1," ") -> -1 | L112: =IFERROR(J112/I112-1," ") | M112: -2356.02 | N112: 0 | O112: 0 | P112: =IFERROR(O112/M112-1," ") -> -1 | Q112: =IFERROR(O112/N112-1," ")
...

Sheet DCL_D-ESPAÇO 
B2: DRE DCL - SHOPPING CENTER (Em R$/Mil) | C2: JUNHO | H2: ACUMULADO JANEIRO A JUNHO | M2: RITMO
C3: Real 2025 | D3: Orç 2026 | E3: Real 2026 | F3: Real 2026 x Orç 2026 | G3: Real 2026 x Real 2025 | H3: Real 2025 | I3: Orç 2026 | J3: Real 2026 | K3: Real 2026 x Orç 2026 | L3: Real 2026 x Real 2025 | M3: Real 2025 | N3: Orç 2026 | O3: Ritmo 2026 | P3: Ritmo 2026 x Orç 2026 | Q3: Ritmo 2026 x Real 2025
B4: 1 - FATURAMENTO BRUTO | C4: ='DRE DCL E D-ESPAÇO'!B4/1000 -> 929.60876 | D4: ='DRE DCL E D-ESPAÇO'!C4/1000 -> 1174.4612 | E4: ='DRE DCL E D-ESPAÇO'!D4/1000 -> 1189.405 | F4: =IFERROR(E4/D4-1," ") -> 0.012723954 | G4: =IFERROR(E4/C4-1," ") -> 0.27946834 | H4: ='DRE DCL E D-ESPAÇO'!H4/1000 -> 5653.6086 | I4: ='DRE DCL E D-ESPAÇO'!I4/1000 -> 6676.4325 | J4: ='DRE DCL E D-ESPAÇO'!J4/1000 -> 7037.3068 | K4: =IFERROR(J4/I4-1," ") -> 0.054051981 | L4: =IFERROR(J4/H4-1," ") -> 0.24474603 | M4: ='DRE DCL E D-ESPAÇO'!N4/1000 -> 12163.891 | N4: ='DRE DCL E D-ESPAÇO'!O4/1000 -> 13536.552 | O4: ='DRE DCL E D-ESPAÇO'!P4/1000 -> 14158.809 | P4: =IFERROR(O4/N4-1," ") -> 0.045968653 | Q4: =IFERROR(O4/M4-1," ") -> 0.16400332
B5: 2 - DEDUÇÃO DE FATURAMENTO | C5: =-'DRE DCL E D-ESPAÇO'!B5/1000 -> -51.48516 | D5: =-'DRE DCL E D-ESPAÇO'!C5/1000 -> -74.83227 | E5: =-'DRE DCL E D-ESPAÇO'!D5/1000 -> -62.78813 | F5: =IFERROR(E5/D5-1," ") -> -0.16094848 | G5: =IFERROR(E5/C5-1," ") -> 0.21953841 | H5: =-'DRE DCL E D-ESPAÇO'!H5/1000 -> -323.6601 | I5: =-'DRE DCL E D-ESPAÇO'!I5/1000 -> -430.04734 | J5: =-'DRE DCL E D-ESPAÇO'!J5/1000 -> -509.34007 | K5: =IFERROR(J5/I5-1," ") -> 0.1843814 | L5: =IFERROR(J5/H5-1," ") -> 0.57368817 | M5: =-'DRE DCL E D-ESPAÇO'!N5/1000 -> -799.44911 | N5: =-'DRE DCL E D-ESPAÇO'!O5/1000 -> -879.06409 | O5: =-'DRE DCL E D-ESPAÇO'!P5/1000 -> -945.916 | P5: =IFERROR(O5/N5-1," ") -> 0.07604896 | Q5: =IFERROR(O5/M5-1," ") -> 0.18320977
B6: 3 - FATURAMENTO LÍQUIDO | C6: =C4+C5 -> 878.1236 | D6: =D4+D5 -> 1099.6289 | E6: =E4+E5 -> 1126.6169 | F6: =IFERROR(E6/D6-1," ") -> 0.024542761 | G6: =IFERROR(E6/C6-1," ") -> 0.28298209 | H6: =H4+H5 -> 5329.9485 | I6: =I4+I5 -> 6246.3851 | J6: =J4+J5 -> 6527.9668 | K6: =IFERROR(J6/I6-1," ") -> 0.04507914 | L6: =IFERROR(J6/H6-1," ") -> 0.22477108 | M6: =M4+M5 -> 11364.441 | N6: =N4+N5 -> 12657.488 | O6: =O4+O5 -> 13212.893 | P6: =IFERROR(O6/N6-1," ") -> 0.043879572 | Q6: =IFERROR(O6/M6-1," ") -> 0.16265221
B7: 4 - CUSTO MERCADORIA VENDIDA | C7: 0 | D7: 0 | E7: 0 | F7: 0 | G7: 0 | H7: 0 | I7: 0 | J7: 0 | K7: 0 | L7: 0 | M7: 0 | N7: 0 | O7: 0 | P7: 0 | Q7: 0
B8: 5 - LUCRO BRUTO | C8: =C6+C7 -> 878.1236 | D8: =D6+D7 -> 1099.6289 | E8: =E6+E7 -> 1126.6169 | F8: =IFERROR(E8/D8-1," ") -> 0.024542761 | G8: =IFERROR(E8/C8-1," ") -> 0.28298209 | H8: =H6 -> 5329.9485 | I8: =I6 -> 6246.3851 | J8: =J6 -> 6527.9668 | K8: =IFERROR(J8/I8-1," ") -> 0.04507914 | L8: =IFERROR(J8/H8-1," ") -> 0.22477108 | M8: =M6+M7 -> 11364.441 | N8: =N6+N7 -> 12657.488 | O8: =O6+O7 -> 13212.893 | P8: =IFERROR(O8/N8-1," ") -> 0.043879572 | Q8: =IFERROR(O8/M8-1," ") -> 0.16265221
B9: 6 - DESPESAS OPERACIONAIS | C9: =-'DRE DCL E D-ESPAÇO'!B7/1000+'DRE DCL E D-ESPAÇO'!B11/1000 -> -418.40528 | D9: =-'DRE DCL E D-ESPAÇO'!C7/1000+'DRE DCL E D-ESPAÇO'!C11/1000 -> -436.56753 | E9: =-'DRE DCL E D-ESPAÇO'!D7/1000+'DRE DCL E D-ESPAÇO'!D11/1000 -> -353.18054 | F9: =IFERROR(E9/D9-1," ") -> -0.19100594 | G9: =IFERROR(E9/C9-1," ") -> -0.1558889 | H9: =-'DRE DCL E D-ESPAÇO'!H7/1000+'DRE DCL E D-ESPAÇO'!H11/1000 -> -2163.8498 | I9: =-'DRE DCL E D-ESPAÇO'!I7/1000+'DRE DCL E D-ESPAÇO'!I11/1000 -> -2686.0201 | J9: =-'DRE DCL E D-ESPAÇO'!J7/1000+'DRE DCL E D-ESPAÇO'!J11/1000 -> -2258.5453 | K9: =IFERROR(J9/I9-1," ") -> -0.159148 | L9: =IFERROR(J9/H9-1," ") -> 0.04376251 | M9: =-'DRE DCL E D-ESPAÇO'!N7/1000+'DRE DCL E D-ESPAÇO'!N11/1000 -> -4444.1877 | N9: =-'DRE DCL E D-ESPAÇO'!O7/1000+'DRE DCL E D-ESPAÇO'!O11/1000+0.6 -> -5191.1278 | O9: =-'DRE DCL E D-ESPAÇO'!P7/1000+'DRE DCL E D-ESPAÇO'!P11/1000 -> -4570.001 | P9: =IFERROR(O9/N9-1," ") -> -0.11965161 | Q9: =IFERROR(O9/M9-1," ") -> 0.028309637
B10: 7 - EBITDA | C10: =C8+C9 -> 459.71832 | D10: =D8+D9 -> 663.06139 | E10: =E8+E9 -> 773.43631 | F10: =IFERROR(E10/D10-1," ") -> 0.1664626 | G10: =IFERROR(E10/C10-1," ") -> 0.6824135 | H10: =H8+H9 -> 3166.0986 | I10: =I8+I9 -> 3560.365 | J10: =J8+J9 -> 4269.4214 | K10: =IFERROR(J10/I10-1," ") -> 0.19915272 | L10: =IFERROR(J10/H10-1," ") -> 0.34848023 | M10: =M8+M9 -> 6920.2538 | N10: =N8+N9 -> 7466.3601 | O10: =O8+O9 -> 8642.892 | P10: =IFERROR(O10/N10-1," ") -> 0.15757771 | Q10: =IFERROR(O10/M10-1," ") -> 0.24892703
B11: 8 - DEPRECIAÇÃO | C11: =-'DRE DCL E D-ESPAÇO'!B9/1000 -> -89.33857 | D11: =-'DRE DCL E D-ESPAÇO'!C9/1000 -> -107.87608 | E11: =-'DRE DCL E D-ESPAÇO'!D9/1000 -> -109.47557 | F11: =IFERROR(E11/D11-1," ") -> 0.014827105 | G11: =IFERROR(E11/C11-1," ") -> 0.22540097 | H11: =-'DRE DCL E D-ESPAÇO'!H9/1000 -> -533.01363 | I11: =-'DRE DCL E D-ESPAÇO'!I9/1000 -> -640.38748 | J11: =-'DRE DCL E D-ESPAÇO'!J9/1000 -> -644.1836 | K11: =IFERROR(J11/I11-1," ") -> 0.0059278486 | L11: =IFERROR(J11/H11-1," ") -> 0.20856872 | M11: =-'DRE DCL E D-ESPAÇO'!N9/1000 -> -1109.9689 | N11: =-'DRE DCL E D-ESPAÇO'!O9/1000 -> -1313.136 | O11: =-'DRE DCL E D-ESPAÇO'!P9/1000 -> -1276.077 | P11: =IFERROR(O11/N11-1," ") -> -0.028221738 | Q11: =IFERROR(O11/M11-1," ") -> 0.14965116
B12: 9 - RESULTADO OPERACIONAL | C12: =C10+C11 -> 370.37975 | D12: =D10+D11 -> 555.18531 | E12: =E10+E11 -> 663.96074 | F12: =IFERROR(E12/D12-1," ") -> 0.19592635 | G12: =IFERROR(E12/C12-1," ") -> 0.7926486 | H12: =H10+H11 -> 2633.085 | I12: =I10+I11 -> 2919.9776 | J12: =J10+J11 -> 3625.2378 | K12: =IFERROR(J12/I12-1," ") -> 0.24152935 | L12: =IFERROR(J12/H12-1," ") -> 0.37680243 | M12: =M10+M11 -> 5810.2849 | N12: =N10+N11-1 -> 6152.2241 | O12: =O10+O11 -> 7366.815 | P12: =IFERROR(O12/N12-1," ") -> 0.19742306 | Q12: =IFERROR(O12/M12-1," ") -> 0.26789221
B13: 10 - OUTRAS RECEITAS E DESPESAS | C13: =C14+C15 -> -43.47349 | D13: =D14+D15 -> -106.56121 | E13: =E14+E15 -> -63.31012 | F13: =IFERROR(E13/D13-1," ") -> -0.40588024 | G13: =IFERROR(E13/C13-1," ") -> 0.45629256 | H13: =H14+H15 -> -263.89106 | I13: =I14+I15 -> -661.15789 | J13: =J14+J15 -> -469.36039 | K13: =IFERROR(J13/I13-1," ") -> -0.29009334 | L13: =IFERROR(J13/H13-1," ") -> 0.77861421 | M13: =M14+M15 -> -853.32875 | N13: =N14+N15 -> -1291.1199 | O13: =O14+O15 -> -1035.8937 | P13: =IFERROR(O13/N13-1," ") -> -0.19767817 | Q13: =IFERROR(O13/M13-1," ") -> 0.21394446
B14: 10.1 - RECEITAS FINANCEIRAS | C14: ='DRE DCL E D-ESPAÇO'!B13/1000 -> 4.72904 | D14: ='DRE DCL E D-ESPAÇO'!C13/1000 -> 11.71742 | E14: ='DRE DCL E D-ESPAÇO'!D13/1000 -> 51.68424 | F14: =IFERROR(E14/D14-1," ") -> 3.4108891 | G14: =IFERROR(E14/C14-1," ") -> 9.9291188 | H14: ='DRE DCL E D-ESPAÇO'!H13/1000 -> 59.21248 | I14: ='DRE DCL E D-ESPAÇO'!I13/1000 -> 65.50501 | J14: ='DRE DCL E D-ESPAÇO'!J13/1000 -> 219.61504 | K14: =IFERROR(J14/I14-1," ") -> 2.3526449 | L14: =IFERROR(J14/H14-1," ") -> 2.7089316 | M14: ='DRE DCL E D-ESPAÇO'!N13/1000 -> 184.39723 | N14: ='DRE DCL E D-ESPAÇO'!O13/1000 -> 111.13091 | O14: ='DRE DCL E D-ESPAÇO'!P13/1000 -> 335.58523 | P14: =IFERROR(O14/N14-1," ") -> 2.019729 | Q14: =IFERROR(O14/M14-1," ") -> 0.81990386
B15: 10.2 - DESPESAS FINANCEIRAS | C15: =-'DRE DCL E D-ESPAÇO'!B14/1000 -> -48.20253 | D15: =-'DRE DCL E D-ESPAÇO'!C14/1000 -> -118.27863 | E15: =-'DRE DCL E D-ESPAÇO'!D14/1000 -> -114.99436 | F15: =IFERROR(E15/D15-1," ") -> -0.027767231 | G15: =IFERROR(E15/C15-1," ") -> 1.3856499 | H15: =-'DRE DCL E D-ESPAÇO'!H14/1000 -> -323.10354 | I15: =-'DRE DCL E D-ESPAÇO'!I14/1000 -> -726.6629 | J15: =-'DRE DCL E D-ESPAÇO'!J14/1000 -> -688.97543 | K15: =IFERROR(J15/I15-1," ") -> -0.05186376 | L15: =IFERROR(J15/H15-1," ") -> 1.1323673 | M15: =-'DRE DCL E D-ESPAÇO'!N14/1000 -> -1037.726 | N15: =-'DRE DCL E D-ESPAÇO'!O14/1000 -> -1402.2508 | O15: =-'DRE DCL E D-ESPAÇO'!P14/1000 -> -1371.4789 | P15: =IFERROR(O15/N15-1," ") -> -0.021944654 | Q15: =IFERROR(O15/M15-1," ") -> 0.32161955
B16: 11 - LUCRO ANTES DO IR/CSLL | C16: =C12+C13 -> 326.90626 | D16: =D12+D13 -> 448.6241 | E16: =E12+E13 -> 600.65062 | F16: =IFERROR(E16/D16-1," ") -> 0.33887283 | G16: =IFERROR(E16/C16-1," ") -> 0.83737876 | H16: =H12+H13 -> 2369.194 | I16: =I12+I13 -> 2258.8197 | J16: =J12+J13 -> 3155.8775 | K16: =IFERROR(J16/I16-1," ") -> 0.39713563 | L16: =IFERROR(J16/H16-1," ") -> 0.3320469 | M16: =M12+M13 -> 4956.9562 | N16: =N12+N13 -> 4861.1041 | O16: =O12+O13 -> 6330.9213 | P16: =IFERROR(O16/N16-1," ") -> 0.30236282 | Q16: =IFERROR(O16/M16-1," ") -> 0.27717919
B17: 12 - IR/CSLL | C17: =-'DRE DCL E D-ESPAÇO'!B16/1000 -> -99.92697 | D17: =-'DRE DCL E D-ESPAÇO'!C16/1000 -> -127.833 | E17: =-'DRE DCL E D-ESPAÇO'!D16/1000 -> -152.66363 | F17: =IFERROR(E17/D17-1," ") -> 0.19424272 | G17: =IFERROR(E17/C17-1," ") -> 0.52775202 | H17: =-'DRE DCL E D-ESPAÇO'!H16/1000 -> -618.35955 | I17: =-'DRE DCL E D-ESPAÇO'!I16/1000 -> -769.64207 | J17: =-'DRE DCL E D-ESPAÇO'!J16/1000 -> -850.70292 | K17: =IFERROR(J17/I17-1," ") -> 0.10532279 | L17: =IFERROR(J17/H17-1," ") -> 0.37574154 | M17: =-'DRE DCL E D-ESPAÇO'!N16/1000 -> -1340.7368 | N17: =-'DRE DCL E D-ESPAÇO'!O16/1000 -> -1462.0052 | O17: =-'DRE DCL E D-ESPAÇO'!P16/1000 -> -1691.415 | P17: =IFERROR(O17/N17-1," ") -> 0.15691447 | Q17: =IFERROR(O17/M17-1," ") -> 0.26155634
B18: 13 - LUCRO LÍQUIDO | C18: =C16+C17 -> 226.97929 | D18: =D16+D17 -> 320.7911 | E18: =E16+E17 -> 447.98699 | F18: =IFERROR(E18/D18-1," ") -> 0.39650692 | G18: =IFERROR(E18/C18-1," ") -> 0.97369104 | H18: =H16+H17 -> 1750.8344 | I18: =I16+I17 -> 1489.1776 | J18: =J16+J17 -> 2305.1745 | K18: =IFERROR(J18/I18-1," ") -> 0.54795138 | L18: =IFERROR(J18/H18-1," ") -> 0.31661482 | M18: =M16+M17 -> 3616.2194 | N18: =N16+N17 -> 3399.0989 | O18: =O16+O17 -> 4639.5063 | P18: =IFERROR(O18/N18-1," ") -> 0.36492241 | Q18: =IFERROR(O18/M18-1," ") -> 0.28297147
B19: Margem EBITDA/ROL | C19: =C10/C6 -> 0.52352348 | D19: =D10/D6 -> 0.6029865 | E19: =E10/E6 -> 0.68651229 | H19: =H10/H6 -> 0.5940205 | I19: =I10/I6 -> 0.56998808 | J19: =J10/J6 -> 0.65402009 | M19: =M10/M6 -> 0.60893919 | N19: =N10/N6 -> 0.58987693 | O19: =O10/O6 -> 0.65412563
B22: DRE D-ESPAÇO (Em R$/Mil) | C22: JUNHO | H22: ACUMULADO JANEIRO A JUNHO | M22: RITMO
C23: Real 2025 | D23: Orç 2026 | E23: Real 2026 | F23: Real 2026 x Orç 2026 | G23: Real 2026 x Real 2025 | H23: Real 2025 | I23: Orç 2026 | J23: Real 2026 | K23: Real 2026 x Orç 2026 | L23: Real 2026 x Real 2025 | M23: Real 2025 | N23: Orç 2026 | O23: Ritmo 2026 | P23: Ritmo 2026 x Orç 2026 | Q23: Ritmo 2026 x Real 2025
B24: 1 - FATURAMENTO BRUTO | C24: ='DRE DCL E D-ESPAÇO'!B23/1000 -> 196.49505 | D24: ='DRE DCL E D-ESPAÇO'!C23/1000 -> 208.34797 | E24: ='DRE DCL E D-ESPAÇO'!D23/1000 -> 222.85259 | F24: =IFERROR(E24/D24-1," ") -> 0.069617285 | G24: =IFERROR(E24/C24-1," ") -> 0.13413844 | H24: ='DRE DCL E D-ESPAÇO'!H23/1000 -> 1164.6683 | I24: ='DRE DCL E D-ESPAÇO'!I23/1000 -> 1248.6041 | J24: ='DRE DCL E D-ESPAÇO'!J23/1000 -> 1294.6718 | K24: =IFERROR(J24/I24-1," ") -> 0.036895338 | L24: =IFERROR(J24/H24-1," ") -> 0.11162272 | M24: ='DRE DCL E D-ESPAÇO'!N23/1000 -> 2393.6629 | N24: ='DRE DCL E D-ESPAÇO'!O23/1000 -> 2504.9619 | O24: ='DRE DCL E D-ESPAÇO'!P23/1000 -> 2585.272 | P24: =IFERROR(O24/N24-1," ") -> 0.032060412 | Q24: =IFERROR(O24/M24-1," ") -> 0.080048494
B25: 2 - DEDUÇÃO DE FATURAMENTO | C25: =-'DRE DCL E D-ESPAÇO'!B24/1000 -> -7.17207 | D25: =-'DRE DCL E D-ESPAÇO'!C24/1000 -> -7.6047 | E25: =-'DRE DCL E D-ESPAÇO'!D24/1000 -> -8.13412 | F25: =IFERROR(E25/D25-1," ") -> 0.069617473 | G25: =IFERROR(E25/C25-1," ") -> 0.1341384 | H25: =-'DRE DCL E D-ESPAÇO'!H24/1000 -> -42.91042 | I25: =-'DRE DCL E D-ESPAÇO'!I24/1000 -> -45.57404 | J25: =-'DRE DCL E D-ESPAÇO'!J24/1000 -> -48.36533 | K25: =IFERROR(J25/I25-1," ") -> 0.061247368 | L25: =IFERROR(J25/H25-1," ") -> 0.1271232 | M25: =-'DRE DCL E D-ESPAÇO'!N24/1000 -> -88.6281 | N25: =-'DRE DCL E D-ESPAÇO'!O24/1000 -> -91.4311 | O25: =-'DRE DCL E D-ESPAÇO'!P24/1000 -> -95.472 | P25: =IFERROR(O25/N25-1," ") -> 0.044196121 | Q25: =IFERROR(O25/M25-1," ") -> 0.07722043
B26: 3 - FATURAMENTO LÍQUIDO | C26: =C24+C25 -> 189.32298 | D26: =D24+D25 -> 200.74327 | E26: =E24+E25 -> 214.71847 | F26: =IFERROR(E26/D26-1," ") -> 0.069617278 | G26: =IFERROR(E26/C26-1," ") -> 0.13413844 | H26: =H24+H25 -> 1121.7579 | I26: =I24+I25 -> 1203.0301 | J26: =J24+J25 -> 1246.3064 | K26: =IFERROR(J26/I26-1," ") -> 0.035972817 | L26: =IFERROR(J26/H26-1," ") -> 0.11102979 | M26: =M24+M25 -> 2305.0348 | N26: =N24+N25 -> 2413.5308 | O26: =O24+O25 -> 2489.8 | P26: =IFERROR(O26/N26-1," ") -> 0.031600678 | Q26: =IFERROR(O26/M26-1," ") -> 0.080157233
B27: 4 - CUSTO MERCADORIA VENDIDA | C27: 0 | D27: 0 | E27: 0 | F27: 0 | G27: 0 | H27: 0 | I27: 0 | J27: 0 | K27: 0 | L27: 0 | M27: 0 | N27: 0 | O27: 0 | P27: 0 | Q27: 0
B28: 5 - LUCRO BRUTO | C28: =C26+C27 -> 189.32298 | D28: =D26+D27 -> 200.74327 | E28: =E26+E27 -> 214.71847 | F28: =IFERROR(E28/D28-1," ") -> 0.069617278 | G28: =IFERROR(E28/C28-1," ") -> 0.13413844 | H28: =H26 -> 1121.7579 | I28: =I26 -> 1203.0301 | J28: =J26 -> 1246.3064 | K28: =IFERROR(J28/I28-1," ") -> 0.035972817 | L28: =IFERROR(J28/H28-1," ") -> 0.11102979 | M28: =M26+M27 -> 2305.0348 | N28: =N26+N27 -> 2413.5308 | O28: =O26+O27 -> 2489.8 | P28: =IFERROR(O28/N28-1," ") -> 0.031600678 | Q28: =IFERROR(O28/M28-1," ") -> 0.080157233
B29: 6 - DESPESAS OPERACIONAIS | C29: =-'DRE DCL E D-ESPAÇO'!B26/1000+'DRE DCL E D-ESPAÇO'!B30/1000 -> -79.55277 | D29: =-'DRE DCL E D-ESPAÇO'!C26/1000+'DRE DCL E D-ESPAÇO'!C30/1000 -> -91.54109 | E29: =-'DRE DCL E D-ESPAÇO'!D26/1000+'DRE DCL E D-ESPAÇO'!D30/1000 -> -90.55219 | F29: =IFERROR(E29/D29-1," ") -> -0.010802799 | G29: =IFERROR(E29/C29-1," ") -> 0.13826571 | H29: =-'DRE DCL E D-ESPAÇO'!H26/1000+'DRE DCL E D-ESPAÇO'!H30/1000 -> -492.48162 | I29: =-'DRE DCL E D-ESPAÇO'!I26/1000+'DRE DCL E D-ESPAÇO'!I30/1000 -> -568.65299 | J29: =-'DRE DCL E D-ESPAÇO'!J26/1000+'DRE DCL E D-ESPAÇO'!J30/1000 -> -530.33505 | K29: =IFERROR(J29/I29-1," ") -> -0.067383696 | L29: =IFERROR(J29/H29-1," ") -> 0.076862625 | M29: =-'DRE DCL E D-ESPAÇO'!N26/1000+'DRE DCL E D-ESPAÇO'!N30/1000 -> -992.48878 | N29: =-'DRE DCL E D-ESPAÇO'!O26/1000+'DRE DCL E D-ESPAÇO'!O30/1000 -> -1087.2307 | O29: =-'DRE DCL E D-ESPAÇO'!P26/1000+'DRE DCL E D-ESPAÇO'!P30/1000 -> -1063.109 | P29: =IFERROR(O29/N29-1," ") -> -0.022186395 | Q29: =IFERROR(O29/M29-1," ") -> 0.071154678
B30: 7 - EBITDA | C30: =C28+C29 -> 109.77021 | D30: =D28+D29 -> 109.20218 | E30: =E28+E29 -> 124.16628 | F30: =IFERROR(E30/D30-1," ") -> 0.13703115 | G30: =IFERROR(E30/C30-1," ") -> 0.13114733 | H30: =H28+H29 -> 629.27628 | I30: =I28+I29 -> 634.37707 | J30: =J28+J29 -> 715.97139 | K30: =IFERROR(J30/I30-1," ") -> 0.12862117 | L30: =IFERROR(J30/H30-1," ") -> 0.13776955 | M30: =M28+M29 -> 1312.546 | N30: =N28+N29 -> 1326.3001 | O30: =O28+O29 -> 1426.691 | P30: =IFERROR(O30/N30-1," ") -> 0.075692479 | Q30: =IFERROR(O30/M30-1," ") -> 0.086964563
B31: 8 - DEPRECIAÇÃO | C31: =-'DRE DCL E D-ESPAÇO'!B28/1000 -> -4.71774 | D31: =-'DRE DCL E D-ESPAÇO'!C28/1000 -> -5.72209 | E31: =-'DRE DCL E D-ESPAÇO'!D28/1000 -> -5.36482 | F31: =IFERROR(E31/D31-1," ") -> -0.062436977 | G31: =IFERROR(E31/C31-1," ") -> 0.13715889 | H31: =-'DRE DCL E D-ESPAÇO'!H28/1000 -> -28.30644 | I31: =-'DRE DCL E D-ESPAÇO'!I28/1000 -> -33.86835 | J31: =-'DRE DCL E D-ESPAÇO'!J28/1000 -> -32.28815 | K31: =IFERROR(J31/I31-1," ") -> -0.04665713 | L31: =IFERROR(J31/H31-1," ") -> 0.14066446 | M31: =-'DRE DCL E D-ESPAÇO'!N28/1000 -> -57.54876 | N31: =-'DRE DCL E D-ESPAÇO'!O28/1000 -> -68.20089 | O31: =-'DRE DCL E D-ESPAÇO'!P28/1000 -> -66.621 | P31: =IFERROR(O31/N31-1," ") -> -0.02316524 | Q31: =IFERROR(O31/M31-1," ") -> 0.1576444
B32: 9 - RESULTADO OPERACIONAL | C32: =C30+C31 -> 105.05247 | D32: =D30+D31 -> 103.48009 | E32: =E30+E31 -> 118.80146 | F32: =IFERROR(E32/D32-1," ") -> 0.14806104 | G32: =IFERROR(E32/C32-1," ") -> 0.13087736 | H32: =H30+H31 -> 600.96984 | I32: =I30+I31 -> 600.50872 | J32: =J30+J31 -> 683.68324 | K32: =IFERROR(J32/I32-1," ") -> 0.13850676 | L32: =IFERROR(J32/H32-1," ") -> 0.1376332 | M32: =M30+M31 -> 1254.9972 | N32: =N30+N31 -> 1258.0992 | O32: =O30+O31 -> 1360.07 | P32: =IFERROR(O32/N32-1," ") -> 0.081051504 | Q32: =IFERROR(O32/M32-1," ") -> 0.08372349
B33: 10 - OUTRAS RECEITAS E DESPESAS | C33: =C34+C35 -> -0.01628 | D33: =D34+D35 -> -0.88176 | E33: =E34+E35 -> -1.11663 | F33: =-IFERROR(E33/D33-1," ") -> -0.266365 | G33: =IFERROR(E33/C33-1," ") -> 67.589066 | H33: =H34+H35 -> 3.87313 | I33: =I34+I35 -> -5.59899 | J33: =J34+J35 -> -2.93225 | K33: =IFERROR(J33/I33-1," ") -> -0.47628947 | L33: =IFERROR(J33/H33-1," ") -> -1.757075 | M33: =M34+M35 -> 2.8025 | N33: =N34+N35 -> -10.98086 | O33: =O34+O35 -> -8.31412 | P33: =IFERROR(O33/N33-1," ") -> -0.24285347 | Q33: =-IFERROR(O33/M33-1," ") -> 3.9666797
B34: 10.1 - RECEITAS FINANCEIRAS | C34: ='DRE DCL E D-ESPAÇO'!B32/1000 -> 2.0482 | D34: ='DRE DCL E D-ESPAÇO'!C32/1000 -> 1.55 | E34: ='DRE DCL E D-ESPAÇO'!D32/1000 -> 1.96712 | F34: =IFERROR(E34/D34-1," ") -> 0.26910968 | G34: =IFERROR(E34/C34-1," ") -> -0.039585978 | H34: ='DRE DCL E D-ESPAÇO'!H32/1000 -> 15.60876 | I34: ='DRE DCL E D-ESPAÇO'!I32/1000 -> 9.3 | J34: ='DRE DCL E D-ESPAÇO'!J32/1000 -> 12.90349 | K34: =IFERROR(J34/I34-1," ") -> 0.38747204 | L34: =IFERROR(J34/H34-1," ") -> -0.17331742 | M34: ='DRE DCL E D-ESPAÇO'!N32/1000 -> 28.1424 | N34: ='DRE DCL E D-ESPAÇO'!O32/1000 -> 18.6 | O34: ='DRE DCL E D-ESPAÇO'!P32/1000 -> 22.20349 | P34: =IFERROR(O34/N34-1," ") -> 0.19373602 | Q34: =IFERROR(O34/M34-1," ") -> -0.21103069
B35: 10.2 - DESPESAS FINANCEIRAS | C35: =-'DRE DCL E D-ESPAÇO'!B33/1000 -> -2.06448 | D35: =-'DRE DCL E D-ESPAÇO'!C33/1000 -> -2.43176 | E35: =-'DRE DCL E D-ESPAÇO'!D33/1000 -> -3.08375 | F35: =IFERROR(E35/D35-1," ") -> 0.26811445 | G35: =IFERROR(E35/C35-1," ") -> 0.49371755 | H35: =-'DRE DCL E D-ESPAÇO'!H33/1000 -> -11.73563 | I35: =-'DRE DCL E D-ESPAÇO'!I33/1000 -> -14.89899 | J35: =-'DRE DCL E D-ESPAÇO'!J33/1000 -> -15.83574 | K35: =IFERROR(J35/I35-1," ") -> 0.062873389 | L35: =IFERROR(J35/H35-1," ") -> 0.34937281 | M35: =-'DRE DCL E D-ESPAÇO'!N33/1000 -> -25.3399 | N35: =-'DRE DCL E D-ESPAÇO'!O33/1000 -> -29.58086 | O35: =-'DRE DCL E D-ESPAÇO'!P33/1000 -> -30.51761 | P35: =IFERROR(O35/N35-1," ") -> 0.031667436 | Q35: =IFERROR(O35/M35-1," ") -> 0.20433032
B36: 11 - LUCRO ANTES DO IR/CSLL | C36: =C32+C33 -> 105.03619 | D36: =D32+D33 -> 102.59833 | E36: =E32+E33 -> 117.68483 | F36: =IFERROR(E36/D36-1," ") -> 0.1470443 | G36: =IFERROR(E36/C36-1," ") -> 0.12042173 | H36: =H32+H33 -> 604.84297 | I36: =I32+I33 -> 594.90973 | J36: =J32+J33 -> 680.75099 | K36: =IFERROR(J36/I36-1," ") -> 0.14429292 | L36: =IFERROR(J36/H36-1," ") -> 0.12550038 | M36: =M32+M33 -> 1257.7997 | N36: =N32+N33 -> 1247.1183 | O36: =O32+O33 -> 1351.7559 | P36: =IFERROR(O36/N36-1," ") -> 0.083903483 | Q36: =IFERROR(O36/M36-1," ") -> 0.074698798
B37: 12 - IR/CSLL | C37: =-'DRE DCL E D-ESPAÇO'!B35/1000 -> -20.69296 | D37: =-'DRE DCL E D-ESPAÇO'!C35/1000 -> -21.90603 | E37: =-'DRE DCL E D-ESPAÇO'!D35/1000 -> -23.46097 | F37: =IFERROR(E37/D37-1," ") -> 0.070982282 | G37: =IFERROR(E37/C37-1," ") -> 0.13376578 | H37: =-'DRE DCL E D-ESPAÇO'!H35/1000 -> -124.52193 | I37: =-'DRE DCL E D-ESPAÇO'!I35/1000 -> -131.25352 | J37: =-'DRE DCL E D-ESPAÇO'!J35/1000 -> -137.02372 | K37: =IFERROR(J37/I37-1," ") -> 0.04396225 | L37: =IFERROR(J37/H37-1," ") -> 0.1003983 | M37: =-'DRE DCL E D-ESPAÇO'!N35/1000 -> -253.29842 | N37: =-'DRE DCL E D-ESPAÇO'!O35/1000 -> -263.43719 | O37: =-'DRE DCL E D-ESPAÇO'!P35/1000 -> -272.933 | P37: =IFERROR(O37/N37-1," ") -> 0.036045822 | Q37: =IFERROR(O37/M37-1," ") -> 0.077515604
B38: 13 - LUCRO LÍQUIDO | C38: =C36+C37 -> 84.34323 | D38: =D36+D37 -> 80.6923 | E38: =E36+E37 -> 94.22386 | F38: =IFERROR(E38/D38-1," ") -> 0.16769332 | G38: =IFERROR(E38/C38-1," ") -> 0.11714787 | H38: =H36+H37 -> 480.32104 | I38: =I36+I37 -> 463.65621 | J38: =J36+J37 -> 543.72727 | K38: =IFERROR(J38/I38-1," ") -> 0.17269489 | L38: =IFERROR(J38/H38-1," ") -> 0.13200802 | M38: =M36+M37 -> 1004.5013 | N38: =N36+N37 -> 983.68112 | O38: =O36+O37 -> 1078.8229 | P38: =IFERROR(O38/N38-1," ") -> 0.096720124 | Q38: =IFERROR(O38/M38-1," ") -> 0.073988503
B39: Margem EBITDA/ROL | C39: =C30/C26 -> 0.57980394 | D39: =D30/D26 -> 0.54398925 | E39: =E30/E26 -> 0.5782748 | H39: =H30/H26 -> 0.56097334 | I39: =I30/I26 -> 0.52731606 | J39: =J30/J26 -> 0.5744746 | M39: =M30/M26 -> 0.56942568 | N39: =N30/N26 -> 0.54952689 | O39: =O30/O26 -> 0.5730143
B43: SHOPPING
B44: Outras receitas e despesas operacionais deverá somar com despesas operacionais (está abaixo do ebitda).
B45: Resultado não operacional = Resultado financeiro líquido.
F46: O sinal ficará positivo quando a recuperação for menor que as depesas. Do contrário, ela subirá negativa.
B53: D-ESPAÇO
B54: Resultado não operacional: soma das contas Outras receitas e despesas operacionais e Resultado financeiro líquido(Resultado não operacional).
B57: DRE DEMINVEST (Em R$/Mil) | C57: FEVEREIRO/2021 | M57: RITMO ANO
C58: Real 2020 | D58: Orç 2021 | E58: Real 2021 | F58: Real 2021 x Real 2020 | G58: Real 2021 x Orç 2021 | M58: Real 2020 | N58: Orç 2021 | O58: Real 2021 | P58: Real 2021 x Real 2020 | Q58: Real 2021 x Orç 2021

Sheet Quadro DRE Consolidado
B2: DRE CR COMB (Em R$/Mil) | C2: MAIO | H2: ACUMULADO JANEIRO A MAIO | M2: RITMO
C3: Real 2024 | D3: Orç 2025 | E3: Real 2025 | F3: Real 2025 x Orç 2025 | G3: Real 2025 x Real 2024 | H3: Real 2024 | I3: Orç 2025 | J3: Real 2025 | K3: Real 2025 x Orç 2025 | L3: Real 2025 x Real 2024 | M3: Real 2024 | N3: Orç 2025 | O3: Ritmo 2025 | P3: Ritmo 2025 x Orç 2025 | Q3: Ritmo 2025 x Real 2024
B4: 1 - FATURAMENTO BRUTO | C4: 0 | D4: 0 | E4: 0 | F4: 0 | G4: 0 | H4: 0 | I4: 0 | J4: 0 | K4: 0 | L4: 0 | M4: 0 | N4: 0 | O4: 0 | P4: 0 | Q4: 0
B5: 2 - DEDUÇÃO DE FATURAMENTO | C5: 0 | D5: 0 | E5: 0 | F5: 0 | G5: 0 | H5: 0 | I5: 0 | J5: 0 | K5: 0 | L5: 0 | M5: 0 | N5: 0 | O5: 0 | P5: 0 | Q5: 0
B6: 3 - FATURAMENTO LÍQUIDO | C6: 0 | D6: 0 | E6: 0 | F6: 0 | G6: 0 | H6: 0 | I6: 0 | J6: 0 | K6: 0 | L6: 0 | M6: 0 | N6: 0 | O6: 0 | P6: 0 | Q6: 0
B7: 4 - CUSTO MERCADORIA VENDIDA | C7: 0 | D7: 0 | E7: 0 | F7: 0 | G7: 0 | H7: 0 | I7: 0 | J7: 0 | K7: 0 | L7: 0 | M7: 0 | N7: 0 | O7: 0 | P7: 0 | Q7: 0
B8: 5 - LUCRO BRUTO | C8: 0 | D8: 0 | E8: 0 | F8: 0 | G8: 0 | H8: 0 | I8: 0 | J8: 0 | K8: 0 | L8: 0 | M8: 0 | N8: 0 | O8: 0 | P8: 0 | Q8: 0
B9: 6 - DESPESAS OPERACIONAIS | C9: =('DRE Posto EsteioCGS'!C35+'DRE Posto EsteioCGS'!C43)/1000 -> -48.48761 | D9: =('DRE Posto EsteioCGS'!D35+'DRE Posto EsteioCGS'!D43)/1000 -> -3.96875 | E9: =('DRE Posto EsteioCGS'!E35+'DRE Posto EsteioCGS'!E43)/1000 -> 0 | F9: =- IFERROR(E9/D9-1," ") -> 1 | G9: =-IFERROR(E9/C9-1," ") -> 1 | H9: =('DRE Posto EsteioCGS'!G35+'DRE Posto EsteioCGS'!G43)/1000 -> -238.23188 | I9: =('DRE Posto EsteioCGS'!H35+'DRE Posto EsteioCGS'!H43)/1000 -> -38.72575 | J9: =('DRE Posto EsteioCGS'!I35+'DRE Posto EsteioCGS'!I43)/1000 -> 151.89878 | K9: =IFERROR(J9/I9-1," ") -> -4.9224232 | L9: =IFERROR(J9/H9-1," ") -> -1.637609 | M9: =('DRE Posto EsteioCGS'!K35+'DRE Posto EsteioCGS'!K43)/1000 -> -256.31814 | N9: =('DRE Posto EsteioCGS'!L35+'DRE Posto EsteioCGS'!L43)/1000 -> -46.36325 | O9: =('DRE Posto EsteioCGS'!M35+'DRE Posto EsteioCGS'!M43)/1000 -> 151.89878 | P9: =-IFERROR(O9/N9-1," ") -> 4.2762755 | Q9: =IFERROR(O9/M9-1," ") -> -1.5926181
B10: 7 - EBITDA | C10: =C8+C9 -> -48.48761 | D10: =D8+D9 -> -3.96875 | E10: =E8+E9 -> 0 | F10: =-IFERROR(E10/D10-1," ") -> 1 | G10: =-IFERROR(E10/C10-1," ") -> 1 | H10: =H8+H9 -> -238.23188 | I10: =I8+I9 -> -38.72575 | J10: =J8+J9 -> 151.89878 | K10: =IFERROR(J10/I10-1," ") -> -4.9224232 | L10: =IFERROR(J10/H10-1," ") -> -1.637609 | M10: =M8+M9 -> -256.31814 | N10: =N8+N9 -> -46.36325 | O10: =O8+O9 -> 151.89878 | P10: =-IFERROR(O10/N10-1," ") -> 4.2762755 | Q10: =IFERROR(O10/M10-1," ") -> -1.5926181
B11: 8 - DEPRECIAÇÃO | C11: ='DRE Posto EsteioCGS'!C45/1000 -> 0 | D11: 0 | E11: 0 | F11: 0 | G11: =IFERROR(E11/C11-1," ") | H11: ='DRE Posto EsteioCGS'!G45/1000 -> -13.03546 | I11: ='DRE Posto EsteioCGS'!H45/1000 -> 0 | J11: ='DRE Posto EsteioCGS'!I45/1000 -> 0 | K11: =IFERROR(J11/I11-1," ") | L11: =IFERROR(J11/H11-1," ") -> -1 | M11: =('DRE Posto EsteioCGS'!K37+'DRE Posto EsteioCGS'!K45)/1000 -> -13.03546 | N11: 0 | O11: 0 | P11: =IFERROR(O11/N11-1," ") | Q11: =IFERROR(O11/M11-1," ") -> -1
B12: 9 - RESULTADO OPERACIONAL | C12: =C10+C11 -> -48.48761 | D12: =D10+D11 -> -3.96875 | E12: =E10+E11 -> 0 | F12: =-IFERROR(E12/D12-1," ") -> 1 | G12: =-IFERROR(E12/C12-1," ") -> 1 | H12: =H10+H11 -> -251.26734 | I12: =I10+I11 -> -38.72575 | J12: =J10+J11 -> 151.89878 | K12: =IFERROR(J12/I12-1," ") -> -4.9224232 | L12: =IFERROR(J12/H12-1," ") -> -1.6045305 | M12: =M10+M11 -> -269.3536 | N12: =N10+N11 -> -46.36325 | O12: =O10+O11 -> 151.89878 | P12: =-IFERROR(O12/N12-1," ") -> 4.2762755 | Q12: =IFERROR(O12/M12-1," ") -> -1.5639382
B13: 10 - OUTRAS RECEITAS E DESPESAS | C13: =('DRE Posto EsteioCGS'!C38+'DRE Posto EsteioCGS'!C47)/1000 -> 1.78459 | D13: =('DRE Posto EsteioCGS'!D38+'DRE Posto EsteioCGS'!D47)/1000 -> 0.23111 | E13: =('DRE Posto EsteioCGS'!E38+'DRE Posto EsteioCGS'!E47)/1000 -> 0 | F13: =IFERROR(E13/D13-1," ") -> -1 | G13: =IFERROR(E13/C13-1," ") -> -1 | H13: ='DRE Posto EsteioCGS'!G47/1000+'DRE Posto EsteioCGS'!G38/1000 -> 77.901 | I13: ='DRE Posto EsteioCGS'!H47/1000 -> 3.7582 | J13: ='DRE Posto EsteioCGS'!I47/1000 -> 45.86464 | K13: =IFERROR(J13/I13-1," ") -> 11.203885 | L13: =IFERROR(J13/H13-1," ") -> -0.41124453 | M13: ='DRE Posto EsteioCGS'!K47/1000 -> 101.35316 | N13: ='DRE Posto EsteioCGS'!L47/1000 -> 4.15908 | O13: ='DRE Posto EsteioCGS'!M47/1000 -> 46.68481 | P13: =IFERROR(O13/N13-1," ") -> 10.224792 | Q13: =IFERROR(O13/M13-1," ") -> -0.53938476
B14: 11 - LUCRO ANTES DO IR/CSLL | C14: =C12+C13 -> -46.70302 | D14: =D12+D13 -> -3.73764 | E14: =E12+E13 -> 0 | F14: =-IFERROR(E14/D14-1," ") -> 1 | G14: =IFERROR(E14/C14-1," ") -> -1 | H14: =H12+H13 -> -173.36634 | I14: =I12+I13 -> -34.96755 | J14: =J12+J13 -> 197.76342 | K14: =IFERROR(J14/I14-1," ") -> -6.655627 | L14: =-IFERROR(J14/H14-1," ") -> 2.1407256 | M14: =M12+M13 -> -168.00044 | N14: =N12+N13 -> -42.20417 | O14: =O12+O13 -> 198.58359 | P14: =-IFERROR(O14/N14-1," ") -> 5.7053073 | Q14: =-IFERROR(O14/M14-1," ") -> 2.1820421
B15: 12 - IR/CSLL | C15: ='DRE Posto EsteioCGS'!C49/1000 -> 0 | D15: 0 | E15: 0 | F15: 0 | G15: =IFERROR(E15/C15-1," ") | H15: ='DRE Posto EsteioCGS'!G49/1000 -> 0 | I15: 0 | J15: 0 | K15: 0 | L15: 1 | M15: =('DRE Posto EsteioCGS'!K37+'DRE Posto EsteioCGS'!K49)/1000 -> 0 | N15: 0 | O15: 0 | P15: 0 | Q15: =IFERROR(O15/M15-1," ")
B16: 13 - LUCRO LÍQUIDO | C16: =C14+C15 -> -46.70302 | D16: =D14+D15 -> -3.73764 | E16: =E14+E15 -> 0 | F16: =-IFERROR(E16/D16-1," ") -> 1 | G16: =IFERROR(E16/C16-1," ") -> -1 | H16: =H14+H15 -> -173.36634 | I16: =I14+I15 -> -34.96755 | J16: =J14+J15 -> 197.76342 | K16: =IFERROR(J16/I16-1," ") -> -6.655627 | L16: =-IFERROR(J16/H16-1," ") -> 2.1407256 | M16: =M14+M15 -> -168.00044 | N16: =N14+N15 -> -42.20417 | O16: =O14+O15 -> 198.58359 | P16: =-IFERROR(O16/N16-1," ") -> 5.7053073 | Q16: =-IFERROR(O16/M16-1," ") -> 2.1820421
B17: Margem EBITDA/ROL | C17: 0 | D17: 0 | E17: 0 | H17: 0 | I17: 0 | J17: 0 | M17: 0 | N17: 0 | O17: 0
B18: Margem CMV/ROL | C18: =C7/C6 -> #DIV/0! | D18: =D7/D6 -> #DIV/0! | E18: =E7/E6 -> #DIV/0! | H18: =H7/H6 -> #DIV/0! | I18: =I7/I6 -> #DIV/0! | J18: =J7/J6 -> #DIV/0! | M18: =M7/M6 -> #DIV/0! | N18: =N7/N6 -> #DIV/0! | O18: =O7/O6 -> #DIV/0!
B22: DRE CAPITAL REALTY/DEMERCADO | C22: =C2 -> MAIO | H22: =H2 -> ACUMULADO JANEIRO A MAIO | M22: RITMO
C23: Real 2024 | D23: Orç 2025 | E23: Real 2025 | F23: Real 2025 x Orç 2025 | G23: Real 2025 x Real 2024 | H23: Real 2023 | I23: Orç 2024 | J23: Real 2024 | K23: Real 2024 x Orç 2024 | L23: Real 2024 x Real 2023 | M23: Real 2024 | N23: Orç 2025 | O23: Ritmo 2025 | P23: Ritmo 2025 x Orç 2025 | Q23: Ritmo 2025 x Real 2024
B24: 1 - FATURAMENTO BRUTO | C24: =('Matriz senha_capital OK'!$C$2+'Demercado_senha capital OK'!$C$2)/1000 -> 4573.739 | D24: =('Matriz senha_capital OK'!$C$18+'Demercado_senha capital OK'!$C$18)/1000 -> 5544.476 | E24: =('Matriz senha_capital OK'!$C$34+'Demercado_senha capital OK'!$C$34)/1000-1 -> 5624.4301 | F24: =IFERROR(E24/C24-1," ") -> 0.22972258 | G24: =IFERROR(E24/D24-1," ") -> 0.014420497 | H24: ='Quadro DRE Apresentação'!H5+'Quadro DRE Apresentação'!H25-1 -> 51175.721 | I24: ='Quadro DRE Apresentação'!I5+'Quadro DRE Apresentação'!I25 -> 56951.157 | J24: ='Quadro DRE Apresentação'!J5+'Quadro DRE Apresentação'!J25 -> 58021.602 | K24: =IFERROR(J24/H24-1," ") -> 0.13377206 | L24: =IFERROR(J24/I24-1," ") -> 0.018795847 | M24: ='Quadro DRE Apresentação'!M5+'Quadro DRE Apresentação'!M25 -> 94045.551 | N24: ='Quadro DRE Apresentação'!N5+'Quadro DRE Apresentação'!N25 -> 105192.11 | O24: ='Quadro DRE Apresentação'!O5+'Quadro DRE Apresentação'!O25-1 -> 107191.04 | P24: =IFERROR(O24/M24-1," ") -> 0.13977794 | Q24: =IFERROR(O24/N24-1," ") -> 0.019002721
B25: 2 - DEDUÇÃO DE FATURAMENTO | C25: =('Matriz senha_capital OK'!$C$3+'Demercado_senha capital OK'!$C$3)/1000 -> -167.96853 | D25: =('Matriz senha_capital OK'!$C$19+'Demercado_senha capital OK'!$C$19)/1000-1 -> -275.55148 | E25: =('Matriz senha_capital OK'!$C$35+'Demercado_senha capital OK'!$C$35)/1000 -> -279.47493 | F25: =IFERROR(E25/C25-1," ") -> 0.66385293 | G25: =IFERROR(E25/D25-1," ") -> 0.014238537 | H25: ='Quadro DRE Apresentação'!H6+'Quadro DRE Apresentação'!H26 -> -2041.7304 | I25: ='Quadro DRE Apresentação'!I6+'Quadro DRE Apresentação'!I26 -> -2078.7172 | J25: ='Quadro DRE Apresentação'!J6+'Quadro DRE Apresentação'!J26 -> -2117.7885 | K25: =IFERROR(J25/H25-1," ") -> 0.037251754 | L25: =IFERROR(J25/I25-1," ") -> 0.018795842 | M25: ='Quadro DRE Apresentação'!M6+'Quadro DRE Apresentação'!M26 -> -3607.5253 | N25: ='Quadro DRE Apresentação'!N6+'Quadro DRE Apresentação'!N26 -> -3839.512 | O25: ='Quadro DRE Apresentação'!O6+'Quadro DRE Apresentação'!O26-1 -> -3913.5096 | P25: =IFERROR(O25/M25-1," ") -> 0.084818349 | Q25: =IFERROR(O25/N25-1," ") -> 0.019272676
B26: 3 - FATURAMENTO LÍQUIDO | C26: =('Matriz senha_capital OK'!$C$4+'Demercado_senha capital OK'!$C$4)/1000 -> 4405.7704 | D26: =('Matriz senha_capital OK'!$C$20+'Demercado_senha capital OK'!$C$20)/1000 -> 5269.9245 | E26: =('Matriz senha_capital OK'!$C$36+'Demercado_senha capital OK'!$C$36)/1000 -> 5345.9551 | F26: =IFERROR(E26/C26-1," ") -> 0.21339848 | G26: =IFERROR(E26/D26-1," ") -> 0.014427275 | H26: ='Quadro DRE Apresentação'!H7+'Quadro DRE Apresentação'!H27 -> 49134.99 | I26: ='Quadro DRE Apresentação'!I7+'Quadro DRE Apresentação'!I27 -> 54872.44 | J26: ='Quadro DRE Apresentação'!J7+'Quadro DRE Apresentação'!J27 -> 55903.814 | K26: =IFERROR(J26/H26-1," ") -> 0.13775974 | L26: =IFERROR(J26/I26-1," ") -> 0.018795847 | M26: ='Quadro DRE Apresentação'!M7+'Quadro DRE Apresentação'!M27+1 -> 90439.026 | N26: ='Quadro DRE Apresentação'!N7+'Quadro DRE Apresentação'!N27 -> 101353.6 | O26: ='Quadro DRE Apresentação'!O7+'Quadro DRE Apresentação'!O27 -> 103279.54 | P26: =IFERROR(O26/M26-1," ") -> 0.14197974 | Q26: =IFERROR(O26/N26-1," ") -> 0.019002173
B27: 4 - CUSTO MERCADORIA VENDIDA | F27: =IFERROR(E27/C27-1," ") | G27: =IFERROR(E27/D27-1," ") | J27: ='Quadro DRE Apresentação'!J8+'Quadro DRE Apresentação'!J28 -> 0 | K27: =IFERROR(J27/H27-1," ") | L27: =IFERROR(J27/I27-1," ") | M27: ='Quadro DRE Apresentação'!M8+'Quadro DRE Apresentação'!M28 -> -75 | N27: ='Quadro DRE Apresentação'!N8+'Quadro DRE Apresentação'!N28 -> 0 | O27: ='Quadro DRE Apresentação'!O8+'Quadro DRE Apresentação'!O28 -> 0 | P27: =IFERROR(O27/M27-1," ") -> -1 | Q27: =IFERROR(O27/N27-1," ")
B28: 5 - LUCRO BRUTO | C28: =('Matriz senha_capital OK'!$C$6+'Demercado_senha capital OK'!$C$6)/1000 -> 4405.7704 | D28: =('Matriz senha_capital OK'!$C$22+'Demercado_senha capital OK'!$C$22)/1000 -> 5269.9245 | E28: =('Matriz senha_capital OK'!$C$38+'Demercado_senha capital OK'!$C$38)/1000 -> 5345.9551 | F28: =IFERROR(E28/C28-1," ") -> 0.21339848 | G28: =IFERROR(E28/D28-1," ") -> 0.014427275 | H28: ='Quadro DRE Apresentação'!H9+'Quadro DRE Apresentação'!H29 -> 49059.883 | I28: ='Quadro DRE Apresentação'!I9+'Quadro DRE Apresentação'!I29 -> 54872.44 | J28: ='Quadro DRE Apresentação'!J9+'Quadro DRE Apresentação'!J29 -> 55903.814 | K28: =IFERROR(J28/H28-1," ") -> 0.13950157 | L28: =IFERROR(J28/I28-1," ") -> 0.018795847 | M28: ='Quadro DRE Apresentação'!M9+'Quadro DRE Apresentação'!M29 -> 90363.026 | N28: ='Quadro DRE Apresentação'!N9+'Quadro DRE Apresentação'!N29 -> 101353.6 | O28: ='Quadro DRE Apresentação'!O9+'Quadro DRE Apresentação'!O29 -> 103279.54 | P28: =IFERROR(O28/M28-1," ") -> 0.1429402 | Q28: =IFERROR(O28/N28-1," ") -> 0.019002173
B29: 6 - DESPESAS OPERACIONAIS | C29: =('Matriz senha_capital OK'!$C$7+'Demercado_senha capital OK'!$C$7)/1000 -> -1286.7854 | D29: =('Matriz senha_capital OK'!$C$23+'Demercado_senha capital OK'!$C$23)/1000 -> -1172.1487 | E29: =('Matriz senha_capital OK'!$C$39+'Demercado_senha capital OK'!$C$39)/1000 -> -925.07345 | F29: =IFERROR(E29/C29-1," ") -> -0.28109734 | G29: =IFERROR(E29/D29-1," ") -> -0.21078832 | H29: ='Quadro DRE Apresentação'!H10+'Quadro DRE Apresentação'!H30 -> -8437.465 | I29: ='Quadro DRE Apresentação'!I10+'Quadro DRE Apresentação'!I30 -> -10439.846 | J29: ='Quadro DRE Apresentação'!J10+'Quadro DRE Apresentação'!J30 -> -9507.5488 | K29: =IFERROR(J29/H29-1," ") -> 0.12682528 | L29: =IFERROR(J29/I29-1," ") -> -0.089301812 | M29: ='Quadro DRE Apresentação'!M10+'Quadro DRE Apresentação'!M30 -> -16421.29 | N29: ='Quadro DRE Apresentação'!N10+'Quadro DRE Apresentação'!N30 -> -18251.295 | O29: ='Quadro DRE Apresentação'!O10+'Quadro DRE Apresentação'!O30 -> -18467.984 | P29: =IFERROR(O29/M29-1," ") -> 0.12463658 | Q29: =IFERROR(O29/N29-1," ") -> 0.01187253
B30: 7 - EBITDA | C30: =('Matriz senha_capital OK'!$C$8+'Demercado_senha capital OK'!$C$8)/1000+1 -> 3119.985 | D30: =(('Matriz senha_capital OK'!$C$24+'Demercado_senha capital OK'!$C$24)/1000)+1 -> 4098.7758 | E30: =('Matriz senha_capital OK'!$C$40+'Demercado_senha capital OK'!$C$40)/1000 -> 4420.8817 | F30: =IFERROR(E30/C30-1," ") -> 0.41695606 | G30: =IFERROR(E30/D30-1," ") -> 0.078585882 | H30: =('Quadro DRE Apresentação'!H11+'Quadro DRE Apresentação'!H31) -> 40622.418 | I30: ='Quadro DRE Apresentação'!I11+'Quadro DRE Apresentação'!I31 -> 44432.594 | J30: ='Quadro DRE Apresentação'!J11+'Quadro DRE Apresentação'!J31 -> 46396.265 | K30: =IFERROR(J30/H30-1," ") -> 0.14213449 | L30: =IFERROR(J30/I30-1," ") -> 0.044194385 | M30: ='Quadro DRE Apresentação'!M11+'Quadro DRE Apresentação'!M31 -> 73941.735 | N30: ='Quadro DRE Apresentação'!N11+'Quadro DRE Apresentação'!N31-1 -> 83100.302 | O30: ='Quadro DRE Apresentação'!O11+'Quadro DRE Apresentação'!O31 -> 84811.551 | P30: =IFERROR(O30/M30-1," ") -> 0.14700515 | Q30: =IFERROR(O30/N30-1," ") -> 0.02059258
B31: 8 - DEPRECIAÇÃO | C31: =('Matriz senha_capital OK'!$C$9+'Demercado_senha capital OK'!$C$9)/1000 -> -419.10592 | D31: =('Matriz senha_capital OK'!$C$25+'Demercado_senha capital OK'!$C$25)/1000 -> -512.80475 | E31: =('Matriz senha_capital OK'!$C$41+'Demercado_senha capital OK'!$C$41)/1000-1 -> -387.87904 | F31: =IFERROR(E31/C31-1," ") -> -0.074508325 | G31: =IFERROR(E31/D31-1," ") -> -0.24361262 | H31: ='Quadro DRE Apresentação'!H12+'Quadro DRE Apresentação'!H32 -> -3425.6746 | I31: ='Quadro DRE Apresentação'!I12+'Quadro DRE Apresentação'!I32 -> -4427.561 | J31: ='Quadro DRE Apresentação'!J12+'Quadro DRE Apresentação'!J32-1 -> -4213.1332 | K31: =IFERROR(J31/H31-1," ") -> 0.22986962 | L31: =IFERROR(J31/I31-1," ") -> -0.048430233 | M31: ='Quadro DRE Apresentação'!M12+'Quadro DRE Apresentação'!M32+1 -> -6835.4976 | N31: ='Quadro DRE Apresentação'!N12+'Quadro DRE Apresentação'!N32 -> -8295.9356 | O31: ='Quadro DRE Apresentação'!O12+'Quadro DRE Apresentação'!O32 -> -7976.2563 | P31: =IFERROR(O31/M31-1," ") -> 0.16688744 | Q31: =IFERROR(O31/N31-1," ") -> -0.038534446
B32: 9 - RESULTADO OPERACIONAL | C32: =('Matriz senha_capital OK'!$C$10+'Demercado_senha capital OK'!$C$10)/1000+1 -> 2700.8791 | D32: =('Matriz senha_capital OK'!$C$26+'Demercado_senha capital OK'!$C$26)/1000-1 -> 3583.971 | E32: =('Matriz senha_capital OK'!$C$42+'Demercado_senha capital OK'!$C$42)/1000 -> 4034.0027 | F32: =IFERROR(E32/C32-1," ") -> 0.49358875 | G32: =IFERROR(E32/D32-1," ") -> 0.12556787 | H32: ='Quadro DRE Apresentação'!H13+'Quadro DRE Apresentação'!H33 -> 37196.743 | I32: ='Quadro DRE Apresentação'!I13+'Quadro DRE Apresentação'!I33 -> 40005.033 | J32: ='Quadro DRE Apresentação'!J13+'Quadro DRE Apresentação'!J33 -> 42184.132 | K32: =IFERROR(J32/H32-1," ") -> 0.13408132 | L32: =IFERROR(J32/I32-1," ") -> 0.054470621 | M32: ='Quadro DRE Apresentação'!M13+'Quadro DRE Apresentação'!M33 -> 67105.238 | N32: ='Quadro DRE Apresentação'!N13+'Quadro DRE Apresentação'!N33 -> 74805.366 | O32: ='Quadro DRE Apresentação'!O13+'Quadro DRE Apresentação'!O33-1 -> 76834.295 | P32: =IFERROR(O32/M32-1," ") -> 0.14498208 | Q32: =IFERROR(O32/N32-1," ") -> 0.027122772
B33: 10 - OUTRAS RECEITAS E DESPESAS | C33: =('Matriz senha_capital OK'!$C$11+'Demercado_senha capital OK'!$C$11)/1000 -> -430.62395 | D33: =('Matriz senha_capital OK'!$C$27+'Demercado_senha capital OK'!$C$27)/1000 -> -525.13773 | E33: =('Matriz senha_capital OK'!$C$43+'Demercado_senha capital OK'!$C$43)/1000 -> -434.73311 | F33: =IFERROR(E33/C33-1," ") -> 0.0095423397 | G33: =IFERROR(E33/D33-1," ") -> -0.17215411 | H33: ='Quadro DRE Apresentação'!H14+'Quadro DRE Apresentação'!H34-1 -> -1527.9673 | I33: ='Quadro DRE Apresentação'!I14+'Quadro DRE Apresentação'!I34 -> -4335.0696 | J33: ='Quadro DRE Apresentação'!J14+'Quadro DRE Apresentação'!J34 -> -3636.036 | K33: =IFERROR(J33/H33-1," ") -> 1.3796557 | L33: =IFERROR(J33/I33-1," ") -> -0.16125084 | M33: ='Quadro DRE Apresentação'!M14+'Quadro DRE Apresentação'!M34-1 -> -3258.1457 | N33: ='Quadro DRE Apresentação'!N14+'Quadro DRE Apresentação'!N34 -> -8164.9746 | O33: ='Quadro DRE Apresentação'!O14+'Quadro DRE Apresentação'!O34-1 -> -7322.4948 | P33: =IFERROR(O33/M33-1," ") -> 1.2474424 | Q33: =IFERROR(O33/N33-1," ") -> -0.10318217
B34: 11 - LUCRO ANTES DO IR/CSLL | C34: =('Matriz senha_capital OK'!$C$12+'Demercado_senha capital OK'!$C$12)/1000 -> 2269.2552 | D34: =('Matriz senha_capital OK'!$C$28+'Demercado_senha capital OK'!$C$28)/1000-1 -> 3058.8333 | E34: =('Matriz senha_capital OK'!$C$44+'Demercado_senha capital OK'!$C$44)/1000 -> 3599.2695 | F34: =IFERROR(E34/C34-1," ") -> 0.58610174 | G34: =IFERROR(E34/D34-1," ") -> 0.17668051 | H34: ='Quadro DRE Apresentação'!H17+'Quadro DRE Apresentação'!H37 -> 35669.776 | I34: ='Quadro DRE Apresentação'!I17+'Quadro DRE Apresentação'!I37 -> 35669.963 | J34: ='Quadro DRE Apresentação'!J17+'Quadro DRE Apresentação'!J37 -> 38548.096 | K34: =IFERROR(J34/H34-1," ") -> 0.080693514 | L34: =IFERROR(J34/I34-1," ") -> 0.080687849 | M34: ='Quadro DRE Apresentação'!M17+'Quadro DRE Apresentação'!M37 -> 63848.092 | N34: ='Quadro DRE Apresentação'!N17+'Quadro DRE Apresentação'!N37-1 -> 66639.392 | O34: ='Quadro DRE Apresentação'!O17+'Quadro DRE Apresentação'!O37 -> 69513.8 | P34: =IFERROR(O34/M34-1," ") -> 0.088737313 | Q34: =IFERROR(O34/N34-1," ") -> 0.043133777
B35: 12 - IR/CSLL | C35: =('Matriz senha_capital OK'!$C$13+'Demercado_senha capital OK'!$C$13)/1000 -> -518.09216 | D35: =('Matriz senha_capital OK'!$C$29+'Demercado_senha capital OK'!$C$29)/1000+1 -> -586.46042 | E35: =('Matriz senha_capital OK'!$C$45+'Demercado_senha capital OK'!$C$45)/1000 -> -640.1935 | F35: =IFERROR(E35/C35-1," ") -> 0.23567494 | G35: =IFERROR(E35/D35-1," ") -> 0.091622688 | H35: ='Quadro DRE Apresentação'!H18+'Quadro DRE Apresentação'!H38 -> -6558.0408 | I35: ='Quadro DRE Apresentação'!I18+'Quadro DRE Apresentação'!I38 -> -7148.3171 | J35: ='Quadro DRE Apresentação'!J18+'Quadro DRE Apresentação'!J38 -> -7366.1152 | K35: =IFERROR(J35/H35-1," ") -> 0.12321888 | L35: =IFERROR(J35/I35-1," ") -> 0.030468437 | M35: ='Quadro DRE Apresentação'!M18+'Quadro DRE Apresentação'!M38-1 -> -12017.946 | N35: ='Quadro DRE Apresentação'!N18+'Quadro DRE Apresentação'!N38 -> -13130.75 | O35: ='Quadro DRE Apresentação'!O18+'Quadro DRE Apresentação'!O38 -> -13566.294 | P35: =IFERROR(O35/M35-1," ") -> 0.12883636 | Q35: =IFERROR(O35/N35-1," ") -> 0.033169808
B36: 13 - LUCRO LIQUIDO | C36: =('Matriz senha_capital OK'!$C$14+'Demercado_senha capital OK'!$C$14)/1000+1 -> 1752.163 | D36: =('Matriz senha_capital OK'!$C$30+'Demercado_senha capital OK'!$C$30)/1000 -> 2472.3729 | E36: =('Matriz senha_capital OK'!$C$46+'Demercado_senha capital OK'!$C$46)/1000 -> 2959.0761 | F36: =IFERROR(E36/C36-1," ") -> 0.68881323 | G36: =IFERROR(E36/D36-1," ") -> 0.1968567 | H36: ='Quadro DRE Apresentação'!H19+'Quadro DRE Apresentação'!H39 -> 29111.735 | I36: ='Quadro DRE Apresentação'!I19+'Quadro DRE Apresentação'!I39 -> 28521.646 | J36: ='Quadro DRE Apresentação'!J19+'Quadro DRE Apresentação'!J39-1 -> 31180.98 | K36: =IFERROR(J36/H36-1," ") -> 0.071079416 | L36: =IFERROR(J36/I36-1," ") -> 0.093239169 | M36: ='Quadro DRE Apresentação'!M19+'Quadro DRE Apresentação'!M39 -> 51831.146 | N36: ='Quadro DRE Apresentação'!N19+'Quadro DRE Apresentação'!N39 -> 53509.642 | O36: ='Quadro DRE Apresentação'!O19+'Quadro DRE Apresentação'!O39 -> 55947.506 | P36: =IFERROR(O36/M36-1," ") -> 0.079418651 | Q36: =IFERROR(O36/N36-1," ") -> 0.045559345
B38: Margem EBITDA/ROL | C38: =C30/C26 -> 0.70815878 | D38: =D30/D26 -> 0.77776746 | E38: =E30/E26 -> 0.82695825 | H38: =H30/H26 -> 0.82675132 | I38: =I30/I26 -> 0.80974336 | J38: =J30/J26 -> 0.82993023 | M38: =M30/M26 -> 0.8175866 | N38: =N30/N26 -> 0.81990481 | O38: =O30/O26 -> 0.82118448
B41: DRE CR ESTACIONAMENTOS (Em R$/Mil) | C41: =C22 -> MAIO | H41: =H2 -> ACUMULADO JANEIRO A MAIO | M41: RITMO
C42: Real 2022 | D42: Orç 2023 | E42: Real 2023 | F42: ∆ Real 2023 x Real 2022 | G42: ∆ Real 2023 x Orç 2023 | H42: Real 2023 | I42: Orç 2024 | J42: Real 2024 | K42: Real 2024 x Orç 2024 | L42: Real 2024 x Real 2023 | M42: Real 2022 | N42: Orç 2023 | O42: Ritmo 2023 | P42: ∆ Real 2023 x Real 2022 | Q42: ∆ Real 2023 x Orç 2023
B43: 1 - FATURAMENTO BRUTO | C43: ='Quadro DRE Apresentação'!C67+'Quadro DRE Apresentação'!C89 -> 471.43324 | D43: ='Quadro DRE Apresentação'!D67+'Quadro DRE Apresentação'!D89 -> 520.386 | E43: ='Quadro DRE Apresentação'!E67+'Quadro DRE Apresentação'!E89 -> 559.40313 | F43: =IFERROR(E43/C43-1," ") -> 0.18660095 | G43: =IFERROR(E43/D43-1," ") -> 0.074977286 | H43: ='Quadro DRE Apresentação'!H67+'Quadro DRE Apresentação'!H89 -> #REF! | I43: ='Quadro DRE Apresentação'!I67+'Quadro DRE Apresentação'!I89 -> #REF! | J43: ='Quadro DRE Apresentação'!J67+'Quadro DRE Apresentação'!J89 -> #REF! | K43: =IFERROR(J43/H43-1," ") | L43: =IFERROR(J43/I43-1," ") | M43: =3487.68-1 -> 3486.68 | N43: 4626.51 | O43: ='Quadro DRE Apresentação'!O67+'Quadro DRE Apresentação'!O89 -> 6021.2993 | P43: =IFERROR(O43/M43-1," ") -> 0.72694347 | Q43: =IFERROR(O43/N43-1," ") -> 0.30147763
B44: 2 - DEDUÇÃO DE FATURAMENTO | C44: ='Quadro DRE Apresentação'!C68+'Quadro DRE Apresentação'!C90 -> -70.38363 | D44: ='Quadro DRE Apresentação'!D68+'Quadro DRE Apresentação'!D90 -> -74.15501 | E44: ='Quadro DRE Apresentação'!E68+'Quadro DRE Apresentação'!E90 -> -80.25691 | F44: =IFERROR(E44/C44-1," ") -> 0.14027807 | G44: =IFERROR(E44/D44-1," ") -> 0.082285742 | H44: ='Quadro DRE Apresentação'!H68+'Quadro DRE Apresentação'!H90 -> #REF! | I44: ='Quadro DRE Apresentação'!I68+'Quadro DRE Apresentação'!I90 -> #REF! | J44: ='Quadro DRE Apresentação'!J68+'Quadro DRE Apresentação'!J90 -> #REF! | K44: =IFERROR(J44/H44-1," ") | L44: =IFERROR(J44/I44-1," ") | M44: -508.02 | N44: -659.27 | O44: ='Quadro DRE Apresentação'!O68+'Quadro DRE Apresentação'!O90 -> -864.57339 | P44: =IFERROR(O44/M44-1," ") -> 0.70184912 | Q44: =IFERROR(O44/N44-1," ") -> 0.31141018
B45: 3 - FATURAMENTO LÍQUIDO | C45: ='Quadro DRE Apresentação'!C69+'Quadro DRE Apresentação'!C91 -> 401.04961 | D45: ='Quadro DRE Apresentação'!D69+'Quadro DRE Apresentação'!D91 -> 446.23099 | E45: ='Quadro DRE Apresentação'!E69+'Quadro DRE Apresentação'!E91 -> 479.14622 | F45: =IFERROR(E45/C45-1," ") -> 0.19473055 | G45: =IFERROR(E45/D45-1," ") -> 0.073762761 | H45: =H43+H44 -> #REF! | I45: ='Quadro DRE Apresentação'!I69+'Quadro DRE Apresentação'!I91 -> #REF! | J45: ='Quadro DRE Apresentação'!J69+'Quadro DRE Apresentação'!J91 -> #REF! | K45: =IFERROR(J45/H45-1," ") | L45: =IFERROR(J45/I45-1," ") | M45: =M43+M44+1 -> 2979.66 | N45: =N43+N44 -> 3967.24 | O45: ='Quadro DRE Apresentação'!O69+'Quadro DRE Apresentação'!O91 -> 5156.7259 | P45: =IFERROR(O45/M45-1," ") -> 0.73064238 | Q45: =IFERROR(O45/N45-1," ") -> 0.29982705
B46: 4 - CUSTO MERCADORIA VENDIDA | C46: 0 | D46: 0 | E46: 0 | F46: 0 | G46: 0 | H46: 0 | I46: 0 | J46: 0 | K46: 0 | L46: 0 | M46: 0 | N46: 0 | O46: 0 | P46: 0 | Q46: 0
B47: 5 - LUCRO BRUTO | C47: =C45+C46 -> 401.04961 | D47: =D45+D46 -> 446.23099 | E47: =E45+E46 -> 479.14622 | F47: =IFERROR(E47/C47-1," ") -> 0.19473055 | G47: =IFERROR(E47/D47-1," ") -> 0.073762761 | H47: =H45+H46 -> #REF! | I47: =I45+I46 -> #REF! | J47: ='Quadro DRE Apresentação'!J71+'Quadro DRE Apresentação'!J93 -> #REF! | K47: =IFERROR(J47/H47-1," ") | L47: =IFERROR(J47/I47-1," ") | M47: =M45+M46 -> 2979.66 | N47: =N45+N46 -> 3967.24 | O47: =O45+O46 -> 5156.7259 | P47: =IFERROR(O47/M47-1," ") -> 0.73064238 | Q47: =IFERROR(O47/N47-1," ") -> 0.29982705
B48: 6 - DESPESAS OPERACIONAIS | C48: ='Quadro DRE Apresentação'!C72+'Quadro DRE Apresentação'!C94 -> -259.60716 | D48: ='Quadro DRE Apresentação'!D72+'Quadro DRE Apresentação'!D94 -> -252.88467 | E48: ='Quadro DRE Apresentação'!E72+'Quadro DRE Apresentação'!E94 -> -219.07085 | F48: =IFERROR(E48/C48-1," ") -> -0.15614481 | G48: =IFERROR(E48/D48-1," ") -> -0.13371242 | H48: ='Quadro DRE Apresentação'!H72+'Quadro DRE Apresentação'!H94 -> #REF! | I48: ='Quadro DRE Apresentação'!I72+'Quadro DRE Apresentação'!I94 -> #REF! | J48: ='Quadro DRE Apresentação'!J72+'Quadro DRE Apresentação'!J94 -> #REF! | K48: =IFERROR(J48/H48-1," ") | L48: =IFERROR(J48/I48-1," ") | M48: =-2664.17-1 -> -2665.17 | N48: -3229.62 | O48: ='Quadro DRE Apresentação'!O72+'Quadro DRE Apresentação'!O94 -> -3205.9569 | P48: =IFERROR(O48/M48-1," ") -> 0.20290899 | Q48: =IFERROR(O48/N48-1," ") -> -0.0073268868
B49: 7 - EBITDA | C49: ='Quadro DRE Apresentação'!C73+'Quadro DRE Apresentação'!C95 -> 141.44245 | D49: ='Quadro DRE Apresentação'!D73+'Quadro DRE Apresentação'!D95 -> 193.34632 | E49: ='Quadro DRE Apresentação'!E73+'Quadro DRE Apresentação'!E95 -> 260.07537 | F49: =IFERROR(E49/C49-1," ") -> 0.83873632 | G49: =IFERROR(E49/D49-1," ") -> 0.34512708 | H49: =H47+H48 -> #REF! | I49: ='Quadro DRE Apresentação'!I73+'Quadro DRE Apresentação'!I95 -> #REF! | J49: ='Quadro DRE Apresentação'!J73+'Quadro DRE Apresentação'!J95 -> #REF! | K49: =IFERROR(J49/H49-1," ") | L49: =IFERROR(J49/I49-1," ") | M49: 315 | N49: =N47+N48 -> 737.62 | O49: ='Quadro DRE Apresentação'!O73+'Quadro DRE Apresentação'!O95 -> 1950.7689 | P49: =IFERROR(O49/M49-1," ") -> 5.1929172 | Q49: =IFERROR(O49/N49-1," ") -> 1.6446801
B50: 8 - DEPRECIAÇÃO | C50: ='Quadro DRE Apresentação'!C74+'Quadro DRE Apresentação'!C96 -> -42.8642 | D50: ='Quadro DRE Apresentação'!D74+'Quadro DRE Apresentação'!D96 -> -46.25173 | E50: ='Quadro DRE Apresentação'!E74+'Quadro DRE Apresentação'!E96 -> -43.08163 | F50: =IFERROR(E50/C50-1," ") -> 0.0050725314 | G50: =IFERROR(E50/D50-1," ") -> -0.068540139 | H50: ='Quadro DRE Apresentação'!H74+'Quadro DRE Apresentação'!H96 -> #REF! | I50: ='Quadro DRE Apresentação'!I96 -> -322.83281 | J50: ='Quadro DRE Apresentação'!J96 -> -299.88051 | K50: =IFERROR(J50/H50-1," ") | L50: =IFERROR(J50/I50-1," ") -> -0.071096553 | M50: -307.23 | N50: -334.86 | O50: ='Quadro DRE Apresentação'!O74+'Quadro DRE Apresentação'!O96 -> -524.71426 | P50: =IFERROR(O50/M50-1," ") -> 0.70788745 | Q50: =IFERROR(O50/N50-1," ") -> 0.56696608
B51: 9 - RESULTADO OPERACIONAL | C51: ='Quadro DRE Apresentação'!C75+'Quadro DRE Apresentação'!C97 -> 98.57825 | D51: ='Quadro DRE Apresentação'!D75+'Quadro DRE Apresentação'!D97 -> 147.09459 | E51: ='Quadro DRE Apresentação'!E75+'Quadro DRE Apresentação'!E97 -> 216.99374 | F51: =IFERROR(E51/C51-1," ") -> 1.2012334 | G51: =IFERROR(E51/D51-1," ") -> 0.47519865 | H51: =H49+H50 -> #REF! | I51: =I49+I50 -> #REF! | J51: ='Quadro DRE Apresentação'!J75+'Quadro DRE Apresentação'!J97 -> #REF! | K51: =-IFERROR(J51/H51-1," ") -> #VALUE! | L51: =IFERROR(J51/I51-1," ") | M51: =M49+M50 -> 7.77 | N51: =N49+N50 -> 402.76 | O51: =O49+O50 -> 1426.0547 | P51: =IFERROR(O51/M51-1," ") -> 182.53342 | Q51: =IFERROR(O51/N51-1," ") -> 2.5407058
B52: 10 - OUTRAS RECEITAS E DESPESAS | C52: ='Quadro DRE Apresentação'!C76+'Quadro DRE Apresentação'!C98 -> -11.99234 | D52: ='Quadro DRE Apresentação'!D76+'Quadro DRE Apresentação'!D98 -> -9.18305 | E52: ='Quadro DRE Apresentação'!E76+'Quadro DRE Apresentação'!E98 -> -0.80054 | F52: =IFERROR(E52/C52-1," ") -> -0.93324572 | G52: =IFERROR(E52/D52-1," ") -> -0.91282417 | H52: ='Quadro DRE Apresentação'!H76+'Quadro DRE Apresentação'!H98 -> #REF! | I52: ='Quadro DRE Apresentação'!I76+'Quadro DRE Apresentação'!I98 -> #REF! | J52: ='Quadro DRE Apresentação'!J76+'Quadro DRE Apresentação'!J98 -> #REF! | K52: =-IFERROR(J52/H52-1," ") -> #VALUE! | L52: =IFERROR(J52/I52-1," ") | M52: -63.31 | N52: 114.37 | O52: ='Quadro DRE Apresentação'!O76+'Quadro DRE Apresentação'!O98 -> -80.58298 | P52: =-IFERROR(O52/M52-1," ") -> -0.27283178 | Q52: =IFERROR(O52/N52-1," ") -> -1.7045814
B53: 11 - LUCRO ANTES DO IR/CSLL | C53: ='Quadro DRE Apresentação'!C77+'Quadro DRE Apresentação'!C101 -> 86.58591 | D53: ='Quadro DRE Apresentação'!D77+'Quadro DRE Apresentação'!D101 -> 137.91154 | E53: ='Quadro DRE Apresentação'!E77+'Quadro DRE Apresentação'!E101 -> 216.1932 | F53: =IFERROR(E53/C53-1," ") -> 1.4968635 | G53: =IFERROR(E53/D53-1," ") -> 0.56762226 | H53: =H51+H52 -> #REF! | I53: =I51+I52 -> #REF! | J53: ='Quadro DRE Apresentação'!J77+'Quadro DRE Apresentação'!J101 -> #REF! | K53: =-IFERROR(J53/H53-1," ") -> #VALUE! | L53: =IFERROR(J53/I53-1," ") | M53: =M51+M52+1 -> -54.54 | N53: =N51+N52 -> 517.13 | O53: =O51+O52 -> 1345.4717 | P53: =-IFERROR(O53/M53-1," ") -> 25.669448 | Q53: =IFERROR(O53/N53-1," ") -> 1.6018055
B54: 12 - IR/CSLL | C54: ='Quadro DRE Apresentação'!C78+'Quadro DRE Apresentação'!C102 -> -15.04749 | D54: ='Quadro DRE Apresentação'!D78+'Quadro DRE Apresentação'!D102 -> -32.3209 | E54: ='Quadro DRE Apresentação'!E78+'Quadro DRE Apresentação'!E102 -> -46.46344 | F54: 0 | G54: =IFERROR(E54/D54-1," ") -> 0.4375664 | H54: 0 | I54: ='Quadro DRE Apresentação'!I78+'Quadro DRE Apresentação'!I102 -> #REF! | J54: ='Quadro DRE Apresentação'!J78+'Quadro DRE Apresentação'!J102 -> #REF! | K54: 0 | L54: =IFERROR(J54/I54-1," ") | M54: 0 | N54: -99.073 | O54: ='Quadro DRE Apresentação'!O78+'Quadro DRE Apresentação'!O102 -> -307.56424 | P54: 0 | Q54: =IFERROR(O54/N54-1," ") -> 2.1044204
B55: 13 - LUCRO LÍQUIDO | C55: ='Quadro DRE Apresentação'!C79+'Quadro DRE Apresentação'!C103 -> 71.53842 | D55: ='Quadro DRE Apresentação'!D79+'Quadro DRE Apresentação'!D103 -> 105.59064 | E55: ='Quadro DRE Apresentação'!E79+'Quadro DRE Apresentação'!E103 -> 169.72976 | F55: =IFERROR(E55/C55-1," ") -> 1.3725679 | G55: =IFERROR(E55/D55-1," ") -> 0.60743187 | H55: =H53+H54 -> #REF! | I55: =I53+I54 -> #REF! | J55: ='Quadro DRE Apresentação'!J79+'Quadro DRE Apresentação'!J103 -> #REF! | K55: =-IFERROR(J55/H55-1," ") -> #VALUE! | L55: =IFERROR(J55/I55-1," ") | M55: =M53+M54 -> -54.54 | N55: =N53+N54 -> 418.057 | O55: =O53+O54 -> 1037.9074 | P55: =-IFERROR(O55/M55-1," ") -> 20.030206 | Q55: =IFERROR(O55/N55-1," ") -> 1.4826936
B56: Margem EBITDA/ROL | C56: =C49/C45 -> 0.35268068 | D56: =D49/D45 -> 0.43328752 | E56: =E49/E45 -> 0.54278915 | F56: 0 | G56: 0 | H56: =H49/H45 -> #REF! | I56: =I49/I45 -> #REF! | J56: =J49/J45 -> #REF! | K56: 0 | L56: 0 | M56: =M49/M45 -> 0.10571676 | N56: =N49/N45 -> 0.18592775 | O56: =O49/O45 -> 0.37829603 | P56: 0 | Q56: 0
B59: DRE CONSOLIDADO CR INFRA | C59: JANEIRO | H59: ACUMULADO JAN A FEV | M59: RITMO | S59: Matriz/Hangar/Garoto
C60: Real 2019 | D60: Orç 2020 | E60: Real 2020 | F60: ∆ Real 2020 x Real 2019 | G60: ∆ Real 2020 x Orc 2020 | H60: Real 2019 | I60: Orç 2020 | J60: Real 2020 | K60: ∆ Real 2020 x Real 2019 | L60: ∆ Real 2020 x Orc 2020 | M60: Real 2019 | N60: Orç 2020 | O60: Ritmo 2020 | P60: ∆ Ritmo 2020 x Real 2019 | Q60: ∆ Ritmo 2020 x Orc 2020
B61: 1 - FATURAMENTO BRUTO | C61: =C43+'Quadro DRE Apresentação'!C5 -> 5901.8662 | D61: =D43+'Quadro DRE Apresentação'!D5 -> 6235.737 | E61: ='Quadro DRE Apresentação'!E5+'Quadro DRE Apresentação'!E67+'Quadro DRE Apresentação'!E89 -> 6686.1931 | F61: =IFERROR(E61/C61-1," ") -> 0.13289474 | G61: =IFERROR(E61/D61-1," ") -> 0.072237837 | H61: ='Quadro DRE Apresentação'!H5+'Quadro DRE Apresentação'!H67+'Quadro DRE Apresentação'!H89-1 -> #REF! | I61: ='Quadro DRE Apresentação'!I5+'Quadro DRE Apresentação'!I67+'Quadro DRE Apresentação'!I89-1 -> #REF! | J61: ='Quadro DRE Apresentação'!J5+'Quadro DRE Apresentação'!J67+'Quadro DRE Apresentação'!J89-1 -> #REF! | K61: =IFERROR(J61/H61-1," ") | L61: =IFERROR(J61/I61-1," ") | M61: ='Quadro DRE Apresentação'!M5+'Quadro DRE Apresentação'!M67+'Quadro DRE Apresentação'!M89 -> 67896.996 | N61: ='Quadro DRE Apresentação'!N5+'Quadro DRE Apresentação'!N67+'Quadro DRE Apresentação'!N89 -> 73811.169 | O61: ='Quadro DRE Apresentação'!O67+'Quadro DRE Apresentação'!O5+'Quadro DRE Apresentação'!O89 -> 75726.167 | P61: =IFERROR(O61/M61-1," ") -> 0.11530953 | Q61: =IFERROR(O61/N61-1," ") -> 0.025944552
B62: 2 - DEDUÇÃO DE FATURAMENTO | C62: =C44+'Quadro DRE Apresentação'!C6 -> -268.59443 | D62: =D44+'Quadro DRE Apresentação'!D6 -> -282.76532 | E62: ='Quadro DRE Apresentação'!E6+'Quadro DRE Apresentação'!E68+'Quadro DRE Apresentação'!E90 -> -303.88475 | F62: =IFERROR(E62/C62-1," ") -> 0.13138887 | G62: =IFERROR(E62/D62-1," ") -> 0.074688897 | H62: ='Quadro DRE Apresentação'!H6+'Quadro DRE Apresentação'!H68+'Quadro DRE Apresentação'!H90 -> #REF! | I62: ='Quadro DRE Apresentação'!I6+'Quadro DRE Apresentação'!I68+'Quadro DRE Apresentação'!I90+1 -> #REF! | J62: ='Quadro DRE Apresentação'!J6+'Quadro DRE Apresentação'!J68+'Quadro DRE Apresentação'!J90 -> #REF! | K62: =IFERROR(J62/H62-1," ") | L62: =IFERROR(J62/I62-1," ") | M62: ='Quadro DRE Apresentação'!M6+'Quadro DRE Apresentação'!M68+'Quadro DRE Apresentação'!M90 -> -3161.7879 | N62: ='Quadro DRE Apresentação'!N6+'Quadro DRE Apresentação'!N68+'Quadro DRE Apresentação'!N90 -> -3275.4893 | O62: ='Quadro DRE Apresentação'!O68+'Quadro DRE Apresentação'!O6+'Quadro DRE Apresentação'!O90 -> -3408.801 | P62: =IFERROR(O62/M62-1," ") -> 0.078124523 | Q62: =IFERROR(O62/N62-1," ") -> 0.040699788
B63: 3 - FATURAMENTO LIQUIDO | C63: =C45+'Quadro DRE Apresentação'!C7 -> 5633.2717 | D63: =D45+'Quadro DRE Apresentação'!D7 -> 5952.9717 | E63: ='Quadro DRE Apresentação'!E7+'Quadro DRE Apresentação'!E69+'Quadro DRE Apresentação'!E91 -> 6382.3084 | F63: =IFERROR(E63/C63-1," ") -> 0.13296654 | G63: =IFERROR(E63/D63-1," ") -> 0.072121412 | H63: ='Quadro DRE Apresentação'!H7+'Quadro DRE Apresentação'!H69+'Quadro DRE Apresentação'!H91-1 -> #REF! | I63: ='Quadro DRE Apresentação'!I7+'Quadro DRE Apresentação'!I69+'Quadro DRE Apresentação'!I91+1 -> #REF! | J63: ='Quadro DRE Apresentação'!J7+'Quadro DRE Apresentação'!J69+'Quadro DRE Apresentação'!J91 -> #REF! | K63: =IFERROR(J63/H63-1," ") | L63: =IFERROR(J63/I63-1," ") | M63: ='Quadro DRE Apresentação'!M7+'Quadro DRE Apresentação'!M69+'Quadro DRE Apresentação'!M91 -> 64735.208 | N63: ='Quadro DRE Apresentação'!N7+'Quadro DRE Apresentação'!N69+'Quadro DRE Apresentação'!N91 -> 70535.68 | O63: ='Quadro DRE Apresentação'!O69+'Quadro DRE Apresentação'!O7+'Quadro DRE Apresentação'!O91 -> 72317.366 | P63: =IFERROR(O63/M63-1," ") -> 0.11712572 | Q63: =IFERROR(O63/N63-1," ") -> 0.025259359
B64: 4 - CUSTO MERCADORIA VENDIDA | F64: =IFERROR(E64/C64-1," ") | G64: =IFERROR(E64/D64-1," ") | H64: ='Quadro DRE Apresentação'!H8+'Quadro DRE Apresentação'!H70+'Quadro DRE Apresentação'!H92 -> -75.10715 | I64: ='Quadro DRE Apresentação'!I8+'Quadro DRE Apresentação'!I70+'Quadro DRE Apresentação'!I92 -> 0 | K64: =IFERROR(J64/H64-1," ") -> -1 | L64: =IFERROR(J64/I64-1," ") | M64: ='Quadro DRE Apresentação'!M8+'Quadro DRE Apresentação'!M70+'Quadro DRE Apresentação'!M92 -> -75 | N64: ='Quadro DRE Apresentação'!N8+'Quadro DRE Apresentação'!N70+'Quadro DRE Apresentação'!N92 -> 0 | P64: =IFERROR(O64/M64-1," ") -> -1 | Q64: =IFERROR(O64/N64-1," ")
B65: 5 - LUCRO BRUTO | C65: =C47+'Quadro DRE Apresentação'!C9 -> 5633.2717 | D65: =D47+'Quadro DRE Apresentação'!D9 -> 5952.9717 | E65: ='Quadro DRE Apresentação'!E9+'Quadro DRE Apresentação'!E71+'Quadro DRE Apresentação'!E93 -> 6382.3084 | F65: =IFERROR(E65/C65-1," ") -> 0.13296654 | G65: =IFERROR(E65/D65-1," ") -> 0.072121412 | H65: ='Quadro DRE Apresentação'!H9+'Quadro DRE Apresentação'!H71+'Quadro DRE Apresentação'!H93-1 -> #REF! | I65: ='Quadro DRE Apresentação'!I9+'Quadro DRE Apresentação'!I71+'Quadro DRE Apresentação'!I93+1 -> #REF! | J65: ='Quadro DRE Apresentação'!J9+'Quadro DRE Apresentação'!J71+'Quadro DRE Apresentação'!J93 -> #REF! | K65: =IFERROR(J65/H65-1," ") | L65: =IFERROR(J65/I65-1," ") | M65: ='Quadro DRE Apresentação'!M9+'Quadro DRE Apresentação'!M71+'Quadro DRE Apresentação'!M93 -> 64660.208 | N65: ='Quadro DRE Apresentação'!N9+'Quadro DRE Apresentação'!N71+'Quadro DRE Apresentação'!N93 -> 70535.68 | O65: ='Quadro DRE Apresentação'!O71+'Quadro DRE Apresentação'!O9+'Quadro DRE Apresentação'!O93 -> 72317.366 | P65: =IFERROR(O65/M65-1," ") -> 0.11842148 | Q65: =IFERROR(O65/N65-1," ") -> 0.025259359
B66: 6 - DESPESAS OPERACIONAIS | C66: =C48+'Quadro DRE Apresentação'!C10 -> -1406.7739 | D66: =D48+'Quadro DRE Apresentação'!D10 -> -1286.5396 | E66: ='Quadro DRE Apresentação'!E10+'Quadro DRE Apresentação'!E72+'Quadro DRE Apresentação'!E94 -> -1147.2842 | F66: =IFERROR(E66/C66-1," ") -> -0.18445731 | G66: =IFERROR(E66/D66-1," ") -> -0.10824032 | H66: ='Quadro DRE Apresentação'!H10+'Quadro DRE Apresentação'!H72+'Quadro DRE Apresentação'!H94 -> #REF! | I66: ='Quadro DRE Apresentação'!I10+'Quadro DRE Apresentação'!I72+'Quadro DRE Apresentação'!I94-1 -> #REF! | J66: ='Quadro DRE Apresentação'!J10+'Quadro DRE Apresentação'!J72+'Quadro DRE Apresentação'!J94 -> #REF! | K66: =IFERROR(J66/H66-1," ") | L66: =IFERROR(J66/I66-1," ") | M66: ='Quadro DRE Apresentação'!M10+'Quadro DRE Apresentação'!M72+'Quadro DRE Apresentação'!M94 -> -14523.948 | N66: ='Quadro DRE Apresentação'!N10+'Quadro DRE Apresentação'!N72+'Quadro DRE Apresentação'!N94 -> -14620.75 | O66: =('Quadro DRE Apresentação'!O72+'Quadro DRE Apresentação'!O10+'Quadro DRE Apresentação'!O94) -> -14654.45 | P66: =IFERROR(O66/M66-1," ") -> 0.0089852503 | Q66: =IFERROR(O66/N66-1," ") -> 0.0023049187
B67: 7 - EBITDA | C67: =C49+'Quadro DRE Apresentação'!C11 -> 4226.4978 | D67: =D49+'Quadro DRE Apresentação'!D11 -> 4666.432 | E67: ='Quadro DRE Apresentação'!E11+'Quadro DRE Apresentação'!E73+'Quadro DRE Apresentação'!E95 -> 5235.0242 | F67: =IFERROR(E67/C67-1," ") -> 0.23861987 | G67: =IFERROR(E67/D67-1," ") -> 0.12184731 | H67: ='Quadro DRE Apresentação'!H11+'Quadro DRE Apresentação'!H73+'Quadro DRE Apresentação'!H95+1 -> #REF! | I67: ='Quadro DRE Apresentação'!I11+'Quadro DRE Apresentação'!I73+'Quadro DRE Apresentação'!I95 -> #REF! | J67: =('Quadro DRE Apresentação'!J11+'Quadro DRE Apresentação'!J73+'Quadro DRE Apresentação'!J95)+1 -> #REF! | K67: =IFERROR(J67/H67-1," ") | L67: =IFERROR(J67/I67-1," ") | M67: ='Quadro DRE Apresentação'!M11+'Quadro DRE Apresentação'!M73+'Quadro DRE Apresentação'!M95 -> 50136.26 | N67: =('Quadro DRE Apresentação'!N11+'Quadro DRE Apresentação'!N73+'Quadro DRE Apresentação'!N95) -> 55914.93 | O67: =(('Quadro DRE Apresentação'!O73+'Quadro DRE Apresentação'!O11+'Quadro DRE Apresentação'!O95)) -> 57662.917 | P67: =IFERROR(O67/M67-1," ") -> 0.15012401 | Q67: =IFERROR(O67/N67-1," ") -> 0.031261532
B68: 8 - DEPRECIAÇÃO | C68: =C50+'Quadro DRE Apresentação'!C12 -> -461.01789 | D68: =D50+'Quadro DRE Apresentação'!D12 -> -514.39474 | E68: ='Quadro DRE Apresentação'!E12+'Quadro DRE Apresentação'!E74+'Quadro DRE Apresentação'!E96 -> -479.93867 | F68: =IFERROR(E68/C68-1," ") -> 0.041041314 | G68: =IFERROR(E68/D68-1," ") -> -0.066983714 | H68: ='Quadro DRE Apresentação'!H12+'Quadro DRE Apresentação'!H74+'Quadro DRE Apresentação'!H96 -> #REF! | I68: ='Quadro DRE Apresentação'!I12+'Quadro DRE Apresentação'!I74+'Quadro DRE Apresentação'!I96-1 -> #REF! | J68: ='Quadro DRE Apresentação'!J12+'Quadro DRE Apresentação'!J74+'Quadro DRE Apresentação'!J96 -> #REF! | K68: =IFERROR(J68/H68-1," ") | L68: =IFERROR(J68/I68-1," ") | M68: ='Quadro DRE Apresentação'!M12+'Quadro DRE Apresentação'!M74+'Quadro DRE Apresentação'!M96 -> -4730.5682 | N68: ='Quadro DRE Apresentação'!N12+'Quadro DRE Apresentação'!N74+'Quadro DRE Apresentação'!N96 -> -6215.0128 | O68: ='Quadro DRE Apresentação'!O74+'Quadro DRE Apresentação'!O12+'Quadro DRE Apresentação'!O96 -> -5934.9309 | P68: =IFERROR(O68/M68-1," ") -> 0.25459156 | Q68: =IFERROR(O68/N68-1," ") -> -0.045065379
B69: 9 - RESULTADO OPERACIONAL | C69: =C51+'Quadro DRE Apresentação'!C13 -> 3765.48 | D69: =D51+'Quadro DRE Apresentação'!D13 -> 4152.0373 | E69: ='Quadro DRE Apresentação'!E13+'Quadro DRE Apresentação'!E75+'Quadro DRE Apresentação'!E97 -> 4755.0855 | F69: =IFERROR(E69/C69-1," ") -> 0.26280995 | G69: =IFERROR(E69/D69-1," ") -> 0.14524153 | H69: ='Quadro DRE Apresentação'!H13+'Quadro DRE Apresentação'!H75+'Quadro DRE Apresentação'!H97 -> #REF! | I69: ='Quadro DRE Apresentação'!I13+'Quadro DRE Apresentação'!I75+'Quadro DRE Apresentação'!I97-1 -> #REF! | J69: ='Quadro DRE Apresentação'!J13+'Quadro DRE Apresentação'!J75+'Quadro DRE Apresentação'!J97 -> #REF! | K69: =IFERROR(J69/H69-1," ") | L69: =IFERROR(J69/I69-1," ") | M69: ='Quadro DRE Apresentação'!M13+'Quadro DRE Apresentação'!M75+'Quadro DRE Apresentação'!M97 -> 45405.692 | N69: ='Quadro DRE Apresentação'!N13+'Quadro DRE Apresentação'!N75+'Quadro DRE Apresentação'!N97 -> 49699.917 | O69: ='Quadro DRE Apresentação'!O75+'Quadro DRE Apresentação'!O13+'Quadro DRE Apresentação'!O97 -> 51727.986 | P69: =IFERROR(O69/M69-1," ") -> 0.13924011 | Q69: =IFERROR(O69/N69-1," ") -> 0.040806271
B70: 10 - RESULTADO NÃO OPERACIONAL | C70: =C52+'Quadro DRE Apresentação'!C14 -> 249.45014 | D70: =D52+'Quadro DRE Apresentação'!D14 -> 37.49481 | E70: ='Quadro DRE Apresentação'!E14+'Quadro DRE Apresentação'!E76+'Quadro DRE Apresentação'!E98 -> 147.66521 | F70: =IFERROR(E70/C70-1," ") -> -0.40803717 | G70: =IFERROR(E70/D70-1," ") -> 2.938284 | H70: ='Quadro DRE Apresentação'!H14+'Quadro DRE Apresentação'!H76+'Quadro DRE Apresentação'!H98 -> #REF! | I70: ='Quadro DRE Apresentação'!I14+'Quadro DRE Apresentação'!I76+'Quadro DRE Apresentação'!I98 -> #REF! | J70: ='Quadro DRE Apresentação'!J14+'Quadro DRE Apresentação'!J76+'Quadro DRE Apresentação'!J98 -> #REF! | K70: =IFERROR(J70/H70-1," ") | L70: =IFERROR(J70/I70-1," ") | M70: ='Quadro DRE Apresentação'!M14+'Quadro DRE Apresentação'!M76+'Quadro DRE Apresentação'!M98 -> 2559.8508 | N70: ='Quadro DRE Apresentação'!N14+'Quadro DRE Apresentação'!N76+'Quadro DRE Apresentação'!N98 -> 487.58471 | O70: ='Quadro DRE Apresentação'!O76+'Quadro DRE Apresentação'!O14+'Quadro DRE Apresentação'!O98 -> 851.67545 | P70: =IFERROR(O70/M70-1," ") -> -0.66729489 | Q70: =IFERROR(O70/N70-1," ") -> 0.74672305
B71: 11 - LUCRO ANTES DO IR/CSLL | C71: =C53+'Quadro DRE Apresentação'!C17 -> 4014.9301 | D71: =D53+'Quadro DRE Apresentação'!D17 -> 4189.5321 | E71: ='Quadro DRE Apresentação'!E17+'Quadro DRE Apresentação'!E77+'Quadro DRE Apresentação'!E101 -> 4902.7508 | F71: =IFERROR(E71/C71-1," ") -> 0.22112979 | G71: =IFERROR(E71/D71-1," ") -> 0.17023826 | H71: ='Quadro DRE Apresentação'!H17+'Quadro DRE Apresentação'!H77+'Quadro DRE Apresentação'!H101 -> #REF! | I71: ='Quadro DRE Apresentação'!I17+'Quadro DRE Apresentação'!I77+'Quadro DRE Apresentação'!I101-1 -> #REF! | J71: ='Quadro DRE Apresentação'!J17+'Quadro DRE Apresentação'!J77+'Quadro DRE Apresentação'!J101 -> #REF! | K71: =IFERROR(J71/H71-1," ") | L71: =IFERROR(J71/I71-1," ") | M71: ='Quadro DRE Apresentação'!M17+'Quadro DRE Apresentação'!M77+'Quadro DRE Apresentação'!M101 -> 47965.543 | N71: ='Quadro DRE Apresentação'!N17+'Quadro DRE Apresentação'!N77+'Quadro DRE Apresentação'!N101 -> 50187.502 | O71: ='Quadro DRE Apresentação'!O77+'Quadro DRE Apresentação'!O17+'Quadro DRE Apresentação'!O101 -> 52579.661 | P71: =IFERROR(O71/M71-1," ") -> 0.09619652 | Q71: =IFERROR(O71/N71-1," ") -> 0.047664437
B72: 12 - IR/CSLL | C72: =C54+'Quadro DRE Apresentação'!C18 -> -702.98101 | D72: =D54+'Quadro DRE Apresentação'!D18 -> -738.12773 | E72: ='Quadro DRE Apresentação'!E18+'Quadro DRE Apresentação'!E78+'Quadro DRE Apresentação'!E102 -> -821.31516 | F72: =IFERROR(E72/C72-1," ") -> 0.16833193 | G72: =IFERROR(E72/D72-1," ") -> 0.11270059 | H72: ='Quadro DRE Apresentação'!H18+'Quadro DRE Apresentação'!H78+'Quadro DRE Apresentação'!H102-1 -> -4647.6373 | I72: ='Quadro DRE Apresentação'!I18+'Quadro DRE Apresentação'!I78+'Quadro DRE Apresentação'!I102+1 -> #REF! | J72: ='Quadro DRE Apresentação'!J18+'Quadro DRE Apresentação'!J78+'Quadro DRE Apresentação'!J102 -> #REF! | K72: =IFERROR(J72/H72-1," ") | L72: =IFERROR(J72/I72-1," ") | M72: ='Quadro DRE Apresentação'!M18+'Quadro DRE Apresentação'!M78+'Quadro DRE Apresentação'!M102 -> -7969.7165 | N72: ='Quadro DRE Apresentação'!N18+'Quadro DRE Apresentação'!N78+'Quadro DRE Apresentação'!N102 -> -8651.834 | O72: ='Quadro DRE Apresentação'!O78+'Quadro DRE Apresentação'!O18+'Quadro DRE Apresentação'!O102 -> -8980.4828 | P72: =IFERROR(O72/M72-1," ") -> 0.12682587 | Q72: =IFERROR(O72/N72-1," ") -> 0.037986019
B73: 13 - LUCRO LIQUIDO | C73: =C55+'Quadro DRE Apresentação'!C19 -> 3311.9491 | D73: =D55+'Quadro DRE Apresentação'!D19 -> 3451.4044 | E73: ='Quadro DRE Apresentação'!E19+'Quadro DRE Apresentação'!E79+'Quadro DRE Apresentação'!E103 -> 4081.4356 | F73: =IFERROR(E73/C73-1," ") -> 0.23233645 | G73: =IFERROR(E73/D73-1," ") -> 0.18254344 | H73: ='Quadro DRE Apresentação'!H19+'Quadro DRE Apresentação'!H79+'Quadro DRE Apresentação'!H103-1 -> #REF! | I73: ='Quadro DRE Apresentação'!I19+'Quadro DRE Apresentação'!I79+'Quadro DRE Apresentação'!I103 -> #REF! | J73: ='Quadro DRE Apresentação'!J19+'Quadro DRE Apresentação'!J79+'Quadro DRE Apresentação'!J103 -> #REF! | K73: =IFERROR(J73/H73-1," ") | L73: =IFERROR(J73/I73-1," ") | M73: ='Quadro DRE Apresentação'!M19+'Quadro DRE Apresentação'!M79+'Quadro DRE Apresentação'!M103 -> 39995.826 | N73: ='Quadro DRE Apresentação'!N19+'Quadro DRE Apresentação'!N79+'Quadro DRE Apresentação'!N103 -> 41535.668 | O73: ='Quadro DRE Apresentação'!O79+'Quadro DRE Apresentação'!O19+'Quadro DRE Apresentação'!O103 -> 43599.178 | P73: =IFERROR(O73/M73-1," ") -> 0.090093202 | Q73: =IFERROR(O73/N73-1," ") -> 0.049680441
B75: Margem EBITDA/ROL | C75: =IFERROR(C67/C63,0) -> 0.7502741 | D75: =D67/D63 -> 0.78388279 | E75: =E67/E63 -> 0.82023994 | H75: =IFERROR(H67/H63,0) -> 0 | I75: =I67/I63 -> #REF! | J75: =J67/J63 -> #REF! | M75: =IFERROR(M67/M63,0) -> 0.7744821 | N75: =N67/N63 -> 0.79271838 | O75: =O67/O63 -> 0.79735919
B77: Margem CMV/ROL | C77: =C64/C63 -> 0 | D77: =D64/D63 -> 0 | E77: =E64/E63 -> 0 | H77: =IFERROR(SUM('Quadro DRE Ritmo'!N80,'Quadro DRE Ritmo'!N100)/SUM('Quadro DRE Ritmo'!N99,'Quadro DRE Ritmo'!N79),0) -> 0 | I77: =IFERROR(SUM('Quadro DRE Ritmo'!P80,'Quadro DRE Ritmo'!P100)/SUM('Quadro DRE Ritmo'!P99,'Quadro DRE Ritmo'!P79),0) -> 0 | J77: =IFERROR(SUM('Quadro DRE Ritmo'!R80,'Quadro DRE Ritmo'!R100)/SUM('Quadro DRE Ritmo'!R99,'Quadro DRE Ritmo'!R79),0) -> 0 | M77: =IFERROR(SUM('Quadro DRE Ritmo'!X80,'Quadro DRE Ritmo'!X100)/SUM('Quadro DRE Ritmo'!X99,'Quadro DRE Ritmo'!X79),0) -> 0 | N77: =IFERROR(SUM('Quadro DRE Ritmo'!Z80,'Quadro DRE Ritmo'!Z100)/SUM('Quadro DRE Ritmo'!Z99,'Quadro DRE Ritmo'!Z79),0) -> 0 | O77: =IFERROR(SUM('Quadro DRE Ritmo'!AB80,'Quadro DRE Ritmo'!AB100)/SUM('Quadro DRE Ritmo'!AB99,'Quadro DRE Ritmo'!AB79),0) -> 0
B80: DRE CONSOLIDADO | C80: JANEIRO | H80: ACUMULADO JAN A FEV | M80: RITMO
C81: Real 2019 | D81: Orç 2020 | E81: Real 2020 | F81: ∆ Real 2020 x Real 2019 | G81: ∆ Real 2020 x Orc 2020 | H81: Real 2019 | I81: Orç 2020 | J81: Real 2020 | K81: ∆ Real 2020 x Real 2019 | L81: ∆ Real 2020 x Orc 2020 | M81: Real 2019 | N81: Orç 2020 | O81: Ritmo 2020 | P81: ∆ Ritmo 2020 x Real 2019 | Q81: ∆ Ritmo 2020 x Orc 2020
B82: 1 - FATURAMENTO BRUTO | C82: ='Quadro DRE Apresentação'!C131+'Quadro DRE Apresentação'!C109+'Quadro DRE Apresentação'!C89+'Quadro DRE Apresentação'!C67+'Quadro DRE Apresentação'!C25+'Quadro DRE Apresentação'!C5 -> 8466.106 | D82: ='Quadro DRE Apresentação'!D5+'Quadro DRE Apresentação'!D25+'Quadro DRE Apresentação'!D67+'Quadro DRE Apresentação'!D89+'Quadro DRE Apresentação'!D109+'Quadro DRE Apresentação'!D131 -> 9338.6846 | E82: ='Quadro DRE Apresentação'!E5+'Quadro DRE Apresentação'!E25+'Quadro DRE Apresentação'!E67+'Quadro DRE Apresentação'!E89+'Quadro DRE Apresentação'!E109+'Quadro DRE Apresentação'!E131 -> 9831.2234 | F82: =IFERROR(E82/C82-1," ") -> 0.16124502 | G82: =IFERROR(E82/D82-1," ") -> 0.052741778 | H82: ='Quadro DRE Apresentação'!H131+'Quadro DRE Apresentação'!H109+'Quadro DRE Apresentação'!H89+'Quadro DRE Apresentação'!H67+'Quadro DRE Apresentação'!H25+'Quadro DRE Apresentação'!H5 -> #REF! | I82: ='Quadro DRE Apresentação'!I131+'Quadro DRE Apresentação'!I109+'Quadro DRE Apresentação'!I89+'Quadro DRE Apresentação'!I67+'Quadro DRE Apresentação'!I25+'Quadro DRE Apresentação'!I5 -> #REF! | J82: ='Quadro DRE Apresentação'!J5+'Quadro DRE Apresentação'!J25+'Quadro DRE Apresentação'!J67+'Quadro DRE Apresentação'!J89+'Quadro DRE Apresentação'!J109+'Quadro DRE Apresentação'!J131 -> #REF! | K82: =IFERROR(J82/H82-1," ") | L82: =IFERROR(J82/I82-1," ") | M82: ='Quadro DRE Apresentação'!M131+'Quadro DRE Apresentação'!M109+'Quadro DRE Apresentação'!M89+'Quadro DRE Apresentação'!M67+'Quadro DRE Apresentação'!M25+'Quadro DRE Apresentação'!M5 -> 103265.35 | N82: ='Quadro DRE Apresentação'!N131+'Quadro DRE Apresentação'!N109+'Quadro DRE Apresentação'!N89+'Quadro DRE Apresentação'!N67+'Quadro DRE Apresentação'!N25+'Quadro DRE Apresentação'!N5 -> 110676.84 | O82: ='Quadro DRE Apresentação'!O131+'Quadro DRE Apresentação'!O109+'Quadro DRE Apresentação'!O89+'Quadro DRE Apresentação'!O67+'Quadro DRE Apresentação'!O25+'Quadro DRE Apresentação'!O5 -> 113213.34 | P82: =IFERROR(O82/M82-1," ") -> 0.096334282 | Q82: =IFERROR(O82/N82-1," ") -> 0.022918106
B83: 2 - DEDUÇÃO DE FATURAMENTO | C83: ='Quadro DRE Apresentação'!C132+'Quadro DRE Apresentação'!C110+'Quadro DRE Apresentação'!C90+'Quadro DRE Apresentação'!C68+'Quadro DRE Apresentação'!C26+'Quadro DRE Apresentação'!C6 -> -362.18919 | D83: ='Quadro DRE Apresentação'!D6+'Quadro DRE Apresentação'!D26+'Quadro DRE Apresentação'!D68+'Quadro DRE Apresentação'!D90+'Quadro DRE Apresentação'!D110+'Quadro DRE Apresentação'!D132 -> -396.02291 | E83: ='Quadro DRE Apresentação'!E6+'Quadro DRE Apresentação'!E26+'Quadro DRE Apresentação'!E68+'Quadro DRE Apresentação'!E90+'Quadro DRE Apresentação'!E110+'Quadro DRE Apresentação'!E132 -> -418.67836 | F83: =IFERROR(E83/C83-1," ") -> 0.15596592 | G83: =IFERROR(E83/D83-1," ") -> 0.057207423 | H83: ='Quadro DRE Apresentação'!H132+'Quadro DRE Apresentação'!H110+'Quadro DRE Apresentação'!H90+'Quadro DRE Apresentação'!H68+'Quadro DRE Apresentação'!H26+'Quadro DRE Apresentação'!H6 -> #REF! | I83: ='Quadro DRE Apresentação'!I132+'Quadro DRE Apresentação'!I110+'Quadro DRE Apresentação'!I90+'Quadro DRE Apresentação'!I68+'Quadro DRE Apresentação'!I26+'Quadro DRE Apresentação'!I6 -> #REF! | J83: ='Quadro DRE Apresentação'!J6+'Quadro DRE Apresentação'!J26+'Quadro DRE Apresentação'!J68+'Quadro DRE Apresentação'!J90+'Quadro DRE Apresentação'!J110+'Quadro DRE Apresentação'!J132 -> #REF! | K83: =IFERROR(J83/H83-1," ") | L83: =IFERROR(J83/I83-1," ") | M83: ='Quadro DRE Apresentação'!M132+'Quadro DRE Apresentação'!M110+'Quadro DRE Apresentação'!M90+'Quadro DRE Apresentação'!M68+'Quadro DRE Apresentação'!M26+'Quadro DRE Apresentação'!M6 -> -4389.4692 | N83: ='Quadro DRE Apresentação'!N132+'Quadro DRE Apresentação'!N110+'Quadro DRE Apresentação'!N90+'Quadro DRE Apresentação'!N68+'Quadro DRE Apresentação'!N26+'Quadro DRE Apresentação'!N6 -> -4621.0863 | O83: ='Quadro DRE Apresentação'!O132+'Quadro DRE Apresentação'!O110+'Quadro DRE Apresentação'!O90+'Quadro DRE Apresentação'!O68+'Quadro DRE Apresentação'!O26+'Quadro DRE Apresentação'!O6 -> -4777.083 | P83: =IFERROR(O83/M83-1," ") -> 0.088305407 | Q83: =IFERROR(O83/N83-1," ") -> 0.033757582
B84: 3 - FATURAMENTO LIQUIDO | C84: ='Quadro DRE Apresentação'!C133+'Quadro DRE Apresentação'!C111+'Quadro DRE Apresentação'!C91+'Quadro DRE Apresentação'!C69+'Quadro DRE Apresentação'!C27+'Quadro DRE Apresentação'!C7 -> 8103.9168 | D84: ='Quadro DRE Apresentação'!D7+'Quadro DRE Apresentação'!D27+'Quadro DRE Apresentação'!D69+'Quadro DRE Apresentação'!D91+'Quadro DRE Apresentação'!D111+'Quadro DRE Apresentação'!D133 -> 8942.6617 | E84: ='Quadro DRE Apresentação'!E7+'Quadro DRE Apresentação'!E27+'Quadro DRE Apresentação'!E69+'Quadro DRE Apresentação'!E91+'Quadro DRE Apresentação'!E111+'Quadro DRE Apresentação'!E133 -> 9412.5451 | F84: =IFERROR(E84/C84-1," ") -> 0.16148096 | G84: =IFERROR(E84/D84-1," ") -> 0.052544018 | H84: ='Quadro DRE Apresentação'!H133+'Quadro DRE Apresentação'!H111+'Quadro DRE Apresentação'!H91+'Quadro DRE Apresentação'!H69+'Quadro DRE Apresentação'!H27+'Quadro DRE Apresentação'!H7 -> #REF! | I84: ='Quadro DRE Apresentação'!I133+'Quadro DRE Apresentação'!I111+'Quadro DRE Apresentação'!I91+'Quadro DRE Apresentação'!I69+'Quadro DRE Apresentação'!I27+'Quadro DRE Apresentação'!I7 -> #REF! | J84: ='Quadro DRE Apresentação'!J7+'Quadro DRE Apresentação'!J27+'Quadro DRE Apresentação'!J69+'Quadro DRE Apresentação'!J91+'Quadro DRE Apresentação'!J111+'Quadro DRE Apresentação'!J133 -> #REF! | K84: =IFERROR(J84/H84-1," ") | L84: =IFERROR(J84/I84-1," ") | M84: ='Quadro DRE Apresentação'!M133+'Quadro DRE Apresentação'!M111+'Quadro DRE Apresentação'!M91+'Quadro DRE Apresentação'!M69+'Quadro DRE Apresentação'!M27+'Quadro DRE Apresentação'!M7 -> 98875.882 | N84: ='Quadro DRE Apresentação'!N133+'Quadro DRE Apresentação'!N111+'Quadro DRE Apresentação'!N91+'Quadro DRE Apresentação'!N69+'Quadro DRE Apresentação'!N27+'Quadro DRE Apresentação'!N7 -> 106056.75 | O84: ='Quadro DRE Apresentação'!O133+'Quadro DRE Apresentação'!O111+'Quadro DRE Apresentação'!O91+'Quadro DRE Apresentação'!O69+'Quadro DRE Apresentação'!O27+'Quadro DRE Apresentação'!O7 -> 108436.26 | P84: =IFERROR(O84/M84-1," ") -> 0.096690713 | Q84: =IFERROR(O84/N84-1," ") -> 0.022436165
B85: 4 - CUSTO MERCADORIA VENDIDA | C85: ='Quadro DRE Apresentação'!C134+'Quadro DRE Apresentação'!C112+'Quadro DRE Apresentação'!C92+'Quadro DRE Apresentação'!C70+'Quadro DRE Apresentação'!C28+'Quadro DRE Apresentação'!C8 -> 0 | D85: ='Quadro DRE Apresentação'!D8+'Quadro DRE Apresentação'!D28+'Quadro DRE Apresentação'!D70+'Quadro DRE Apresentação'!D92+'Quadro DRE Apresentação'!D112+'Quadro DRE Apresentação'!D134 -> 0 | E85: ='Quadro DRE Apresentação'!E8+'Quadro DRE Apresentação'!E28+'Quadro DRE Apresentação'!E70+'Quadro DRE Apresentação'!E92+'Quadro DRE Apresentação'!E112+'Quadro DRE Apresentação'!E134 -> 0 | F85: =IFERROR(E85/C85-1," ") | G85: =IFERROR(E85/D85-1," ") | H85: ='Quadro DRE Apresentação'!H134+'Quadro DRE Apresentação'!H112+'Quadro DRE Apresentação'!H92+'Quadro DRE Apresentação'!H70+'Quadro DRE Apresentação'!H28+'Quadro DRE Apresentação'!H8 -> -4168.4087 | I85: ='Quadro DRE Apresentação'!I134+'Quadro DRE Apresentação'!I112+'Quadro DRE Apresentação'!I92+'Quadro DRE Apresentação'!I70+'Quadro DRE Apresentação'!I28+'Quadro DRE Apresentação'!I8 -> 0 | J85: ='Quadro DRE Apresentação'!J8+'Quadro DRE Apresentação'!J28+'Quadro DRE Apresentação'!J70+'Quadro DRE Apresentação'!J92+'Quadro DRE Apresentação'!J112+'Quadro DRE Apresentação'!J134 -> 0 | K85: =IFERROR(J85/H85-1," ") -> -1 | L85: =IFERROR(J85/I85-1," ") | M85: ='Quadro DRE Apresentação'!M134+'Quadro DRE Apresentação'!M112+'Quadro DRE Apresentação'!M92+'Quadro DRE Apresentação'!M70+'Quadro DRE Apresentação'!M28+'Quadro DRE Apresentação'!M8 -> -4168.31 | N85: ='Quadro DRE Apresentação'!N134+'Quadro DRE Apresentação'!N112+'Quadro DRE Apresentação'!N92+'Quadro DRE Apresentação'!N70+'Quadro DRE Apresentação'!N28+'Quadro DRE Apresentação'!N8 -> 0 | O85: ='Quadro DRE Apresentação'!O134+'Quadro DRE Apresentação'!O112+'Quadro DRE Apresentação'!O92+'Quadro DRE Apresentação'!O70+'Quadro DRE Apresentação'!O28+'Quadro DRE Apresentação'!O8 -> 0 | P85: =IFERROR(O85/M85-1," ") -> -1 | Q85: =IFERROR(O85/N85-1," ")
B86: 5 - LUCRO BRUTO | C86: ='Quadro DRE Apresentação'!C135+'Quadro DRE Apresentação'!C113+'Quadro DRE Apresentação'!C93+'Quadro DRE Apresentação'!C71+'Quadro DRE Apresentação'!C29+'Quadro DRE Apresentação'!C9 -> 8103.9168 | D86: ='Quadro DRE Apresentação'!D9+'Quadro DRE Apresentação'!D29+'Quadro DRE Apresentação'!D71+'Quadro DRE Apresentação'!D93+'Quadro DRE Apresentação'!D113+'Quadro DRE Apresentação'!D135 -> 8942.6617 | E86: ='Quadro DRE Apresentação'!E9+'Quadro DRE Apresentação'!E29+'Quadro DRE Apresentação'!E71+'Quadro DRE Apresentação'!E93+'Quadro DRE Apresentação'!E113+'Quadro DRE Apresentação'!E135 -> 9412.5451 | F86: =IFERROR(E86/C86-1," ") -> 0.16148096 | G86: =IFERROR(E86/D86-1," ") -> 0.052544018 | H86: ='Quadro DRE Apresentação'!H135+'Quadro DRE Apresentação'!H113+'Quadro DRE Apresentação'!H93+'Quadro DRE Apresentação'!H71+'Quadro DRE Apresentação'!H29+'Quadro DRE Apresentação'!H9 -> #REF! | I86: ='Quadro DRE Apresentação'!I135+'Quadro DRE Apresentação'!I113+'Quadro DRE Apresentação'!I93+'Quadro DRE Apresentação'!I71+'Quadro DRE Apresentação'!I29+'Quadro DRE Apresentação'!I9 -> #REF! | J86: ='Quadro DRE Apresentação'!J9+'Quadro DRE Apresentação'!J29+'Quadro DRE Apresentação'!J71+'Quadro DRE Apresentação'!J93+'Quadro DRE Apresentação'!J113+'Quadro DRE Apresentação'!J135 -> #REF! | K86: =IFERROR(J86/H86-1," ") | L86: =IFERROR(J86/I86-1," ") | M86: ='Quadro DRE Apresentação'!M135+'Quadro DRE Apresentação'!M113+'Quadro DRE Apresentação'!M93+'Quadro DRE Apresentação'!M71+'Quadro DRE Apresentação'!M29+'Quadro DRE Apresentação'!M9 -> 94707.572 | N86: ='Quadro DRE Apresentação'!N135+'Quadro DRE Apresentação'!N113+'Quadro DRE Apresentação'!N93+'Quadro DRE Apresentação'!N71+'Quadro DRE Apresentação'!N29+'Quadro DRE Apresentação'!N9 -> 106056.75 | O86: ='Quadro DRE Apresentação'!O135+'Quadro DRE Apresentação'!O113+'Quadro DRE Apresentação'!O93+'Quadro DRE Apresentação'!O71+'Quadro DRE Apresentação'!O29+'Quadro DRE Apresentação'!O9 -> 108436.26 | P86: =IFERROR(O86/M86-1," ") -> 0.14495873 | Q86: =IFERROR(O86/N86-1," ") -> 0.022436165
B87: 6 - DESPESAS OPERACIONAIS | C87: ='Quadro DRE Apresentação'!C136+'Quadro DRE Apresentação'!C114+'Quadro DRE Apresentação'!C94+'Quadro DRE Apresentação'!C72+'Quadro DRE Apresentação'!C30+'Quadro DRE Apresentação'!C10 -> -1990.2762 | D87: ='Quadro DRE Apresentação'!D10+'Quadro DRE Apresentação'!D30+'Quadro DRE Apresentação'!D72+'Quadro DRE Apresentação'!D94+'Quadro DRE Apresentação'!D114+'Quadro DRE Apresentação'!D136 -> -1964.7542 | E87: ='Quadro DRE Apresentação'!E10+'Quadro DRE Apresentação'!E30+'Quadro DRE Apresentação'!E72+'Quadro DRE Apresentação'!E94+'Quadro DRE Apresentação'!E114+'Quadro DRE Apresentação'!E136 -> -2005.8484 | F87: =IFERROR(E87/C87-1," ") -> 0.0078241552 | G87: =IFERROR(E87/D87-1," ") -> 0.0209157 | H87: ='Quadro DRE Apresentação'!H136+'Quadro DRE Apresentação'!H114+'Quadro DRE Apresentação'!H94+'Quadro DRE Apresentação'!H72+'Quadro DRE Apresentação'!H30+'Quadro DRE Apresentação'!H10 -> #REF! | I87: ='Quadro DRE Apresentação'!I136+'Quadro DRE Apresentação'!I114+'Quadro DRE Apresentação'!I94+'Quadro DRE Apresentação'!I72+'Quadro DRE Apresentação'!I30+'Quadro DRE Apresentação'!I10 -> #REF! | J87: ='Quadro DRE Apresentação'!J10+'Quadro DRE Apresentação'!J30+'Quadro DRE Apresentação'!J72+'Quadro DRE Apresentação'!J94+'Quadro DRE Apresentação'!J114+'Quadro DRE Apresentação'!J136 -> #REF! | K87: =IFERROR(J87/H87-1," ") | L87: =IFERROR(J87/I87-1," ") | M87: ='Quadro DRE Apresentação'!M136+'Quadro DRE Apresentação'!M114+'Quadro DRE Apresentação'!M94+'Quadro DRE Apresentação'!M72+'Quadro DRE Apresentação'!M30+'Quadro DRE Apresentação'!M10 -> -18639.6 | N87: ='Quadro DRE Apresentação'!N136+'Quadro DRE Apresentação'!N114+'Quadro DRE Apresentação'!N94+'Quadro DRE Apresentação'!N72+'Quadro DRE Apresentação'!N30+'Quadro DRE Apresentação'!N10 -> -21551.351 | O87: ='Quadro DRE Apresentação'!O136+'Quadro DRE Apresentação'!O114+'Quadro DRE Apresentação'!O94+'Quadro DRE Apresentação'!O72+'Quadro DRE Apresentação'!O30+'Quadro DRE Apresentação'!O10 -> -21854.698 | P87: =IFERROR(O87/M87-1," ") -> 0.17248746 | Q87: =IFERROR(O87/N87-1," ") -> 0.014075556
B88: 7 - EBITDA | C88: =('Quadro DRE Apresentação'!C137+'Quadro DRE Apresentação'!C115+'Quadro DRE Apresentação'!C95+'Quadro DRE Apresentação'!C73+'Quadro DRE Apresentação'!C31+'Quadro DRE Apresentação'!C11) -> 6113.6406 | D88: =('Quadro DRE Apresentação'!D11+'Quadro DRE Apresentação'!D31+'Quadro DRE Apresentação'!D73+'Quadro DRE Apresentação'!D95+'Quadro DRE Apresentação'!D115+'Quadro DRE Apresentação'!D137) -> 6977.9075 | E88: =('Quadro DRE Apresentação'!E11+'Quadro DRE Apresentação'!E31+'Quadro DRE Apresentação'!E73+'Quadro DRE Apresentação'!E95+'Quadro DRE Apresentação'!E115+'Quadro DRE Apresentação'!E137) -> 7406.6966 | F88: =IFERROR(E88/C88-1," ") -> 0.21150345 | G88: =IFERROR(E88/D88-1," ") -> 0.061449535 | H88: =('Quadro DRE Apresentação'!H137+'Quadro DRE Apresentação'!H115+'Quadro DRE Apresentação'!H95+'Quadro DRE Apresentação'!H73+'Quadro DRE Apresentação'!H31+'Quadro DRE Apresentação'!H11) -> #REF! | I88: =('Quadro DRE Apresentação'!I137+'Quadro DRE Apresentação'!I115+'Quadro DRE Apresentação'!I95+'Quadro DRE Apresentação'!I73+'Quadro DRE Apresentação'!I31+'Quadro DRE Apresentação'!I11) -> #REF! | J88: ='Quadro DRE Apresentação'!J11+'Quadro DRE Apresentação'!J31+'Quadro DRE Apresentação'!J73+'Quadro DRE Apresentação'!J95+'Quadro DRE Apresentação'!J115+'Quadro DRE Apresentação'!J137 -> #REF! | K88: =IFERROR(J88/H88-1," ") | L88: =IFERROR(J88/I88-1," ") | M88: ='Quadro DRE Apresentação'!M137+'Quadro DRE Apresentação'!M115+'Quadro DRE Apresentação'!M95+'Quadro DRE Apresentação'!M73+'Quadro DRE Apresentação'!M31+'Quadro DRE Apresentação'!M11 -> 76067.971 | N88: ='Quadro DRE Apresentação'!N137+'Quadro DRE Apresentação'!N115+'Quadro DRE Apresentação'!N95+'Quadro DRE Apresentação'!N73+'Quadro DRE Apresentação'!N31+'Quadro DRE Apresentação'!N11 -> 84504.404 | O88: =('Quadro DRE Apresentação'!O137+'Quadro DRE Apresentação'!O115+'Quadro DRE Apresentação'!O95+'Quadro DRE Apresentação'!O73+'Quadro DRE Apresentação'!O31+'Quadro DRE Apresentação'!O11) -> 86581.563 | P88: =IFERROR(O88/M88-1," ") -> 0.13821313 | Q88: =IFERROR(O88/N88-1," ") -> 0.02458049
B89: 8 - DEPRECIAÇÃO | C89: ='Quadro DRE Apresentação'!C139+'Quadro DRE Apresentação'!C117+'Quadro DRE Apresentação'!C96+'Quadro DRE Apresentação'!C74+'Quadro DRE Apresentação'!C32+'Quadro DRE Apresentação'!C12 -> -680.49714 | D89: ='Quadro DRE Apresentação'!D12+'Quadro DRE Apresentação'!D32+'Quadro DRE Apresentação'!D74+'Quadro DRE Apresentação'!D96+'Quadro DRE Apresentação'!D117+'Quadro DRE Apresentação'!D139 -> -728.11868 | E89: ='Quadro DRE Apresentação'!E12+'Quadro DRE Apresentação'!E32+'Quadro DRE Apresentação'!E74+'Quadro DRE Apresentação'!E96+'Quadro DRE Apresentação'!E117+'Quadro DRE Apresentação'!E139 -> -684.69949 | F89: =IFERROR(E89/C89-1," ") -> 0.0061754117 | G89: =IFERROR(E89/D89-1," ") -> -0.059632023 | H89: ='Quadro DRE Apresentação'!H139+'Quadro DRE Apresentação'!H117+'Quadro DRE Apresentação'!H96+'Quadro DRE Apresentação'!H74+'Quadro DRE Apresentação'!H32+'Quadro DRE Apresentação'!H12 -> #REF! | I89: ='Quadro DRE Apresentação'!I139+'Quadro DRE Apresentação'!I117+'Quadro DRE Apresentação'!I96+'Quadro DRE Apresentação'!I74+'Quadro DRE Apresentação'!I32+'Quadro DRE Apresentação'!I12 -> #REF! | J89: ='Quadro DRE Apresentação'!J12+'Quadro DRE Apresentação'!J32+'Quadro DRE Apresentação'!J74+'Quadro DRE Apresentação'!J96+'Quadro DRE Apresentação'!J117+'Quadro DRE Apresentação'!J139 -> #REF! | K89: =IFERROR(J89/H89-1," ") | L89: =IFERROR(J89/I89-1," ") | M89: ='Quadro DRE Apresentação'!M139+'Quadro DRE Apresentação'!M117+'Quadro DRE Apresentação'!M96+'Quadro DRE Apresentação'!M74+'Quadro DRE Apresentação'!M32+'Quadro DRE Apresentação'!M12 -> -7402.8702 | N89: ='Quadro DRE Apresentação'!N139+'Quadro DRE Apresentação'!N117+'Quadro DRE Apresentação'!N96+'Quadro DRE Apresentação'!N74+'Quadro DRE Apresentação'!N32+'Quadro DRE Apresentação'!N12 -> -8863.2821 | O89: ='Quadro DRE Apresentação'!O139+'Quadro DRE Apresentação'!O117+'Quadro DRE Apresentação'!O96+'Quadro DRE Apresentação'!O74+'Quadro DRE Apresentação'!O32+'Quadro DRE Apresentação'!O12 -> -8520.6056 | P89: =IFERROR(O89/M89-1," ") -> 0.15098675 | Q89: =IFERROR(O89/N89-1," ") -> -0.038662493
B90: 9 - RESULTADO OPERACIONAL | C90: ='Quadro DRE Apresentação'!C140+'Quadro DRE Apresentação'!C118+'Quadro DRE Apresentação'!C97+'Quadro DRE Apresentação'!C75+'Quadro DRE Apresentação'!C33+'Quadro DRE Apresentação'!C13 -> 5433.1435 | D90: ='Quadro DRE Apresentação'!D13+'Quadro DRE Apresentação'!D33+'Quadro DRE Apresentação'!D75+'Quadro DRE Apresentação'!D97+'Quadro DRE Apresentação'!D118+'Quadro DRE Apresentação'!D140 -> 6249.7888 | E90: ='Quadro DRE Apresentação'!E13+'Quadro DRE Apresentação'!E33+'Quadro DRE Apresentação'!E75+'Quadro DRE Apresentação'!E97+'Quadro DRE Apresentação'!E118+'Quadro DRE Apresentação'!E140 -> 6721.9972 | F90: =IFERROR(E90/C90-1," ") -> 0.23722063 | G90: =IFERROR(E90/D90-1," ") -> 0.075555891 | H90: ='Quadro DRE Apresentação'!H140+'Quadro DRE Apresentação'!H118+'Quadro DRE Apresentação'!H97+'Quadro DRE Apresentação'!H75+'Quadro DRE Apresentação'!H33+'Quadro DRE Apresentação'!H13 -> #REF! | I90: ='Quadro DRE Apresentação'!I140+'Quadro DRE Apresentação'!I118+'Quadro DRE Apresentação'!I97+'Quadro DRE Apresentação'!I75+'Quadro DRE Apresentação'!I33+'Quadro DRE Apresentação'!I13 -> #REF! | J90: ='Quadro DRE Apresentação'!J13+'Quadro DRE Apresentação'!J33+'Quadro DRE Apresentação'!J75+'Quadro DRE Apresentação'!J97+'Quadro DRE Apresentação'!J118+'Quadro DRE Apresentação'!J140 -> #REF! | K90: =IFERROR(J90/H90-1," ") | L90: =IFERROR(J90/I90-1," ") | M90: ='Quadro DRE Apresentação'!M140+'Quadro DRE Apresentação'!M118+'Quadro DRE Apresentação'!M97+'Quadro DRE Apresentação'!M75+'Quadro DRE Apresentação'!M33+'Quadro DRE Apresentação'!M13 -> 68665.101 | N90: ='Quadro DRE Apresentação'!N140+'Quadro DRE Apresentação'!N118+'Quadro DRE Apresentação'!N97+'Quadro DRE Apresentação'!N75+'Quadro DRE Apresentação'!N33+'Quadro DRE Apresentação'!N13 -> 75641.122 | O90: ='Quadro DRE Apresentação'!O140+'Quadro DRE Apresentação'!O118+'Quadro DRE Apresentação'!O97+'Quadro DRE Apresentação'!O75+'Quadro DRE Apresentação'!O33+'Quadro DRE Apresentação'!O13 -> 78060.958 | P90: =IFERROR(O90/M90-1," ") -> 0.13683599 | Q90: =IFERROR(O90/N90-1," ") -> 0.031991014
B91: 10 - RESULTADO NÃO OPERACIONAL | C91: ='Quadro DRE Apresentação'!C141+'Quadro DRE Apresentação'!C119+'Quadro DRE Apresentação'!C98+'Quadro DRE Apresentação'!C76+'Quadro DRE Apresentação'!C34+'Quadro DRE Apresentação'!C14 -> -271.48231 | D91: ='Quadro DRE Apresentação'!D14+'Quadro DRE Apresentação'!D34+'Quadro DRE Apresentação'!D76+'Quadro DRE Apresentação'!D98+'Quadro DRE Apresentação'!D119+'Quadro DRE Apresentação'!D141 -> -660.63987 | E91: ='Quadro DRE Apresentação'!E14+'Quadro DRE Apresentação'!E34+'Quadro DRE Apresentação'!E76+'Quadro DRE Apresentação'!E98+'Quadro DRE Apresentação'!E119+'Quadro DRE Apresentação'!E141 -> -543.60509 | F91: =IFERROR(E91/C91-1," ") -> 1.0023592 | G91: =IFERROR(E91/D91-1," ") -> -0.17715367 | H91: ='Quadro DRE Apresentação'!H141+'Quadro DRE Apresentação'!H119+'Quadro DRE Apresentação'!H98+'Quadro DRE Apresentação'!H76+'Quadro DRE Apresentação'!H34+'Quadro DRE Apresentação'!H14 -> #REF! | I91: ='Quadro DRE Apresentação'!I141+'Quadro DRE Apresentação'!I119+'Quadro DRE Apresentação'!I98+'Quadro DRE Apresentação'!I76+'Quadro DRE Apresentação'!I34+'Quadro DRE Apresentação'!I14 -> #REF! | J91: ='Quadro DRE Apresentação'!J14+'Quadro DRE Apresentação'!J34+'Quadro DRE Apresentação'!J76+'Quadro DRE Apresentação'!J98+'Quadro DRE Apresentação'!J119+'Quadro DRE Apresentação'!J141 -> #REF! | K91: =IFERROR(J91/H91-1," ") | L91: =IFERROR(J91/I91-1," ") | M91: ='Quadro DRE Apresentação'!M141+'Quadro DRE Apresentação'!M119+'Quadro DRE Apresentação'!M98+'Quadro DRE Apresentação'!M76+'Quadro DRE Apresentação'!M34+'Quadro DRE Apresentação'!M14 -> -3806.157 | N91: ='Quadro DRE Apresentação'!N141+'Quadro DRE Apresentação'!N119+'Quadro DRE Apresentação'!N98+'Quadro DRE Apresentação'!N76+'Quadro DRE Apresentação'!N34+'Quadro DRE Apresentação'!N14 -> -8016.6739 | O91: ='Quadro DRE Apresentação'!O141+'Quadro DRE Apresentação'!O119+'Quadro DRE Apresentação'!O98+'Quadro DRE Apresentação'!O76+'Quadro DRE Apresentação'!O34+'Quadro DRE Apresentação'!O14 -> -7090.2791 | P91: =IFERROR(O91/M91-1," ") -> 0.86284462 | Q91: =IFERROR(O91/N91-1," ") -> -0.11555849
B92: 11 - LUCRO ANTES DO IR/CSLL | C92: ='Quadro DRE Apresentação'!C142+'Quadro DRE Apresentação'!C120+'Quadro DRE Apresentação'!C101+'Quadro DRE Apresentação'!C77+'Quadro DRE Apresentação'!C37+'Quadro DRE Apresentação'!C17 -> 5161.6611 | D92: ='Quadro DRE Apresentação'!D17+'Quadro DRE Apresentação'!D37+'Quadro DRE Apresentação'!D77+'Quadro DRE Apresentação'!D101+'Quadro DRE Apresentação'!D120+'Quadro DRE Apresentação'!D142 -> 5589.1489 | E92: ='Quadro DRE Apresentação'!E17+'Quadro DRE Apresentação'!E37+'Quadro DRE Apresentação'!E77+'Quadro DRE Apresentação'!E101+'Quadro DRE Apresentação'!E120+'Quadro DRE Apresentação'!E142 -> 6178.3921 | F92: =IFERROR(E92/C92-1," ") -> 0.19697746 | G92: =IFERROR(E92/D92-1," ") -> 0.10542627 | H92: ='Quadro DRE Apresentação'!H142+'Quadro DRE Apresentação'!H120+'Quadro DRE Apresentação'!H101+'Quadro DRE Apresentação'!H77+'Quadro DRE Apresentação'!H37+'Quadro DRE Apresentação'!H17 -> #REF! | I92: ='Quadro DRE Apresentação'!I142+'Quadro DRE Apresentação'!I120+'Quadro DRE Apresentação'!I101+'Quadro DRE Apresentação'!I77+'Quadro DRE Apresentação'!I37+'Quadro DRE Apresentação'!I17 -> #REF! | J92: ='Quadro DRE Apresentação'!J17+'Quadro DRE Apresentação'!J37+'Quadro DRE Apresentação'!J77+'Quadro DRE Apresentação'!J101+'Quadro DRE Apresentação'!J120+'Quadro DRE Apresentação'!J142 -> #REF! | K92: =IFERROR(J92/H92-1," ") | L92: =IFERROR(J92/I92-1," ") | M92: ='Quadro DRE Apresentação'!M142+'Quadro DRE Apresentação'!M120+'Quadro DRE Apresentação'!M101+'Quadro DRE Apresentação'!M77+'Quadro DRE Apresentação'!M37+'Quadro DRE Apresentação'!M17 -> 64858.944 | N92: ='Quadro DRE Apresentação'!N142+'Quadro DRE Apresentação'!N120+'Quadro DRE Apresentação'!N101+'Quadro DRE Apresentação'!N77+'Quadro DRE Apresentação'!N37+'Quadro DRE Apresentação'!N17 -> 67624.448 | O92: ='Quadro DRE Apresentação'!O142+'Quadro DRE Apresentação'!O120+'Quadro DRE Apresentação'!O101+'Quadro DRE Apresentação'!O77+'Quadro DRE Apresentação'!O37+'Quadro DRE Apresentação'!O17 -> 70970.679 | P92: =IFERROR(O92/M92-1," ") -> 0.09423118 | Q92: =IFERROR(O92/N92-1," ") -> 0.049482562
B93: 12 - IR/CSLL | C93: ='Quadro DRE Apresentação'!C143+'Quadro DRE Apresentação'!C121+'Quadro DRE Apresentação'!C102+'Quadro DRE Apresentação'!C78+'Quadro DRE Apresentação'!C38+'Quadro DRE Apresentação'!C18 -> -1001.6532 | D93: ='Quadro DRE Apresentação'!D18+'Quadro DRE Apresentação'!D38+'Quadro DRE Apresentação'!D78+'Quadro DRE Apresentação'!D102+'Quadro DRE Apresentação'!D121+'Quadro DRE Apresentação'!D143 -> -1142.0512 | E93: ='Quadro DRE Apresentação'!E18+'Quadro DRE Apresentação'!E38+'Quadro DRE Apresentação'!E78+'Quadro DRE Apresentação'!E102+'Quadro DRE Apresentação'!E121+'Quadro DRE Apresentação'!E143 -> -1232.7934 | F93: =IFERROR(E93/C93-1," ") -> 0.23075867 | G93: =IFERROR(E93/D93-1," ") -> 0.079455522 | H93: ='Quadro DRE Apresentação'!H143+'Quadro DRE Apresentação'!H121+'Quadro DRE Apresentação'!H102+'Quadro DRE Apresentação'!H78+'Quadro DRE Apresentação'!H38+'Quadro DRE Apresentação'!H18 -> -6760.2107 | I93: ='Quadro DRE Apresentação'!I143+'Quadro DRE Apresentação'!I121+'Quadro DRE Apresentação'!I102+'Quadro DRE Apresentação'!I78+'Quadro DRE Apresentação'!I38+'Quadro DRE Apresentação'!I18 -> #REF! | J93: ='Quadro DRE Apresentação'!J18+'Quadro DRE Apresentação'!J38+'Quadro DRE Apresentação'!J78+'Quadro DRE Apresentação'!J102+'Quadro DRE Apresentação'!J121+'Quadro DRE Apresentação'!J143 -> #REF! | K93: =IFERROR(J93/H93-1," ") | L93: =IFERROR(J93/I93-1," ") | M93: ='Quadro DRE Apresentação'!M143+'Quadro DRE Apresentação'!M121+'Quadro DRE Apresentação'!M102+'Quadro DRE Apresentação'!M78+'Quadro DRE Apresentação'!M38+'Quadro DRE Apresentação'!M18 -> -12262.052 | N93: ='Quadro DRE Apresentação'!N143+'Quadro DRE Apresentação'!N121+'Quadro DRE Apresentação'!N102+'Quadro DRE Apresentação'!N78+'Quadro DRE Apresentação'!N38+'Quadro DRE Apresentação'!N18 -> -13348.37 | O93: ='Quadro DRE Apresentação'!O143+'Quadro DRE Apresentação'!O121+'Quadro DRE Apresentação'!O102+'Quadro DRE Apresentação'!O78+'Quadro DRE Apresentação'!O38+'Quadro DRE Apresentação'!O18 -> -13892.484 | P93: =IFERROR(O93/M93-1," ") -> 0.13296567 | Q93: =IFERROR(O93/N93-1," ") -> 0.040762594
B94: 13 - LUCRO LIQUIDO | C94: ='Quadro DRE Apresentação'!C144+'Quadro DRE Apresentação'!C122+'Quadro DRE Apresentação'!C103+'Quadro DRE Apresentação'!C79+'Quadro DRE Apresentação'!C39+'Quadro DRE Apresentação'!C19 -> 4160.0079 | D94: ='Quadro DRE Apresentação'!D19+'Quadro DRE Apresentação'!D39+'Quadro DRE Apresentação'!D79+'Quadro DRE Apresentação'!D103+'Quadro DRE Apresentação'!D122+'Quadro DRE Apresentação'!D144 -> 4447.0978 | E94: ='Quadro DRE Apresentação'!E19+'Quadro DRE Apresentação'!E39+'Quadro DRE Apresentação'!E79+'Quadro DRE Apresentação'!E103+'Quadro DRE Apresentação'!E122+'Quadro DRE Apresentação'!E144 -> 4945.5986 | F94: =IFERROR(E94/C94-1," ") -> 0.18884357 | G94: =IFERROR(E94/D94-1," ") -> 0.11209577 | H94: ='Quadro DRE Apresentação'!H144+'Quadro DRE Apresentação'!H122+'Quadro DRE Apresentação'!H103+'Quadro DRE Apresentação'!H79+'Quadro DRE Apresentação'!H39+'Quadro DRE Apresentação'!H19 -> #REF! | I94: ='Quadro DRE Apresentação'!I144+'Quadro DRE Apresentação'!I122+'Quadro DRE Apresentação'!I103+'Quadro DRE Apresentação'!I79+'Quadro DRE Apresentação'!I39+'Quadro DRE Apresentação'!I19 -> #REF! | J94: ='Quadro DRE Apresentação'!J19+'Quadro DRE Apresentação'!J39+'Quadro DRE Apresentação'!J79+'Quadro DRE Apresentação'!J103+'Quadro DRE Apresentação'!J122+'Quadro DRE Apresentação'!J144 -> #REF! | K94: =IFERROR(J94/H94-1," ") | L94: =IFERROR(J94/I94-1," ") | M94: ='Quadro DRE Apresentação'!M144+'Quadro DRE Apresentação'!M122+'Quadro DRE Apresentação'!M103+'Quadro DRE Apresentação'!M79+'Quadro DRE Apresentação'!M39+'Quadro DRE Apresentação'!M19 -> 52596.892 | N94: ='Quadro DRE Apresentação'!N144+'Quadro DRE Apresentação'!N122+'Quadro DRE Apresentação'!N103+'Quadro DRE Apresentação'!N79+'Quadro DRE Apresentação'!N39+'Quadro DRE Apresentação'!N19 -> 54276.078 | O94: ='Quadro DRE Apresentação'!O144+'Quadro DRE Apresentação'!O122+'Quadro DRE Apresentação'!O103+'Quadro DRE Apresentação'!O79+'Quadro DRE Apresentação'!O39+'Quadro DRE Apresentação'!O19 -> 57078.195 | P94: =IFERROR(O94/M94-1," ") -> 0.085200907 | Q94: =IFERROR(O94/N94-1," ") -> 0.051627104
B96: Margem EBITDA/ROL | C96: =IFERROR(C88/C84,0) -> 0.75440565 | D96: =D88/D84 -> 0.78029425 | E96: =E88/E84 -> 0.78689627 | H96: =IFERROR(H88/H84,0) -> 0 | I96: =I88/I84 -> #REF! | J96: =J88/J84 -> #REF! | M96: =IFERROR(M88/M84,0) -> 0.76932787 | N96: =N88/N84 -> 0.79678474 | O96: =O88/O84 -> 0.79845582
B98: Margem CMV/ROL | C98: =IFERROR(SUM('Quadro DRE Ritmo'!D200,'Quadro DRE Ritmo'!D221)/SUM('Quadro DRE Ritmo'!D220,'Quadro DRE Ritmo'!D199),0) -> 0 | D98: =IFERROR(SUM('Quadro DRE Ritmo'!F200,'Quadro DRE Ritmo'!F221)/SUM('Quadro DRE Ritmo'!F220,'Quadro DRE Ritmo'!F199),0) -> 0 | E98: =IFERROR(SUM('Quadro DRE Ritmo'!H200,'Quadro DRE Ritmo'!H221)/SUM('Quadro DRE Ritmo'!H220,'Quadro DRE Ritmo'!H199),0) -> 0 | H98: =IFERROR(SUM('Quadro DRE Ritmo'!N196,'Quadro DRE Ritmo'!N216)/SUM('Quadro DRE Ritmo'!N215,'Quadro DRE Ritmo'!N195),0) -> 0 | I98: =IFERROR(SUM('Quadro DRE Ritmo'!P196,'Quadro DRE Ritmo'!P216)/SUM('Quadro DRE Ritmo'!P215,'Quadro DRE Ritmo'!P195),0) -> 0 | J98: =IFERROR(SUM('Quadro DRE Ritmo'!R196,'Quadro DRE Ritmo'!R216)/SUM('Quadro DRE Ritmo'!R215,'Quadro DRE Ritmo'!R195),0) -> 0 | M98: =IFERROR(SUM('Quadro DRE Ritmo'!X196,'Quadro DRE Ritmo'!X216)/SUM('Quadro DRE Ritmo'!X215,'Quadro DRE Ritmo'!X195),0) -> 0 | N98: =IFERROR(SUM('Quadro DRE Ritmo'!Z196,'Quadro DRE Ritmo'!Z216)/SUM('Quadro DRE Ritmo'!Z215,'Quadro DRE Ritmo'!Z195),0) -> 0 | O98: =IFERROR(SUM('Quadro DRE Ritmo'!AB196,'Quadro DRE Ritmo'!AB216)/SUM('Quadro DRE Ritmo'!AB215,'Quadro DRE Ritmo'!AB195),0) -> 0
F100: CHECAR FÓRMULA % VARIAÇÃO

Sheet DRE DCL E D-ESPAÇO
A2: DRE DCL SHOPPING | B2: Junho | H2: Acumulado | N2: Acumulado
A3: R$ | B3: AA | C3: Meta | D3: Real | E3: % Meta | F3: % AA | H3: AA | I3: Meta | J3: Real | K3: % Meta | L3: % AA | N3: AA | O3: Meta | P3: Real | Q3: % Meta | R3: % AA
A4: FATURAMENTO BRUTO | B4: 929608.76 | C4: 1174461.2 | D4: 1189405 | E4: 0.11174566 | F4: 0.11722187 | H4: 5653608.6 | I4: 6676432.5 | J4: 7037306.9 | K4: 0.11174566 | L4: 0.11722187 | N4: 12163891 | O4: 13536552 | P4: 14158809 | Q4: 0.0090857894 | R4: 0.072327185
A5: DEDUÇÃO DE FATURAMENTO | B5: 51485.16 | C5: 74832.27 | D5: 62788.13 | E5: -0.17419989 | F5: -0.50831726 | H5: 323660.1 | I5: 430047.34 | J5: 509340.07 | K5: -0.17419989 | L5: -0.50831726 | N5: 799449.11 | O5: 879064.09 | P5: 945916 | Q5: -0.013432937 | R5: -0.41420301
A6: FATURAMENTO LÍQUIDO | B6: =B4-B5 -> 878123.6 | C6: =C4-C5 -> 1099628.9 | D6: =D4-D5 -> 1126616.9 | E6: =IF(ISERROR((D6/C6)-1),"",(D6/C6-1)) -> 0.024542761 | F6: =IF(ISERROR((D6/B6)-1),"",(D6/B6-1)) -> 0.28298209 | H6: =H4-H5 -> 5329948.5 | I6: =I4-I5 -> 6246385.1 | J6: =J4-J5 -> 6527966.8 | K6: =IF(ISERROR((J6/I6)-1),"",(J6/I6-1)) -> 0.04507914 | L6: =IF(ISERROR((J6/H6)-1),"",(J6/H6-1)) -> 0.22477108 | N6: =N4-N5 -> 11364441 | O6: =O4-O5 -> 12657488 | P6: =P4-P5+1 -> 13212894 | Q6: =IF(ISERROR((P6/O6)-1),"",(P6/O6-1)) -> 0.043879651 | R6: =IF(ISERROR((P6/N6)-1),"",(P6/N6-1)) -> 0.1626523
A7: DESPESAS OPERACIONAIS | B7: 416791.7 | C7: 418150 | D7: 355146.78 | E7: -0.085689292 | F7: -0.1459812 | H7: 2348976.3 | I7: 2575514.9 | J7: 2300515.2 | K7: -0.085689292 | L7: -0.1459812 | N7: 4739242.9 | O7: 4970717.4 | P7: 4615387 | Q7: -0.0071350911 | R7: -0.034523029
A8: EBITDA | B8: =B6-B7 -> 461331.9 | C8: =C6-C7 -> 681478.92 | D8: =D6-D7 -> 771470.07 | E8: =IF(ISERROR((D8-C8)/ABS(C8)),"",(D8-C8)/ABS(C8)) -> 0.13205273 | F8: =IF(ISERROR((D8-B8)/ABS(B8)),"",(D8-B8)/ABS(B8)) -> 0.67226691 | H8: =H6-H7-1 -> 2980971.1 | I8: =I6-I7+1 -> 3670871.2 | J8: =J6-J7 -> 4227451.6 | K8: =IF(ISERROR((J8/I8)-1),"",(J8/I8-1)) -> 0.15162078 | L8: =IF(ISERROR((J8/H8)-1),"",(J8/H8-1)) -> 0.41814577 | N8: =N6-N7 -> 6625198.5 | O8: =O6-O7 -> 7686770.4 | P8: =P6-P7 -> 8597507 | Q8: =IF(ISERROR((P8/O8)-1),"",(P8/O8-1)) -> 0.11848104 | R8: =IF(ISERROR((P8/N8)-1),"",(P8/N8-1)) -> 0.29769802
A9: DEPRECIAÇÃO / AMORTIZAÇÃO | B9: 89338.57 | C9: 107876.08 | D9: 109475.57 | E9: -0.0036024004 | F9: 0.12027966 | H9: 533013.63 | I9: 640387.48 | J9: 644183.6 | K9: -0.0036024004 | L9: 0.12027966 | N9: 1109968.9 | O9: 1313136 | P9: 1276077 | Q9: -0.0002811986 | R9: 0.19002251
A10: RESULTADO OPERACIONAL | B10: =B8-B9 -> 371993.33 | C10: =C8-C9 -> 573602.84 | D10: =D8-D9 -> 661994.5 | E10: =IF(ISERROR((D10-C10)/ABS(C10)),"",(D10-C10)/ABS(C10)) -> 0.15409906 | F10: =IF(ISERROR((D10-B10)/ABS(B10)),"",(D10-B10)/ABS(B10)) -> 0.77958702 | H10: =H8-H9+1 -> 2447958.5 | I10: =I8-I9 -> 3030483.8 | J10: =J8-J9 -> 3583268 | K10: =IF(ISERROR((J10/I10)-1),"",(J10/I10-1)) -> 0.18240792 | L10: =IF(ISERROR((J10/H10)-1),"",(J10/H10-1)) -> 0.46377808 | N10: =N8-N9 -> 5515229.7 | O10: =O8-O9 -> 6373634.4 | P10: =P8-P9 -> 7321430 | Q10: =IF(ISERROR((P10/O10)-1),"",(P10/O10-1)) -> 0.14870567 | R10: =IF(ISERROR((P10/N10)-1),"",(P10/N10-1)) -> 0.32749322
A11: OUTRAS RECEITAS E DESPESAS OPERACIONAIS | B11: -1613.58 | C11: -18417.53 | D11: 1966.24 | E11: 1.2684181 | F11: -0.65381916 | H11: 185126.51 | I11: -110505.18 | J11: 41969.85 | K11: 1.2684181 | L11: -0.65381916 | N11: 295055.27 | O11: -221010.36 | P11: 45386 | Q11: 0.10776343 | R11: -2.8734114
A12: RESULTADO FINANCEIRO LÍQUIDO | B12: =B13-B14 -> -43473.49 | C12: =C13-C14 -> -106561.21 | D12: =D13-D14 -> -63310.12 | E12: 0.19138804 | F12: 0.33190013 | H12: =H13-H14 -> -263891.06 | I12: =I13-I14 -> -661157.89 | J12: =J13-J14 -> -469360.39 | K12: 0.19138804 | L12: 0.33190013 | N12: -853328.75 | O12: -1291119.9 | P12: =P13-P14 -> -1035893.7 | Q12: 0.011838515 | R12: -0.33857504
A13: Receitas Financeiras | B13: 4729.04 | C13: 11717.42 | D13: 51684.24 | E13: 1.4742026 | F13: -0.4780046 | H13: 59212.48 | I13: 65505.01 | J13: 219615.04 | K13: 1.4742026 | L13: -0.4780046 | N13: 184397.23 | O13: 111130.91 | P13: 335585.23 | Q13: 0.071676971 | R13: -0.047642332
A14: Despesas Financeiras | B14: 48202.53 | C14: 118278.63 | D14: 114994.36 | E14: -0.09763484 | F14: -0.35956586 | H14: 323103.54 | I14: 726662.9 | J14: 688975.43 | K14: -0.09763484 | L14: -0.35956586 | N14: 1037726 | O14: 1402250.9 | P14: 1371478.9 | Q14: -0.0059481687 | R14: 0.29853325
A15: LUCRO ANTES DO IR / CSLL | B15: =B10+B11+B12 -> 326906.26 | C15: =C10+C11+C12 -> 448624.1 | D15: =D10+D11+D12 -> 600650.62 | E15: =IF(ISERROR((D15-C15)/ABS(C15)),"",(D15-C15)/ABS(C15)) -> 0.33887283 | F15: =IF(ISERROR((D15-B15)/ABS(B15)),"",(D15-B15)/ABS(B15)) -> 0.83737876 | H15: =H10+H11+H12 -> 2369194 | I15: =I10+I11+I12-1 -> 2258819.7 | J15: =J10+J11+J12 -> 3155877.5 | K15: =IF(ISERROR((J15/I15)-1),"",(J15/I15-1)) -> 0.39713563 | L15: =IF(ISERROR((J15/H15)-1),"",(J15/H15-1)) -> 0.3320469 | N15: =N10+N11+N12 -> 4956956.2 | O15: =O10+O11+O12 -> 4861504.1 | P15: =P10+P11+P12 -> 6330922.3 | Q15: =IF(ISERROR((P15/O15)-1),"",(P15/O15-1)) -> 0.30225587 | R15: =IF(ISERROR((P15/N15)-1),"",(P15/N15-1)) -> 0.27717939
A16: Provisão de IR e CSLL | B16: 99926.97 | C16: 127833 | D16: 152663.63 | E16: 0.15893095 | F16: 1.0272363 | H16: 618359.55 | I16: 769642.07 | J16: 850702.92 | K16: 0.15893095 | L16: 1.0272363 | N16: 1340736.8 | O16: 1462005.2 | P16: 1691415 | Q16: 0.012829119 | R16: 0.88475597
A17: LUCRO LÍQUIDO DO EXERCÍCIO | B17: =B15-B16 -> 226979.29 | C17: =C15-C16 -> 320791.1 | D17: =D15-D16 -> 447986.99 | E17: =IF(ISERROR((D17-C17)/ABS(C17)),"",(D17-C17)/ABS(C17)) -> 0.39650692 | F17: =IF(ISERROR((D17-B17)/ABS(B17)),"",(D17-B17)/ABS(B17)) -> 0.97369104 | H17: =H15-H16 -> 1750834.4 | I17: =I15-I16 -> 1489177.6 | J17: =J15-J16 -> 2305174.5 | K17: =IF(ISERROR((J17/I17)-1),"",(J17/I17-1)) -> 0.54795138 | L17: =IF(ISERROR((J17/H17)-1),"",(J17/H17-1)) -> 0.31661482 | N17: =N15-N16 -> 3616219.4 | O17: =O15-O16 -> 3399498.9 | P17: =P15-P16+P18 -> 4639507.3 | Q17: =IF(ISERROR((P17/O17)-1),"",(P17/O17-1)) -> 0.36476211 | R17: =IF(ISERROR((P17/N17)-1),"",(P17/N17-1)) -> 0.28297174
A18: Margem Líquida | B18: =IFERROR(B17/B6,"") -> 0.25848217 | C18: =IFERROR(C17/C6,"") -> 0.29172669 | D18: =IFERROR(D17/D6,"") -> 0.39763917 | K18: =IF(ISERROR((J18/I18)-1),"",(J18/I18-1)) | L18: =IF(ISERROR((J18/H18)-1),"",(J18/H18-1))
K19: =IF(ISERROR((J19/I19)-1),"",(J19/I19-1)) | L19: =IF(ISERROR((J19/H19)-1),"",(J19/H19-1))
K20: =IF(ISERROR((J20/I20)-1),"",(J20/I20-1)) | L20: =IF(ISERROR((J20/H20)-1),"",(J20/H20-1))
A21: DRE D-ESPAÇO | B21: Junho | H21: Acumulado | N21: Acumulado
A22: R$ | B22: AA | C22: Meta | D22: Real | E22: % Meta | F22: % AA | H22: AA | I22: Meta | J22: Real | K22: % Meta | L22: % AA | N22: AA | O22: Meta | P22: Real | Q22: % Meta | R22: % AA
A23: FATURAMENTO BRUTO | B23: 196495.05 | C23: 208347.97 | D23: 222852.59 | E23: 0.043840993 | F23: 0.12299698 | H23: 1164668.3 | I23: 1248604.1 | J23: 1294671.8 | K23: 0.043840993 | L23: 0.12299698 | N23: 2393662.9 | O23: 2504961.9 | P23: 2585272 | Q23: 0.0036196179 | R23: 0.028074669
A24: DEDUÇÃO DE FATURAMENTO | B24: 7172.07 | C24: 7604.7 | D24: 8134.12 | E24: 0.043840007 | F24: 0.12299573 | H24: 42910.42 | I24: 45574.04 | J24: 48365.33 | K24: 0.043840007 | L24: 0.12299573 | N24: 88628.1 | O24: 91431.1 | P24: 95472 | Q24: 0.0036195388 | R24: 0.028074599
A25: FATURAMENTO LÍQUIDO | B25: =B23-B24 -> 189322.98 | C25: =C23-C24 -> 200743.27 | D25: =D23-D24 -> 214718.47 | E25: =IF(ISERROR((D25/C25)-1),"",(D25/C25-1)) -> 0.069617278 | F25: =IF(ISERROR((D25/B25)-1),"",(D25/B25-1)) -> 0.13413844 | H25: =H23-H24 -> 1121757.9 | I25: =I23-I24 -> 1203030.1 | J25: =J23-J24 -> 1246306.4 | K25: =IF(ISERROR((J25/I25)-1),"",(J25/I25-1)) -> 0.035972817 | L25: =IF(ISERROR((J25/H25)-1),"",(J25/H25-1)) -> 0.11102979 | N25: =N23-N24 -> 2305034.8 | O25: =O23-O24 -> 2413530.8 | P25: =P23-P24 -> 2489800 | Q25: =IF(ISERROR((P25/O25)-1),"",(P25/O25-1)) -> 0.031600678 | R25: =IF(ISERROR((P25/N25)-1),"",(P25/N25-1)) -> 0.080157233
A26: DESPESAS OPERACIONAIS | B26: 81523.84 | C26: 93264.29 | D26: 92098.84 | E26: 0.1142908 | F26: 0.25302374 | H26: 507263.38 | I26: 579168.11 | J26: 543024.65 | K26: 0.1142908 | L26: 0.25302374 | N26: 1016373.3 | O26: 1111038.8 | P26: 1089092 | Q26: 0.0087850829 | R26: 0.079960216
A27: EBITDA | B27: =B25-B26 -> 107799.14 | C27: =C25-C26-1 -> 107477.98 | D27: =D25-D26 -> 122619.63 | E27: =IF(ISERROR((D27-C27)/ABS(C27)),"",(D27-C27)/ABS(C27)) -> 0.14088142 | F27: =IF(ISERROR((D27-B27)/ABS(B27)),"",(D27-B27)/ABS(B27)) -> 0.13748245 | H27: =H25-H26-1 -> 614493.52 | I27: =I25-I26 -> 623861.95 | J27: =J25-J26 -> 703281.79 | K27: =IF(ISERROR((J27/I27)-1),"",(J27/I27-1)) -> 0.12730355 | L27: =IF(ISERROR((J27/H27)-1),"",(J27/H27-1)) -> 0.14449016 | N27: =N25-N26 -> 1288661.5 | O27: =O25-O26 -> 1302492 | P27: =P25-P26 -> 1400708 | Q27: =IF(ISERROR((P27/O27)-1),"",(P27/O27-1)) -> 0.075406246 | R27: =IF(ISERROR((P27/N27)-1),"",(P27/N27-1)) -> 0.086947994
A28: DEPRECIAÇÃO / AMORTIZAÇÃO | B28: 4717.74 | C28: 5722.09 | D28: 5364.82 | E28: 0.015242387 | F28: 0.049786382 | H28: 28306.44 | I28: 33868.35 | J28: 32288.15 | K28: 0.015242387 | L28: 0.049786382 | N28: 57548.76 | O28: 68200.89 | P28: 66621 | Q28: 0.0010957779 | R28: 0.18369551
A29: RESULTADO OPERACIONAL | B29: =B27-B28 -> 103081.4 | C29: =C27-C28 -> 101755.89 | D29: =D27-D28 -> 117254.81 | E29: =IF(ISERROR((D29-C29)/ABS(C29)),"",(D29-C29)/ABS(C29)) -> 0.15231472 | F29: =IF(ISERROR((D29-B29)/ABS(B29)),"",(D29-B29)/ABS(B29)) -> 0.13749726 | H29: =H27-H28 -> 586187.08 | I29: =I27-I28 -> 589993.6 | J29: =J27-J28 -> 670993.64 | K29: =IF(ISERROR((J29/I29)-1),"",(J29/I29-1)) -> 0.13728969 | L29: =IF(ISERROR((J29/H29)-1),"",(J29/H29-1)) -> 0.1446749 | N29: =N27-N28 -> 1231112.7 | O29: =O27-O28 -> 1234291.1 | P29: =P27-P28 -> 1334087 | Q29: =IF(ISERROR((P29/O29)-1),"",(P29/O29-1)) -> 0.080852824 | R29: =IF(ISERROR((P29/N29)-1),"",(P29/N29-1)) -> 0.083643268
A30: OUTRAS RECEITAS E DESPESAS OPERACIONAIS | B30: 1971.07 | C30: 1723.2 | D30: 1546.65 | E30: -0.49939833 | F30: 2.12 | H30: 14781.76 | I30: 10515.12 | J30: 12689.6 | K30: -0.49939833 | L30: -0.51211449 | N30: 23884.54 | O30: 23808.09 | P30: 25983 | Q30: -0.04325131 | R30: 0.20863433
A31: RESULTADO FINANCEIRO LÍQUIDO | B31: =B32-B33 -> -16.28 | C31: =C32-C33 -> -881.76 | D31: =D32-D33 -> -1116.63 | E31: 48.84075 | F31: 1.2718477 | H31: =H32-H33 -> 3873.13 | I31: =I32-I33 -> -5598.99 | J31: =J32-J33 -> -2932.25 | K31: 47.84075 | L31: 1.2718477 | N31: =N32-N33 -> 2802.5 | O31: =O32-O33 -> -10980.86 | P31: =P32-P33 -> -8314.12 | Q31: 5.5562619 | R31: -0.83458911
A32: Receitas Financeiras | B32: 2048.2 | C32: 1550 | D32: 1967.12 | E32: 1.5725214 | F32: 0.52370899 | H32: 15608.76 | I32: 9300 | J32: 12903.49 | K32: 1.5725214 | L32: 0.52370899 | N32: 28142.4 | O32: 18600 | P32: 22203.49 | Q32: 0.13104345 | R32: -0.40136428
A33: Despesas Financeiras | B33: 2064.48 | C33: 2431.76 | D33: 3083.75 | E33: 0.21169118 | F33: 0.095874924 | H33: 11735.63 | I33: 14898.99 | J33: 15835.74 | K33: 0.21169118 | L33: 0.095874924 | N33: 25339.9 | O33: 29580.86 | P33: 30517.61 | Q33: 0.017576313 | R33: -0.054749222
A34: LUCRO ANTES DO IR / CSLL | B34: =B29+B30+B31+1 -> 105037.19 | C34: =C29+C30+C31 -> 102597.33 | D34: =D29+D30+D31 -> 117684.83 | E34: -0.0035704887 | F34: 0.025961589 | H34: =H29+H30+H31 -> 604841.97 | I34: =I29+I30+I31 -> 594909.73 | J34: =J29+J30+J31 -> 680750.99 | K34: -0.0035704887 | L34: 0.025961589 | N34: =N29+N30+N31 -> 1257799.8 | O34: =O29+O30+O31 -> 1247118.3 | P34: =P29+P30+P31-1 -> 1351754.9 | Q34: -0.00031663083 | R34: -0.032001214
A35: Provisão de IR e CSLL | B35: 20692.96 | C35: 21906.03 | D35: 23460.97 | E35: 0.11519403 | F35: 0.14379356 | H35: 124521.93 | I35: 131253.52 | J35: 137023.72 | K35: 0.11519403 | L35: 0.14379356 | N35: 253298.42 | O35: 263437.19 | P35: 272933 | Q35: 0.0095232055 | R35: -0.02055991
A36: LUCRO LÍQUIDO DO EXERCÍCIO | B36: =B34-B35 -> 84344.23 | C36: =C34-C35+1 -> 80692.3 | D36: =D34-D35 -> 94223.86 | E36: =IF(ISERROR((D36-C36)/ABS(C36)),"",(D36-C36)/ABS(C36)) -> 0.16769332 | F36: =IF(ISERROR((D36-B36)/ABS(B36)),"",(D36-B36)/ABS(B36)) -> 0.11713463 | H36: =H34-H35 -> 480320.04 | I36: =I34-I35 -> 463656.21 | J36: =J34-J35 -> 543727.27 | K36: =IF(ISERROR((J36/I36)-1),"",(J36/I36-1)) -> 0.17269489 | L36: =IF(ISERROR((J36/H36)-1),"",(J36/H36-1)) -> 0.13201038 | N36: =N34-N35 -> 1004501.3 | O36: =O34-O35 -> 983681.12 | P36: =P34-P35+1 -> 1078822.9 | Q36: =IF(ISERROR((P36/O36)-1),"",(P36/O36-1)) -> 0.096720124 | R36: =IF(ISERROR((P36/N36)-1),"",(P36/N36-1)) -> 0.073988503
K37: =IF(ISERROR((J37/I37)-1),"",(J37/I37-1)) | L37: =IF(ISERROR((J37/H37)-1),"",(J37/H37-1))
K39: =IF(ISERROR((J39-I39)/ABS(I39)),"",(J39-I39)/ABS(I39)) | L39: =IF(ISERROR((J39-H39)/ABS(H39)),"",(J39-H39)/ABS(H39))
K40: =IF(ISERROR((J40/I40)-1),"",(J40/I40-1)) | L40: =IF(ISERROR((J40/H40)-1),"",(J40/H40-1))
K41: =IF(ISERROR((J41/I41)-1),"",(J41/I41-1)) | L41: =IF(ISERROR((J41/H41)-1),"",(J41/H41-1))
K42: =IF(ISERROR((J42/I42)-1),"",(J42/I42-1)) | L42: =IF(ISERROR((J42/H42)-1),"",(J42/H42-1))
K43: =IF(ISERROR((J43/I43)-1),"",(J43/I43-1)) | L43: =IF(ISERROR((J43/H43)-1),"",(J43/H43-1))
K44: =IF(ISERROR((J44/I44)-1),"",(J44/I44-1)) | L44: =IF(ISERROR((J44/H44)-1),"",(J44/H44-1))
K46: =IF(ISERROR((J46-I46)/ABS(I46)),"",(J46-I46)/ABS(I46)) | L46: =IF(ISERROR((J46-H46)/ABS(H46)),"",(J46-H46)/ABS(H46))
K47: =IF(ISERROR((J47/I47)-1),"",(J47/I47-1)) | L47: =IF(ISERROR((J47/H47)-1),"",(J47/H47-1))
K49: =IF(ISERROR((J49-I49)/ABS(I49)),"",(J49-I49)/ABS(I49)) | L49: =IF(ISERROR((J49-H49)/ABS(H49)),"",(J49-H49)/ABS(H49))

Sheet BMFD_senha capita
